Workbook

Sheet Required changes checklist
A1: Change ID | B1: Name | C1: Description | D1: Done Date | E1: Notes
A2: 0 | B2: Change the file location | C2: Currently the master file is not in a secure location. Only a copy should be shared in the weely deck file. master should be kept in a separate location with limited access to just mobile marketing. | E2: Do you mean we need to keep the collated file in PPT Automated folder?
A3: 0A | B3: Several versions and tables of collated file exist. Need to decide on best way to collate.
A4: 1 | B4: Clean up data set formatting: | C4: Unhide all columns, and clean up, be careful not to remove old data that might be useful. Remove Blank rows, columns and move data around so newest row is at the very bottom of the sheet | E4: There will some columns which will be blank for recent times as the inputs for those column are not available for present times. For e.g. installs from Tapjoy / Liftoff etc
A5: 2 | B5: Remove Blank Rows and Columns | C5: Remove rows that are blank and columns, remove extra column titles. This will allow for easier utilization of the excel file.
A6: 3 | B6: Re-order data to decending order (newest week is at the bottom of the sheet) | I6: Wide to long format is "Ideal" however, LOE may not be worth the benefit. But note there are many benefits from this format.
A7: 5 | B7: Newest week should be added to the bottom of the sheet.
A8: 6 | B8: Some data will need to be on secondary tables, this data should deffinitely follow tidy data principles. (other strategies for data base design could also be implemented here. I'm open to ideas. But in the end, the data should be easily put into a tableau dashboard, or pivot table. | C8: I'm not sure it will be practicle to transform the overall metrics sheet from Wide to Long, However, the smaller pages should be Long not wide. See here for examples: https://byuidatascience.github.io/python4ds/tidy-data.html | E8: We need to list out which all data need to be present in the secondary table. From your POV I believe Installs to be surely present split by Week/Month and Channel | H8: TIDY DATA: WIDE TO LONG FORMAT
A9: 7 | B9: Change column names to match "Col Name Deffinitions" tab.
A10: 8 | B10: Create some light insights. | C10: Create pivot tables using the data with some common views that illustrates the weekly report but on a extended timeline (high level, not every detail needed) --- depending on how this works out, this may take place of the tableau dashboard. | E10: Decided that we will include a link to the event tracker instead in order to keep this project moving.
A11: 9 | B11: Connecting all the sheets in excel for continuity. (this can be done after piping is complete) | C11: Not sure what the best way is to do this, it may be that we add some of the over KPIs to the overall metrics sheet, or we connect using fiscal week as UID. | E11: Can be completed after Piping. (John can take up)
A12: 10 | B12: Ensure all automation pipelines are connected and working properly.
A13: 11 | B13: To accommodate the provison of Source in collated file | C13: Update: it was decided we will include a link to the event tracker. | E13: There has been lot of source changes, and we need to think on how best we can mention them in collated to avoid any future confusion
A14: 12 | B14: Restrict the formula driven columns so as to avoid any manuall update hampering the formula logic | E14: Have to check the possibility of Airflow to update the collated file if it is restricted for some of the columns

Sheet Col Name Deffinitions
A1: Location (Sheet Name) | B1: Name | C1: Data Source (include link when applicable) | D1: Purpose or description | E1: notes
A2: Primary KPIs | B2: UID_FiscalYR_FiscalWk
A3: Primary KPIs | B3: Fiscal_Year | C3: Net New | J3: Formatting Keys
A4: Primary KPIs | B4: Fiscal_Week | C4: Net New | J4: *All | K4: Further breakout exists
A5: Primary KPIs | B5: Calendar_Week_Start | C5: Net New
A6: Primary KPIs | B6: Calendar_Week_End | C6: Net New | D6: Anirban QC for all column headings
A7: Primary KPIs | B7: Installs_All | D7: Remove any extra spaces in the name (except for owned breakdown slide)
A8: Primary KPIs | B8: Installs_iOS | D8: App_Orders_All vs. App_Order_All
A9: Primary KPIs | B9: Installs_AND | D9: App_Order_All vs. Total_App_Orders
A10: Primary KPIs | B10: Installs_Organic_All
A11: Primary KPIs | B11: Installs_Organic_iOS
A12: Primary KPIs | B12: Installs_Organic_AND
A13: Primary KPIs | B13: Installs_Owned_All
A14: Primary KPIs | B14: Installs_Owned_iOS
A15: Primary KPIs | B15: Installs_Owned_AND
A16: Primary KPIs | B16: Installs_Paid_All
A17: Primary KPIs | B17: Installs_Paid_iOS
A18: Primary KPIs | B18: Installs_Paid_And
A19: Primary KPIs | B19: Installs_Paid_Atributed_All
A20: Primary KPIs | B20: Installs_Paid_Atributed_iOS
A21: Primary KPIs | B21: Installs_Paid_Atributed_And
... A78: Primary KPIs | B78: App_RetentionRate_30D_ReturningUser
A79: Primary KPIs | B79: App_WAU_New | C79: Same as weekly installs
A80: Primary KPIs | B80: App_WAU_Current | C80: <<Why is RR repeat and WAU current? Can the naming convention be aligned or is there a reason they are different?
A81: Primary KPIs | B81: App_WAU_Reactivated
A82: Primary KPIs | B82: App_WAU_Dormant_All
A83: Primary KPIs | B83: App_WAU_New_Dormant
A84: Primary KPIs | B84: App_WAU_Current_Dormant
A85: Primary KPIs | B85: App_WAU_Reactivated_Dormant
A86: Owned Breakdown
A87: paid Breakdown By Partner

Sheet QC Checklist
B2: Week | C2: ='Overall Metrics'!A1 -> 202505
B4: S.No. | C4: Sheet | D4: Description | E4: Status
B5: 1 | C5: Overall Metrics | D5: Attr. + Misatr. = Paid Overall | E5: =IFERROR(IF(VLOOKUP(C2,'Overall Metrics'!$F$7:$BK$1085,COLUMNS('Overall Metrics'!F7:N7),FALSE)=SUM(VLOOKUP(C2,'Overall Metrics'!$F$7:$BK$1085,COLUMNS('Overall Metrics'!F7:AV7),FALSE),VLOOKUP(C2,'Overall Metrics'!$F$7:$BK$1085,COLUMNS('Overall Metrics'!F7:AY7),FALSE)),"OK","Sum of attributed and misattributed does not equal paid overall."),"") -> OK
D6: Android: Org + Owned + Paid = Installs | E6: =IFERROR(IF(VLOOKUP(C2,'Overall Metrics'!$F$7:$BK$1085,COLUMNS('Overall Metrics'!F7:H7),FALSE)=SUM(VLOOKUP(C2,'Overall Metrics'!$F$7:$BK$1085,COLUMNS('Overall Metrics'!F7:AZ7),FALSE),VLOOKUP(C2,'Overall Metrics'!$F$7:$BK$1085,COLUMNS('Overall Metrics'!F7:BB7),FALSE),VLOOKUP(C2,'Overall Metrics'!$F$7:$BK$1085,COLUMNS('Overall Metrics'!F7:BD7),FALSE)),"OK","Sum of category installs does not equal all Android installs."),"") -> OK
D7: iOS: Org + Owned + Paid = Installs | E7: =IFERROR(IF(VLOOKUP(C2,'Overall Metrics'!$F$7:$BK$1085,COLUMNS('Overall Metrics'!F7:I7),FALSE)=SUM(VLOOKUP(C2,'Overall Metrics'!$F$7:$BK$1085,COLUMNS('Overall Metrics'!F7:BA7),FALSE),VLOOKUP(C2,'Overall Metrics'!$F$7:$BK$1085,COLUMNS('Overall Metrics'!F7:BC7),FALSE),VLOOKUP(C2,'Overall Metrics'!$F$7:$BK$1085,COLUMNS('Overall Metrics'!F7:BE7),FALSE)),"OK","Sum of category installs does not equal all iOS installs."),"") -> OK
D8: WoW Install Variance | E8: =IFERROR(IF(OR('Overall Metrics'!G1>=0.1,'Overall Metrics'!G1<=-0.1),"WoW variation in installs is more than 10% - debug / figure out the drivers", "No action."),"") -> No action.
D9: YoY Install Variance | E9: =IFERROR(IF(OR('Overall Metrics'!G2>=0.1,'Overall Metrics'!G2<=-0.1),"YoY variation in installs is more than 10% - debug / figure out the drivers", "No action."),"") -> No action.
D10: All Spend Equals sum of Android and iOS | E10: =IFERROR(IF(ABS(VLOOKUP(C2,'Overall Metrics'!$F$7:$BK$1085,COLUMNS('Overall Metrics'!$F:$W),FALSE)-SUM(VLOOKUP(C2,'Overall Metrics'!$F$7:$BK$1085,COLUMNS('Overall Metrics'!$F:$Z),FALSE),VLOOKUP(C2,'Overall Metrics'!$F$7:$BK$1085,COLUMNS('Overall Metrics'!$F:$AA),FALSE))<=1),"OK","Sum of Android and iOS does not equal all spend."),"") -> OK
B11: 2 | C11: Channel & Campaign Metrics | D11: Misattr. figures match on Overall Metrics and Channel & Campaign Sheet | E11: =IFERROR(IF(VLOOKUP(C2,'Overall Metrics'!$F$7:$BK$334,COLUMNS('Overall Metrics'!$F:$AY),FALSE)=VLOOKUP(C2,'Channel & Campaign Metrics'!$F$6:$BX$400,COLUMNS('Channel & Campaign Metrics'!$F:$Y),FALSE),"OK","There is a discrepancy."),"") -> OK
D12: WoW MAI Spend Variance | E12: =IFERROR(IF(OR('Channel & Campaign Metrics'!AR1>=0.1,'Channel & Campaign Metrics'!AR1<=-0.1),"More than 10% variation WoW. Debug / figure out the reason","OK"),"") -> OK
D13: WoW CPI Variance | E13: =IFERROR(IF(OR('Channel & Campaign Metrics'!BI1>=0.1,'Channel & Campaign Metrics'!BI1<=-0.1),"More than 10% variation WoW. Debug / figure out the reason","OK"),"") -> More than 10% variation WoW. Debug / figure out the reason
D14: WoW MAE Spend Variance | E14: =IFERROR(IF(OR('Channel & Campaign Metrics'!BN1>=0.1,'Channel & Campaign Metrics'!BN1<=-0.1),"More than 10% variation WoW. Debug / figure out the reason","OK"),"") -> OK
D15: WoW CPA Variance | E15: =IFERROR(IF(OR('Channel & Campaign Metrics'!BX1>=0.1,'Channel & Campaign Metrics'!BX1<=-0.1),"More than 10% variation WoW. Debug / figure out the reason","OK"),"") -> More than 10% variation WoW. Debug / figure out the reason
B16: 3 | C16: Glass Metrics | D16: App Orders - WoW Variation | E16: =IFERROR(IF(OR('Glass Metrics'!I1>=0.1,'Glass Metrics'!I1<=-0.1),"More than 10% variation WoW. Debug / figure out the reason.","OK"),"") -> More than 10% variation WoW. Debug / figure out the reason.
D17: App GMV - WoW Variation | E17: =IFERROR(IF(OR('Glass Metrics'!N1>=0.1,'Glass Metrics'!N1<=-0.1),"More than 10% variation WoW. Debug / figure out the reason.","OK"),"") -> More than 10% variation WoW. Debug / figure out the reason.
D18: App Visits - WoW Variation | E18: =IFERROR(IF(OR('Glass Metrics'!S1>=0.1,'Glass Metrics'!S1<=-0.1),"More than 10% variation WoW. Debug / figure out the reason.","OK"),"") -> More than 10% variation WoW. Debug / figure out the reason.
D19: App WAU - WoW Variation | E19: =IFERROR(IF(OR('Glass Metrics'!AC1>=0.1,'Glass Metrics'!AC1<=-0.1),"More than 10% variation WoW. Debug / figure out the reason.","OK"),"") -> More than 10% variation WoW. Debug / figure out the reason.
B20: 4 | C20: Lifecycle (Glass) | D20: Make sure WAU is close to active users in this sheet. | E20: =IFERROR(IF(ABS((VLOOKUP(C2,'Glass Metrics'!$F$7:$AU$400,COLUMNS('Glass Metrics'!F:AC),FALSE)/VLOOKUP(C2,'Lifecycle (Glass)'!F6:Y400,COLUMNS('Lifecycle (Glass)'!F:G),FALSE))-1)<=0.03,"OK","More than 3% discrepancy."),"") -> More than 3% discrepancy.
B21: 5 | C21: Customer Segmentation | D21: Customers count in Glass Metrics should match with Customer Segmentation | E21: =IFERROR(IF(ABS(VLOOKUP(C2,'Glass Metrics'!$F$7:$AU$400,COLUMNS('Glass Metrics'!F:X),FALSE)/VLOOKUP(C2,'Customer Segmentation'!$F$9:$R$400,COLUMNS('Customer Segmentation'!F:J),FALSE) - 1)<0.015,"OK","Numbers vary signficantly."),"") -> Numbers vary signficantly.

Sheet Overall Metrics
A1: =VLOOKUP(E1,E7:F319,2,FALSE) -> 202505 | D1: =E1-6 -> 45717 | E1: 45723 | F1: WoW | G1: =IFERROR(VLOOKUP($A$1,$F$7:G319,COLUMNS($F$7:G319),FALSE)/VLOOKUP(($A$1-IF(RIGHT($A$1,2)="01",48,1)),$F$7:G319,COLUMNS($F$7:G319),FALSE)-1,"NA") -> -0.065550208 | H1: =IFERROR(VLOOKUP($A$1,$F$7:H319,COLUMNS($F$7:H319),FALSE)/VLOOKUP(($A$1-IF(RIGHT($A$1,2)="01",48,1)),$F$7:H319,COLUMNS($F$7:H319),FALSE)-1,"NA") -> -0.18452123 | I1: =IFERROR(VLOOKUP($A$1,$F$7:I319,COLUMNS($F$7:I319),FALSE)/VLOOKUP(($A$1-IF(RIGHT($A$1,2)="01",48,1)),$F$7:I319,COLUMNS($F$7:I319),FALSE)-1,"NA") -> 0.01269585 | J1: =IFERROR(VLOOKUP($A$1,$F$7:J319,COLUMNS($F$7:J319),FALSE)-VLOOKUP(($A$1-IF(RIGHT($A$1,2)="01",48,1)),$F$7:J319,COLUMNS($F$7:J319),FALSE),"NA") -> -0.050513 | K1: =IFERROR(VLOOKUP($A$1,$F$7:K319,COLUMNS($F$7:K319),FALSE)-VLOOKUP(($A$1-IF(RIGHT($A$1,2)="01",48,1)),$F$7:K319,COLUMNS($F$7:K319),FALSE),"NA") -> 0.050513 | L1: =IFERROR(VLOOKUP($A$1,$F$7:L319,COLUMNS($F$7:L319),FALSE)/VLOOKUP(($A$1-IF(RIGHT($A$1,2)="01",48,1)),$F$7:L319,COLUMNS($F$7:L319),FALSE)-1,"NA") -> -0.065550208 | M1: =IFERROR(VLOOKUP($A$1,$F$7:M319,COLUMNS($F$7:M319),FALSE)/VLOOKUP(($A$1-IF(RIGHT($A$1,2)="01",48,1)),$F$7:M319,COLUMNS($F$7:M319),FALSE)-1,"NA") -> -0.14241588 | N1: =IFERROR(VLOOKUP($A$1,$F$7:N319,COLUMNS($F$7:N319),FALSE)/VLOOKUP(($A$1-IF(RIGHT($A$1,2)="01",48,1)),$F$7:N319,COLUMNS($F$7:N319),FALSE)-1,"NA") -> 0.12931912 | O1: =IFERROR(VLOOKUP($A$1,$F$7:O319,COLUMNS($F$7:O319),FALSE)-VLOOKUP(($A$1-IF(RIGHT($A$1,2)="01",48,1)),$F$7:O319,COLUMNS($F$7:O319),FALSE),"NA") -> 5.5511151e-17 | P1: =IFERROR(VLOOKUP($A$1,$F$7:P319,COLUMNS($F$7:P319),FALSE)-VLOOKUP(($A$1-IF(RIGHT($A$1,2)="01",48,1)),$F$7:P319,COLUMNS($F$7:P319),FALSE),"NA") -> -0.031460512 | Q1: =IFERROR(VLOOKUP($A$1,$F$7:Q319,COLUMNS($F$7:Q319),FALSE)-VLOOKUP(($A$1-IF(RIGHT($A$1,2)="01",48,1)),$F$7:Q319,COLUMNS($F$7:Q319),FALSE),"NA") -> 0.039327827 | R1: =IFERROR(VLOOKUP($A$1,$F$7:R319,COLUMNS($F$7:R319),FALSE)/VLOOKUP(($A$1-IF(RIGHT($A$1,2)="01",48,1)),$F$7:R319,COLUMNS($F$7:R319),FALSE)-1,"NA") -> 0.20210639 | S1: =IFERROR(VLOOKUP($A$1,$F$7:S319,COLUMNS($F$7:S319),FALSE)/VLOOKUP(($A$1-IF(RIGHT($A$1,2)="01",48,1)),$F$7:S319,COLUMNS($F$7:S319),FALSE)-1,"NA") -> -0.31147281 | T1: =IFERROR(VLOOKUP($A$1,$F$7:T319,COLUMNS($F$7:T319),FALSE)/VLOOKUP(($A$1-IF(RIGHT($A$1,2)="01",48,1)),$F$7:T319,COLUMNS($F$7:T319),FALSE)-1,"NA") -> 0.25157674 | U1: =IFERROR(VLOOKUP($A$1,$F$7:U319,COLUMNS($F$7:U319),FALSE)/VLOOKUP(($A$1-IF(RIGHT($A$1,2)="01",48,1)),$F$7:U319,COLUMNS($F$7:U319),FALSE)-1,"NA") -> 0.29700952 | V1: =IFERROR(VLOOKUP($A$1,$F$7:V319,COLUMNS($F$7:V319),FALSE)/VLOOKUP(($A$1-IF(RIGHT($A$1,2)="01",48,1)),$F$7:V319,COLUMNS($F$7:V319),FALSE)-1,"NA") -> 0.19622233 | W1: =IFERROR(VLOOKUP($A$1,$F$7:W319,COLUMNS($F$7:W319),FALSE)/VLOOKUP(($A$1-IF(RIGHT($A$1,2)="01",48,1)),$F$7:W319,COLUMNS($F$7:W319),FALSE)-1,"NA") -> -0.070066834 | X1: =IFERROR(VLOOKUP($A$1,$F$7:X319,COLUMNS($F$7:X319),FALSE)/VLOOKUP(($A$1-IF(RIGHT($A$1,2)="01",48,1)),$F$7:X319,COLUMNS($F$7:X319),FALSE)-1,"NA") -> -0.058532661 | Y1: =IFERROR(VLOOKUP($A$1,$F$7:Y319,COLUMNS($F$7:Y319),FALSE)/VLOOKUP(($A$1-IF(RIGHT($A$1,2)="01",48,1)),$F$7:Y319,COLUMNS($F$7:Y319),FALSE)-1,"NA") -> -0.094199355 | ... AF1: =IFERROR(VLOOKUP($A$1,$F$7:AF319,COLUMNS($F$7:AF319),FALSE)/VLOOKUP(($A$1-IF(RIGHT($A$1,2)="01",48,1)),$F$7:AF319,COLUMNS($F$7:AF319),FALSE)-1,"NA") -> 0.37882644 | AG1: =IFERROR(VLOOKUP($A$1,$F$7:AG319,COLUMNS($F$7:AG319),FALSE)-VLOOKUP(($A$1-IF(RIGHT($A$1,2)="01",48,1)),$F$7:AG319,COLUMNS($F$7:AG319),FALSE),"NA") -> -0.29773576 | AH1: =IFERROR(VLOOKUP($A$1,$F$7:AH319,COLUMNS($F$7:AH319),FALSE)/VLOOKUP(($A$1-IF(RIGHT($A$1,2)="01",48,1)),$F$7:AH319,COLUMNS($F$7:AH319),FALSE)-1,"NA") -> 0.0029550357 | AI1: =IFERROR(VLOOKUP($A$1,$F$7:AI319,COLUMNS($F$7:AI319),FALSE)-VLOOKUP(($A$1-IF(RIGHT($A$1,2)="01",48,1)),$F$7:AI319,COLUMNS($F$7:AI319),FALSE),"NA") -> 0.28064232 | AJ1: {=IFERROR(VLOOKUP($A$1-IF(RIGHT($A$1,2)="01",48,1),$F$7:AJ319,COLUMNS($F$7:AJ319),FALSE)-VLOOKUP(($A$1-IFERROR(_xlfn.IFS(RIGHT($A$1,2)="01",49,RIGHT($A$1,2)="02",49),2)),$F$7:AJ319,COLUMNS($F$7:AJ319),FALSE),"NA")} -> 0.034551406 | AK1: {=IFERROR(VLOOKUP($A$1-IF(RIGHT($A$1,2)="01",48,1),$F$7:AK319,COLUMNS($F$7:AK319),FALSE)-VLOOKUP(($A$1-IFERROR(_xlfn.IFS(RIGHT($A$1,2)="01",49,RIGHT($A$1,2)="02",49),2)),$F$7:AK319,COLUMNS($F$7:AK319),FALSE),"NA")} -> 0.47562074 | AL1: {=IFERROR(VLOOKUP($A$1-IF(RIGHT($A$1,2)="01",48,1),$F$7:AL319,COLUMNS($F$7:AL319),FALSE)-VLOOKUP(($A$1-IFERROR(_xlfn.IFS(RIGHT($A$1,2)="01",49,RIGHT($A$1,2)="02",49),2)),$F$7:AL319,COLUMNS($F$7:AL319),FALSE),"NA")} -> -0.46020713 | AM1: {=IFERROR(VLOOKUP($A$1-IF(RIGHT($A$1,2)="01",48,1),$F$7:AM319,COLUMNS($F$7:AM319),FALSE)/VLOOKUP(($A$1-IFERROR(_xlfn.IFS(RIGHT($A$1,2)="01",49,RIGHT($A$1,2)="02",49),2)),$F$7:AM319,COLUMNS($F$7:AM319),FALSE)-1,"NA")} -> 0.41287157 | AN1: {=IFERROR(VLOOKUP($A$1-IF(RIGHT($A$1,2)="01",48,1),$F$7:AN319,COLUMNS($F$7:AN319),FALSE)/VLOOKUP(($A$1-IFERROR(_xlfn.IFS(RIGHT($A$1,2)="01",49,RIGHT($A$1,2)="02",49),2)),$F$7:AN319,COLUMNS($F$7:AN319),FALSE)-1,"NA")} -> 0.39315551 | AO1: {=IFERROR(VLOOKUP($A$1-IF(RIGHT($A$1,2)="01",48,1),$F$7:AO319,COLUMNS($F$7:AO319),FALSE)-VLOOKUP(($A$1-IFERROR(_xlfn.IFS(RIGHT($A$1,2)="01",49,RIGHT($A$1,2)="02",49),2)),$F$7:AO319,COLUMNS($F$7:AO319),FALSE),"NA")} -> 0.034551406 | AP1: {=IFERROR(VLOOKUP($A$1-IFERROR(_xlfn.IFS(RIGHT($A$1,2)="01",51,RIGHT($A$1,2)="02",51,RIGHT($A$1,2)="03",51,RIGHT($A$1,2)="04",51),4),$F$7:AP319,COLUMNS($F$7:AP319),FALSE)-VLOOKUP(($A$1-IFERROR(_xlfn.IFS(RIGHT($A$1,2)="01",52,RIGHT($A$1,2)="02",52,RIGHT($A$1,2)="03",52,RIGHT($A$1,2)="04",52,RIGHT($A$1,2)="05",52),5)),$F$7:AP319,COLUMNS($F$7:AP319),FALSE),"NA")} -> 0.53688196 | AQ1: {=IFERROR(VLOOKUP($A$1-IFERROR(_xlfn.IFS(RIGHT($A$1,2)="01",51,RIGHT($A$1,2)="02",51,RIGHT($A$1,2)="03",51,RIGHT($A$1,2)="04",51),4),$F$7:AQ319,COLUMNS($F$7:AQ319),FALSE)-VLOOKUP(($A$1-IFERROR(_xlfn.IFS(RIGHT($A$1,2)="01",52,RIGHT($A$1,2)="02",52,RIGHT($A$1,2)="03",52,RIGHT($A$1,2)="04",52,RIGHT($A$1,2)="05",52),5)),$F$7:AQ319,COLUMNS($F$7:AQ319),FALSE),"NA")} -> 0.49505614 | AR1: {=IFERROR(VLOOKUP($A$1-IFERROR(_xlfn.IFS(RIGHT($A$1,2)="01",51,RIGHT($A$1,2)="02",51,RIGHT($A$1,2)="03",51,RIGHT($A$1,2)="04",51),4),$F$7:AR319,COLUMNS($F$7:AR319),FALSE)-VLOOKUP(($A$1-IFERROR(_xlfn.IFS(RIGHT($A$1,2)="01",52,RIGHT($A$1,2)="02",52,RIGHT($A$1,2)="03",52,RIGHT($A$1,2)="04",52,RIGHT($A$1,2)="05",52),5)),$F$7:AR319,COLUMNS($F$7:AR319),FALSE),"NA")} -> 0.57870777 | AS1: {=IFERROR(VLOOKUP($A$1-IFERROR(_xlfn.IFS(RIGHT($A$1,2)="01",51,RIGHT($A$1,2)="02",51,RIGHT($A$1,2)="03",51,RIGHT($A$1,2)="04",51),4),$F$7:AS319,COLUMNS($F$7:AS319),FALSE)-VLOOKUP(($A$1-IFERROR(_xlfn.IFS(RIGHT($A$1,2)="01",52,RIGHT($A$1,2)="02",52,RIGHT($A$1,2)="03",52,RIGHT($A$1,2)="04",52,RIGHT($A$1,2)="05",52),5)),$F$7:AS319,COLUMNS($F$7:AS319),FALSE),"NA")} -> 0.53688196 | AT1: =IFERROR(VLOOKUP($A$1,$F$7:AT319,COLUMNS($F$7:AT319),FALSE)/VLOOKUP(($A$1-IF(RIGHT($A$1,2)="01",48,1)),$F$7:AT319,COLUMNS($F$7:AT319),FALSE)-1,"NA") -> 0.20189424 | AU1: =IFERROR(VLOOKUP($A$1,$F$7:AU319,COLUMNS($F$7:AU319),FALSE)/VLOOKUP(($A$1-IF(RIGHT($A$1,2)="01",48,1)),$F$7:AU319,COLUMNS($F$7:AU319),FALSE)-1,"NA") -> 0.10597792 | AV1: =IFERROR(VLOOKUP($A$1,$F$7:AV319,COLUMNS($F$7:AV319),FALSE)/VLOOKUP(($A$1-IF(RIGHT($A$1,2)="01",48,1)),$F$7:AV319,COLUMNS($F$7:AV319),FALSE)-1,"NA") -> 0.12931912 | AW1: =IFERROR(VLOOKUP($A$1,$F$7:AW319,COLUMNS($F$7:AW319),FALSE)/VLOOKUP(($A$1-IF(RIGHT($A$1,2)="01",48,1)),$F$7:AW319,COLUMNS($F$7:AW319),FALSE)-1,"NA") -> 0.20189424 | AX1: =IFERROR(VLOOKUP($A$1,$F$7:AX319,COLUMNS($F$7:AX319),FALSE)/VLOOKUP(($A$1-IF(RIGHT($A$1,2)="01",48,1)),$F$7:AX319,COLUMNS($F$7:AX319),FALSE)-1,"NA") -> 0.10597792 | AY1: =IFERROR(VLOOKUP($A$1,$F$7:AY319,COLUMNS($F$7:AY319),FALSE)/VLOOKUP(($A$1-IF(RIGHT($A$1,2)="01",48,1)),$F$7:AY319,COLUMNS($F$7:AY319),FALSE)-1,"NA") -> 0.12931912 | AZ1: =IFERROR(VLOOKUP($A$1,$F$7:AZ319,COLUMNS($F$7:AZ319),FALSE)/VLOOKUP(($A$1-IF(RIGHT($A$1,2)="01",48,1)),$F$7:AZ319,COLUMNS($F$7:AZ319),FALSE)-1,"NA") -> -0.18452123 | BA1: =IFERROR(VLOOKUP($A$1,$F$7:BA319,COLUMNS($F$7:BA319),FALSE)/VLOOKUP(($A$1-IF(RIGHT($A$1,2)="01",48,1)),$F$7:BA319,COLUMNS($F$7:BA319),FALSE)-1,"NA") -> 0.01269585 | ... BE1: =IFERROR(VLOOKUP($A$1,$F$7:BE319,COLUMNS($F$7:BE319),FALSE)/VLOOKUP(($A$1-IF(RIGHT($A$1,2)="01",48,1)),$F$7:BE319,COLUMNS($F$7:BE319),FALSE)-1,"NA") -> 0.10597792 | BF1: =IFERROR(VLOOKUP($A$1,$F$7:BF319,COLUMNS($F$7:BF319),FALSE)-VLOOKUP(($A$1-IF(RIGHT($A$1,2)="01",48,1)),$F$7:BF319,COLUMNS($F$7:BF319),FALSE),"NA") -> -0.050513 | BG1: =IFERROR(VLOOKUP($A$1,$F$7:BG319,COLUMNS($F$7:BG319),FALSE)-VLOOKUP(($A$1-IF(RIGHT($A$1,2)="01",48,1)),$F$7:BG319,COLUMNS($F$7:BG319),FALSE),"NA") -> 0.050513 | BH1: =IFERROR(VLOOKUP($A$1,$F$7:BH319,COLUMNS($F$7:BH319),FALSE)-VLOOKUP(($A$1-IF(RIGHT($A$1,2)="01",48,1)),$F$7:BH319,COLUMNS($F$7:BH319),FALSE),"NA") -> -0.082130114 | BI1: =IFERROR(VLOOKUP($A$1,$F$7:BI319,COLUMNS($F$7:BI319),FALSE)-VLOOKUP(($A$1-IF(RIGHT($A$1,2)="01",48,1)),$F$7:BI319,COLUMNS($F$7:BI319),FALSE),"NA") -> 0.082124046 | BJ1: =IFERROR(VLOOKUP($A$1,$F$7:BJ319,COLUMNS($F$7:BJ319),FALSE)-VLOOKUP(($A$1-IF(RIGHT($A$1,2)="01",48,1)),$F$7:BJ319,COLUMNS($F$7:BJ319),FALSE),"NA") -> 0.015638742 | BK1: =IFERROR(VLOOKUP($A$1,$F$7:BK319,COLUMNS($F$7:BK319),FALSE)-VLOOKUP(($A$1-IF(RIGHT($A$1,2)="01",48,1)),$F$7:BK319,COLUMNS($F$7:BK319),FALSE),"NA") -> -0.015638742 | BL1: =IFERROR(VLOOKUP($A$1,$F$7:BL319,COLUMNS($F$7:BL319),FALSE)/VLOOKUP(($A$1-IF(RIGHT($A$1,2)="01",48,1)),$F$7:BL319,COLUMNS($F$7:BL319),FALSE)-1,"NA") -> 0.11650752 | BM1: =IFERROR(VLOOKUP($A$1,$F$7:BM319,COLUMNS($F$7:BM319),FALSE)/VLOOKUP(($A$1-IF(RIGHT($A$1,2)="01",48,1)),$F$7:BM319,COLUMNS($F$7:BM319),FALSE)-1,"NA") -> 0.27885643 | BN1: =IFERROR(VLOOKUP($A$1,$F$7:BN319,COLUMNS($F$7:BN319),FALSE)/VLOOKUP(($A$1-IF(RIGHT($A$1,2)="01",48,1)),$F$7:BN319,COLUMNS($F$7:BN319),FALSE)-1,"NA") -> 0.20307449
F2: YoY | G2: =IFERROR(VLOOKUP($A$1,$F$7:G319,COLUMNS($F$7:G319),FALSE)/VLOOKUP(($A$1-99),$F$7:G267,COLUMNS($F$7:G319),FALSE)-1,"NA") -> 0.061082969 | H2: =IFERROR(VLOOKUP($A$1,$F$7:H319,COLUMNS($F$7:H319),FALSE)/VLOOKUP(($A$1-99),$F$7:H319,COLUMNS($F$7:H319),FALSE)-1,"NA") -> -0.15347916 | I2: =IFERROR(VLOOKUP($A$1,$F$7:I319,COLUMNS($F$7:I319),FALSE)/VLOOKUP(($A$1-99),$F$7:I319,COLUMNS($F$7:I319),FALSE)-1,"NA") -> 0.2256036 | J2: =IFERROR(VLOOKUP($A$1,$F$7:J319,COLUMNS($F$7:J319),FALSE)-VLOOKUP(($A$1-99),$F$7:J319,COLUMNS($F$7:J319),FALSE),"NA") -> -0.087758673 | K2: =IFERROR(VLOOKUP($A$1,$F$7:K319,COLUMNS($F$7:K319),FALSE)-VLOOKUP(($A$1-99),$F$7:K319,COLUMNS($F$7:K319),FALSE),"NA") -> 0.087758673 | L2: =IFERROR(VLOOKUP($A$1,$F$7:L319,COLUMNS($F$7:L319),FALSE)/VLOOKUP(($A$1-99),$F$7:L319,COLUMNS($F$7:L319),FALSE)-1,"NA") -> 0.061082969 | M2: =IFERROR(VLOOKUP($A$1,$F$7:M319,COLUMNS($F$7:M319),FALSE)/VLOOKUP(($A$1-99),$F$7:M319,COLUMNS($F$7:M319),FALSE)-1,"NA") -> 0.061727727 | N2: =IFERROR(VLOOKUP($A$1,$F$7:N319,COLUMNS($F$7:N319),FALSE)/VLOOKUP(($A$1-99),$F$7:N319,COLUMNS($F$7:N319),FALSE)-1,"NA") -> 0.059843542 | O2: =IFERROR(VLOOKUP($A$1,$F$7:O319,COLUMNS($F$7:O319),FALSE)-VLOOKUP(($A$1-99),$F$7:O319,COLUMNS($F$7:O319),FALSE),"NA") -> 5.5511151e-17 | P2: =IFERROR(VLOOKUP($A$1,$F$7:P319,COLUMNS($F$7:P319),FALSE)-VLOOKUP(($A$1-99),$F$7:P319,COLUMNS($F$7:P319),FALSE),"NA") -> 0.00021315422 | Q2: =IFERROR(VLOOKUP($A$1,$F$7:Q319,COLUMNS($F$7:Q319),FALSE)-VLOOKUP(($A$1-99),$F$7:Q319,COLUMNS($F$7:Q319),FALSE),"NA") -> -0.00026653384 | R2: =IFERROR(VLOOKUP($A$1,$F$7:R319,COLUMNS($F$7:R319),FALSE)/VLOOKUP(($A$1-99),$F$7:R319,COLUMNS($F$7:R319),FALSE)-1,"NA") -> 0.028694205 | S2: =IFERROR(VLOOKUP($A$1,$F$7:S319,COLUMNS($F$7:S319),FALSE)/VLOOKUP(($A$1-99),$F$7:S319,COLUMNS($F$7:S319),FALSE)-1,"NA") -> -0.19808274 | T2: =IFERROR(VLOOKUP($A$1,$F$7:T319,COLUMNS($F$7:T319),FALSE)/VLOOKUP(($A$1-99),$F$7:T319,COLUMNS($F$7:T319),FALSE)-1,"NA") -> -0.12029185 | U2: =IFERROR(VLOOKUP($A$1,$F$7:U319,COLUMNS($F$7:U319),FALSE)/VLOOKUP(($A$1-99),$F$7:U319,COLUMNS($F$7:U319),FALSE)-1,"NA") -> -0.22562582 | V2: =IFERROR(VLOOKUP($A$1,$F$7:V319,COLUMNS($F$7:V319),FALSE)/VLOOKUP(($A$1-99),$F$7:V319,COLUMNS($F$7:V319),FALSE)-1,"NA") -> -0.13307501 | W2: =IFERROR(VLOOKUP($A$1,$F$7:W319,COLUMNS($F$7:W319),FALSE)/VLOOKUP(($A$1-99),$F$7:W319,COLUMNS($F$7:W319),FALSE)-1,"NA") -> 0.22851984 | X2: =IFERROR(VLOOKUP($A$1,$F$7:X319,COLUMNS($F$7:X319),FALSE)/VLOOKUP(($A$1-99),$F$7:X319,COLUMNS($F$7:X319),FALSE)-1,"NA") -> -0.079418141 | Y2: =IFERROR(VLOOKUP($A$1,$F$7:Y319,COLUMNS($F$7:Y319),FALSE)/VLOOKUP(($A$1-99),$F$7:Y319,COLUMNS($F$7:Y319),FALSE)-1,"NA") -> 3.5071297 | ... AF2: =IFERROR(VLOOKUP($A$1,$F$7:AF319,COLUMNS($F$7:AF319),FALSE)/VLOOKUP(($A$1-99),$F$7:AF319,COLUMNS($F$7:AF319),FALSE)-1,"NA") -> 0.48268919 | AG2: =IFERROR(VLOOKUP($A$1,$F$7:AG319,COLUMNS($F$7:AG319),FALSE)-VLOOKUP(($A$1-99),$F$7:AG319,COLUMNS($F$7:AG319),FALSE),"NA") -> -0.23174496 | AH2: =IFERROR(VLOOKUP($A$1,$F$7:AH319,COLUMNS($F$7:AH319),FALSE)/VLOOKUP(($A$1-99),$F$7:AH319,COLUMNS($F$7:AH319),FALSE)-1,"NA") -> 0.23220917 | AI2: =IFERROR(VLOOKUP($A$1,$F$7:AI319,COLUMNS($F$7:AI319),FALSE)-VLOOKUP(($A$1-99),$F$7:AI319,COLUMNS($F$7:AI319),FALSE),"NA") -> 0.88357987 | AJ2: =IFERROR(VLOOKUP(($A$1-IF(RIGHT($A$1,2)="01",48,1)),$F$7:AJ319,COLUMNS($F$7:AJ319),FALSE)-VLOOKUP(($A$1-IF(RIGHT($A$1,2)="01",100,100)),$F$7:AJ319,COLUMNS($F$7:AJ319),FALSE),"NA") -> -0.32647402 | AK2: =IFERROR(VLOOKUP(($A$1-IF(RIGHT($A$1,2)="01",48,1)),$F$7:AK319,COLUMNS($F$7:AK319),FALSE)-VLOOKUP(($A$1-IF(RIGHT($A$1,2)="01",100,100)),$F$7:AK319,COLUMNS($F$7:AK319),FALSE),"NA") -> -0.42592911 | AL2: =IFERROR(VLOOKUP(($A$1-IF(RIGHT($A$1,2)="01",48,1)),$F$7:AL319,COLUMNS($F$7:AL319),FALSE)-VLOOKUP(($A$1-IF(RIGHT($A$1,2)="01",100,100)),$F$7:AL319,COLUMNS($F$7:AL319),FALSE),"NA") -> -0.25597689 | AM2: =IFERROR(VLOOKUP(($A$1-IF(RIGHT($A$1,2)="01",48,1)),$F$7:AM319,COLUMNS($F$7:AM319),FALSE)/VLOOKUP(($A$1-IF(RIGHT($A$1,2)="01",100,100)),$F$7:AM319,COLUMNS($F$7:AM319),FALSE)-1,"NA") -> 0.81324141 | AN2: =IFERROR(VLOOKUP(($A$1-IF(RIGHT($A$1,2)="01",48,1)),$F$7:AN319,COLUMNS($F$7:AN319),FALSE)/VLOOKUP(($A$1-IF(RIGHT($A$1,2)="01",100,100)),$F$7:AN319,COLUMNS($F$7:AN319),FALSE)-1,"NA") -> 0.48150923 | AO2: =IFERROR(VLOOKUP(($A$1-IF(RIGHT($A$1,2)="01",48,1)),$F$7:AO319,COLUMNS($F$7:AO319),FALSE)-VLOOKUP(($A$1-IF(RIGHT($A$1,2)="01",100,100)),$F$7:AO319,COLUMNS($F$7:AO319),FALSE),"NA") -> -0.32647402 | AP2: =IFERROR(VLOOKUP(($A$1-IF(OR(RIGHT($A$1,2)="01",RIGHT($A$1,2)="02",RIGHT($A$1,2)="03",RIGHT($A$1,2)="04"),51,4)),$F$7:AP319,COLUMNS($F$7:AP319),FALSE)-VLOOKUP(($A$1-IF(OR(RIGHT($A$1,2)="01",RIGHT($A$1,2)="02",RIGHT($A$1,2)="03"),151,103)),$F$7:AP319,COLUMNS($F$7:AP319),FALSE),"NA") -> 0.66889427 | AQ2: =IFERROR(VLOOKUP(($A$1-IF(OR(RIGHT($A$1,2)="01",RIGHT($A$1,2)="02",RIGHT($A$1,2)="03",RIGHT($A$1,2)="04"),51,4)),$F$7:AQ319,COLUMNS($F$7:AQ319),FALSE)-VLOOKUP(($A$1-IF(OR(RIGHT($A$1,2)="01",RIGHT($A$1,2)="02",RIGHT($A$1,2)="03"),151,103)),$F$7:AQ319,COLUMNS($F$7:AQ319),FALSE),"NA") -> 0.2564579 | AR2: =IFERROR(VLOOKUP(($A$1-IF(OR(RIGHT($A$1,2)="01",RIGHT($A$1,2)="02",RIGHT($A$1,2)="03",RIGHT($A$1,2)="04"),51,4)),$F$7:AR319,COLUMNS($F$7:AR319),FALSE)-VLOOKUP(($A$1-IF(OR(RIGHT($A$1,2)="01",RIGHT($A$1,2)="02",RIGHT($A$1,2)="03"),151,103)),$F$7:AR319,COLUMNS($F$7:AR319),FALSE),"NA") -> 0.28981003 | AS2: =IFERROR(VLOOKUP(($A$1-IF(OR(RIGHT($A$1,2)="01",RIGHT($A$1,2)="02",RIGHT($A$1,2)="03",RIGHT($A$1,2)="04"),51,4)),$F$7:AS319,COLUMNS($F$7:AS319),FALSE)-VLOOKUP(($A$1-IF(OR(RIGHT($A$1,2)="01",RIGHT($A$1,2)="02",RIGHT($A$1,2)="03"),151,103)),$F$7:AS319,COLUMNS($F$7:AS319),FALSE),"NA") -> 0.66889427 | AT2: =IFERROR(VLOOKUP($A$1,$F$7:AT319,COLUMNS($F$7:AT319),FALSE)/VLOOKUP(($A$1-99),$F$7:AT319,COLUMNS($F$7:AT319),FALSE)-1,"NA") -> 0.50281259 | AU2: =IFERROR(VLOOKUP($A$1,$F$7:AU319,COLUMNS($F$7:AU319),FALSE)/VLOOKUP(($A$1-99),$F$7:AU319,COLUMNS($F$7:AU319),FALSE)-1,"NA") -> -0.039144338 | AV2: =IFERROR(VLOOKUP($A$1,$F$7:AV319,COLUMNS($F$7:AV319),FALSE)/VLOOKUP(($A$1-99),$F$7:AV319,COLUMNS($F$7:AV319),FALSE)-1,"NA") -> 0.059843542 | AW2: =IFERROR(VLOOKUP($A$1,$F$7:AW319,COLUMNS($F$7:AW319),FALSE)/VLOOKUP(($A$1-99),$F$7:AW319,COLUMNS($F$7:AW319),FALSE)-1,"NA") -> 0.50281259 | AX2: =IFERROR(VLOOKUP($A$1,$F$7:AX319,COLUMNS($F$7:AX319),FALSE)/VLOOKUP(($A$1-99),$F$7:AX319,COLUMNS($F$7:AX319),FALSE)-1,"NA") -> -0.039144338 | AY2: =IFERROR(VLOOKUP($A$1,$F$7:AY319,COLUMNS($F$7:AY319),FALSE)/VLOOKUP(($A$1-99),$F$7:AY319,COLUMNS($F$7:AY319),FALSE)-1,"NA") -> 0.059843542 | AZ2: =IFERROR(VLOOKUP($A$1,$F$7:AZ319,COLUMNS($F$7:AZ319),FALSE)/VLOOKUP(($A$1-99),$F$7:AZ319,COLUMNS($F$7:AZ319),FALSE)-1,"NA") -> -0.15347916 | BA2: =IFERROR(VLOOKUP($A$1,$F$7:BA319,COLUMNS($F$7:BA319),FALSE)/VLOOKUP(($A$1-99),$F$7:BA319,COLUMNS($F$7:BA319),FALSE)-1,"NA") -> 0.2256036 | ... BE2: =IFERROR(VLOOKUP($A$1,$F$7:BE319,COLUMNS($F$7:BE319),FALSE)/VLOOKUP(($A$1-99),$F$7:BE319,COLUMNS($F$7:BE319),FALSE)-1,"NA") -> -0.039144338 | BF2: =IFERROR(VLOOKUP($A$1,$F$7:BF319,COLUMNS($F$7:BF319),FALSE)-VLOOKUP(($A$1-99),$F$7:BF319,COLUMNS($F$7:BF319),FALSE),"NA") -> -0.087758673 | BG2: =IFERROR(VLOOKUP($A$1,$F$7:BG319,COLUMNS($F$7:BG319),FALSE)-VLOOKUP(($A$1-99),$F$7:BG319,COLUMNS($F$7:BG319),FALSE),"NA") -> 0.087758673 | BH2: =IFERROR(VLOOKUP($A$1,$F$7:BH319,COLUMNS($F$7:BH319),FALSE)-VLOOKUP(($A$1-99),$F$7:BH319,COLUMNS($F$7:BH319),FALSE),"NA") -> -0.21654122 | BI2: =IFERROR(VLOOKUP($A$1,$F$7:BI319,COLUMNS($F$7:BI319),FALSE)-VLOOKUP(($A$1-99),$F$7:BI319,COLUMNS($F$7:BI319),FALSE),"NA") -> 0.21654148 | BJ2: =IFERROR(VLOOKUP($A$1,$F$7:BJ319,COLUMNS($F$7:BJ319),FALSE)-VLOOKUP(($A$1-99),$F$7:BJ319,COLUMNS($F$7:BJ319),FALSE),"NA") -> 0.076339423 | BK2: =IFERROR(VLOOKUP($A$1,$F$7:BK319,COLUMNS($F$7:BK319),FALSE)-VLOOKUP(($A$1-99),$F$7:BK319,COLUMNS($F$7:BK319),FALSE),"NA") -> -0.076339423 | BL2: =IFERROR(VLOOKUP($A$1,$F$7:BL319,COLUMNS($F$7:BL319),FALSE)/VLOOKUP(($A$1-99),$F$7:BL319,COLUMNS($F$7:BL319),FALSE)-1,"NA") -> -0.028586596 | BM2: =IFERROR(VLOOKUP($A$1,$F$7:BM319,COLUMNS($F$7:BM319),FALSE)/VLOOKUP(($A$1-99),$F$7:BM319,COLUMNS($F$7:BM319),FALSE)-1,"NA") -> 0.56067791 | BN2: =IFERROR(VLOOKUP($A$1,$F$7:BN319,COLUMNS($F$7:BN319),FALSE)/VLOOKUP(($A$1-99),$F$7:BN319,COLUMNS($F$7:BN319),FALSE)-1,"NA") -> 0.23590681
F3: Primary Source | G3: (AppsFlyer) | H3: (AppsFlyer) | I3: (AppsFlyer) | J3: (Derived) | K3: (Derived) | L3: (AppsFlyer) | M3: (AppsFlyer) | N3: (AppsFlyer) | O3: (Derived) | P3: (Derived) | Q3: (Derived) | R3: (Linked) | S3: (Linked) | T3: (Derived) | U3: (Derived) | V3: (Derived) | W3: (Derived) | X3: (Linked) | Y3: (Linked) | Z3: (PubW) | AA3: (PubW) | AB3: (Linked - Amplitude) | AC3: (Linked - SOL_V) | AD3: (Linked - SOL_V) | AE3: (Linked - Adobe) | AF3: (Derived) | AG3: (Derived) | AH3: (Derived) | AI3: (Derived) | AJ3: (Derived) | AK3: (Amplitude) | AL3: (Amplitude) | AM3: (Amplitude) | AN3: (Amplitude) | AO3: (Derived) | AP3: (Derived) | AQ3: (Amplitude) | AR3: (Amplitude) | AS3: (Derived) | AT3: (AppsFlyer) | AU3: (AppsFlyer) | AV3: (Derived) | AW3: (Derived) | AX3: (Derived) | AY3: (Derived) | AZ3: (Derived) | BA3: (Derived) | BB3: (AppsFlyer) | BC3: (AppsFlyer) | BD3: (AppsFlyer) | BE3: (AppsFlyer) | BF3: (Derived) | BG3: (Derived) | BH3: (Derived) | BI3: (Derived) | BJ3: (Derived) | BK3: (Derived) | BL3: (Omniture) | BM3: (Omniture) | BN3: (Derived)
F4: Secondary Source | G4: (ST360) | H4: (ST360) | I4: (ST360) | L4: (ST360) | AK4: (Adjusted) | AO4: (Adjusted) | AQ4: (Adjusted) | AS4: (Adjusted)
A6: Fiscal_Year | B6: Fiscal_Week | C6: Fiscal_Quarter | D6: Calendar_Week_Start | E6: Calendar_Week_End | F6: Week_UID | G6: Installs_All | H6: Installs_ AND | I6: Installs_ iOS | J6: Installs_AND_Share | K6: Installs_iOS_Share | L6: Installs_ Organic_All | M6: Installs_ Owned_All | N6: Installs_Paid_All | O6: Installs_ Organic_Share | P6: Installs_ Owned_Share | Q6: Installs_Paid_Share | R6: Installs_ Forecast_All | S6: Installs_Plan_All_Rev | T6: Installs_Actual_All_YTD | U6: Installs_Forecast_All_YTD | V6: Installs_Plan_All_YTD_Rev | W6: Spend_All | X6: Spend_Paid_MAI | Y6: Spend_Paid_MAE | Z6: Spend_AND | AA6: Spend_iOS | AB6: App_WAU_All | AC6: App_Orders_All | AD6: App_Revenue_All | AE6: App_Visits_All | AF6: App_Session_per_User | AG6: App_ CvR_All | AH6: App_ AOV_All | AI6: Growth_ Index | AJ6: App_7D_RR_All | AK6: App_7D_RR_iOS | AL6: App_7D_RR_AND | AM6: 7D_RR_iOS_Installs | AN6: 7D_RR_AND_Installs | AO6: App_7D_RR_All_Estimate | AP6: App_30D_RR_All | AQ6: App_30D_RR_iOS | AR6: App_30D_RR_AND | AS6: App_30D_RR_All_Estimate | AT6: Installs_Paid_MAI_Attributed_AND | AU6: Installs_Paid_MAI_Attributed_iOS | AV6: Installs_Paid_MAI_Attributed_All | AW6: Installs_Paid_MAI_Misattributed_AND | AX6: Installs_Paid_MAI_Misattributed_iOS | AY6: Installs_Paid_MAI_Misattributed_All | AZ6: Installs_ Organic_AND | BA6: Installs_ Organic_iOS | BB6: Installs_ Owned_AND | BC6: Installs_ Owned_iOS | BD6: Installs_Paid_AND | BE6: Installs_Paid_iOS | BF6: Installs_Organic_AND_Share | BG6: Installs_Organic_iOS_Share | BH6: Installs_Owned_AND_Share | BI6: Installs_Owned_iOS_Share | BJ6: Installs_Paid_AND_Share | BK6: Installs_Paid_iOS_Share | BL6: InStore_ Sessions_iOS | BM6: InStore_ Sessions_AND | BN6: InStore_ Sessions_ALL
A7: =LEFT(F7,4)+1 -> 2021 | B7: =RIGHT(F7,2) -> 01 | C7: {=_xlfn.IFS(_xlfn.NUMBERVALUE(B7)<=13,"Q1",AND(_xlfn.NUMBERVALUE(B7)>13,_xlfn.NUMBERVALUE(B7)<=26),"Q2", AND(_xlfn.NUMBERVALUE(B7)>26,_xlfn.NUMBERVALUE(B7)<=39),"Q3",_xlfn.NUMBERVALUE(B7)>39,"Q4")} -> Q1 | D7: 43862 | E7: =D7+6 -> 43868 | F7: 202001 | G7: =SUM(H7:I7) -> 0 | J7: =IFERROR(H7/G7,0) -> 0 | K7: =IFERROR(I7/G7,0) -> 0 | O7: =IFERROR(L7/$G7,0) -> 0 | P7: =IFERROR(M7/$G7,0) -> 0 | Q7: =IFERROR(N7/$G7,0) -> 0 | R7: =Forecast!J2 -> 0 | S7: =Forecast!N2 -> 0 | T7: =IF(OR(RIGHT(F7,2) = "01",G7 = 0),G7,T6+G7) -> 0 | U7: =IF(RIGHT(F7,2)="01",R7,R7+U6) -> 0 | V7: =IF(RIGHT(F7,2)="01",S7,S7+V6) -> 0 | W7: =X7+Y7 -> 0 | X7: ='Channel & Campaign Metrics'!AR6 -> 0 | Y7: ='Channel & Campaign Metrics'!BS6 -> 0 | AB7: ='Glass Metrics'!AC7 -> 0 | AC7: ='Glass Metrics'!I7 -> 0 | AD7: ='Glass Metrics'!N7 -> 0 | AE7: ='Glass Metrics'!S7 -> 0 | AF7: =IFERROR(AE7/AB7,"") | AG7: =IFERROR(AC7/AE7,"") | AH7: =IFERROR(AD7/AC7,"") | AI7: =IFERROR(G7/AB7,"") | AO7: =AJ7 -> 0 | AS7: =AP7 -> 0 | AV7: =SUM(AT7:AU7) -> 0 | BN7: =SUM(BL7:BM7) -> 0
A8: =LEFT(F8,4)+1 -> 2021 | B8: =RIGHT(F8,2) -> 02 | C8: {=_xlfn.IFS(_xlfn.NUMBERVALUE(B8)<=13,"Q1",AND(_xlfn.NUMBERVALUE(B8)>13,_xlfn.NUMBERVALUE(B8)<=26),"Q2", AND(_xlfn.NUMBERVALUE(B8)>26,_xlfn.NUMBERVALUE(B8)<=39),"Q3",_xlfn.NUMBERVALUE(B8)>39,"Q4")} -> Q1 | D8: =E7+1 -> 43869 | E8: =D8+6 -> 43875 | F8: 202002 | G8: =SUM(H8:I8) -> 0 | J8: =IFERROR(H8/G8,0) -> 0 | K8: =IFERROR(I8/G8,0) -> 0 | O8: =IFERROR(L8/$G8,0) -> 0 | P8: =IFERROR(M8/$G8,0) -> 0 | Q8: =IFERROR(N8/$G8,0) -> 0 | R8: =Forecast!J3 -> 0 | S8: =Forecast!N3 -> 0 | T8: =IF(OR(RIGHT(F8,2) = "01",G8 = 0),G8,T7+G8) -> 0 | U8: =IF(RIGHT(F8,2)="01",R8,R8+U7) -> 0 | V8: =IF(RIGHT(F8,2)="01",S8,S8+V7) -> 0 | W8: =X8+Y8 -> 0 | X8: ='Channel & Campaign Metrics'!AR7 -> 0 | Y8: ='Channel & Campaign Metrics'!BS7 -> 0 | AB8: ='Glass Metrics'!AC8 -> 0 | AC8: ='Glass Metrics'!I8 -> 0 | AD8: ='Glass Metrics'!N8 -> 0 | AE8: ='Glass Metrics'!S8 -> 0 | AF8: =IFERROR(AE8/AB8,"") | AG8: =IFERROR(AC8/AE8,"") | AH8: =IFERROR(AD8/AC8,"") | AI8: =IFERROR(G8/AB8,"") | AO8: =AJ8 -> 0 | AS8: =AP8 -> 0 | AV8: =SUM(AT8:AU8) -> 0 | BN8: =SUM(BL8:BM8) -> 0
A9: =LEFT(F9,4)+1 -> 2021 | B9: =RIGHT(F9,2) -> 03 | C9: {=_xlfn.IFS(_xlfn.NUMBERVALUE(B9)<=13,"Q1",AND(_xlfn.NUMBERVALUE(B9)>13,_xlfn.NUMBERVALUE(B9)<=26),"Q2", AND(_xlfn.NUMBERVALUE(B9)>26,_xlfn.NUMBERVALUE(B9)<=39),"Q3",_xlfn.NUMBERVALUE(B9)>39,"Q4")} -> Q1 | D9: =E8+1 -> 43876 | E9: =D9+6 -> 43882 | F9: 202003 | G9: =SUM(H9:I9) -> 0 | J9: =IFERROR(H9/G9,0) -> 0 | K9: =IFERROR(I9/G9,0) -> 0 | O9: =IFERROR(L9/$G9,0) -> 0 | P9: =IFERROR(M9/$G9,0) -> 0 | Q9: =IFERROR(N9/$G9,0) -> 0 | R9: =Forecast!J4 -> 0 | S9: =Forecast!N4 -> 0 | T9: =IF(OR(RIGHT(F9,2) = "01",G9 = 0),G9,T8+G9) -> 0 | U9: =IF(RIGHT(F9,2)="01",R9,R9+U8) -> 0 | V9: =IF(RIGHT(F9,2)="01",S9,S9+V8) -> 0 | W9: =X9+Y9 -> 0 | X9: ='Channel & Campaign Metrics'!AR8 -> 0 | Y9: ='Channel & Campaign Metrics'!BS8 -> 0 | AB9: ='Glass Metrics'!AC9 -> 0 | AC9: ='Glass Metrics'!I9 -> 0 | AD9: ='Glass Metrics'!N9 -> 0 | AE9: ='Glass Metrics'!S9 -> 0 | AF9: =IFERROR(AE9/AB9,"") | AG9: =IFERROR(AC9/AE9,"") | AH9: =IFERROR(AD9/AC9,"") | AI9: =IFERROR(G9/AB9,"") | AO9: =AJ9 -> 0 | AS9: =AP9 -> 0 | AV9: =SUM(AT9:AU9) -> 0 | BN9: =SUM(BL9:BM9) -> 0
A10: =LEFT(F10,4)+1 -> 2021 | B10: =RIGHT(F10,2) -> 04 | C10: {=_xlfn.IFS(_xlfn.NUMBERVALUE(B10)<=13,"Q1",AND(_xlfn.NUMBERVALUE(B10)>13,_xlfn.NUMBERVALUE(B10)<=26),"Q2", AND(_xlfn.NUMBERVALUE(B10)>26,_xlfn.NUMBERVALUE(B10)<=39),"Q3",_xlfn.NUMBERVALUE(B10)>39,"Q4")} -> Q1 | D10: =E9+1 -> 43883 | E10: =D10+6 -> 43889 | F10: 202004 | G10: =SUM(H10:I10) -> 0 | J10: =IFERROR(H10/G10,0) -> 0 | K10: =IFERROR(I10/G10,0) -> 0 | O10: =IFERROR(L10/$G10,0) -> 0 | P10: =IFERROR(M10/$G10,0) -> 0 | Q10: =IFERROR(N10/$G10,0) -> 0 | R10: =Forecast!J5 -> 0 | S10: =Forecast!N5 -> 0 | T10: =IF(OR(RIGHT(F10,2) = "01",G10 = 0),G10,T9+G10) -> 0 | U10: =IF(RIGHT(F10,2)="01",R10,R10+U9) -> 0 | V10: =IF(RIGHT(F10,2)="01",S10,S10+V9) -> 0 | W10: =X10+Y10 -> 0 | X10: ='Channel & Campaign Metrics'!AR9 -> 0 | Y10: ='Channel & Campaign Metrics'!BS9 -> 0 | AB10: ='Glass Metrics'!AC10 -> 0 | AC10: ='Glass Metrics'!I10 -> 0 | AD10: ='Glass Metrics'!N10 -> 0 | AE10: ='Glass Metrics'!S10 -> 0 | AF10: =IFERROR(AE10/AB10,"") | AG10: =IFERROR(AC10/AE10,"") | AH10: =IFERROR(AD10/AC10,"") | AI10: =IFERROR(G10/AB10,"") | AO10: =AJ10 -> 0 | AS10: =AP10 -> 0 | AV10: =SUM(AT10:AU10) -> 0 | BN10: =SUM(BL10:BM10) -> 0
A11: =LEFT(F11,4)+1 -> 2021 | B11: =RIGHT(F11,2) -> 05 | C11: {=_xlfn.IFS(_xlfn.NUMBERVALUE(B11)<=13,"Q1",AND(_xlfn.NUMBERVALUE(B11)>13,_xlfn.NUMBERVALUE(B11)<=26),"Q2", AND(_xlfn.NUMBERVALUE(B11)>26,_xlfn.NUMBERVALUE(B11)<=39),"Q3",_xlfn.NUMBERVALUE(B11)>39,"Q4")} -> Q1 | D11: =E10+1 -> 43890 | E11: =D11+6 -> 43896 | F11: 202005 | G11: =SUM(H11:I11) -> 0 | J11: =IFERROR(H11/G11,0) -> 0 | K11: =IFERROR(I11/G11,0) -> 0 | O11: =IFERROR(L11/$G11,0) -> 0 | P11: =IFERROR(M11/$G11,0) -> 0 | Q11: =IFERROR(N11/$G11,0) -> 0 | R11: =Forecast!J6 -> 0 | S11: =Forecast!N6 -> 0 | T11: =IF(OR(RIGHT(F11,2) = "01",G11 = 0),G11,T10+G11) -> 0 | U11: =IF(RIGHT(F11,2)="01",R11,R11+U10) -> 0 | V11: =IF(RIGHT(F11,2)="01",S11,S11+V10) -> 0 | W11: =X11+Y11 -> 0 | X11: ='Channel & Campaign Metrics'!AR10 -> 0 | Y11: ='Channel & Campaign Metrics'!BS10 -> 0 | AB11: ='Glass Metrics'!AC11 -> 0 | AC11: ='Glass Metrics'!I11 -> 0 | AD11: ='Glass Metrics'!N11 -> 0 | AE11: ='Glass Metrics'!S11 -> 0 | AF11: =IFERROR(AE11/AB11,"") | AG11: =IFERROR(AC11/AE11,"") | AH11: =IFERROR(AD11/AC11,"") | AI11: =IFERROR(G11/AB11,"") | AO11: =AJ11 -> 0 | AS11: =AP11 -> 0 | AV11: =SUM(AT11:AU11) -> 0 | BN11: =SUM(BL11:BM11) -> 0
A12: =LEFT(F12,4)+1 -> 2021 | B12: =RIGHT(F12,2) -> 06 | C12: {=_xlfn.IFS(_xlfn.NUMBERVALUE(B12)<=13,"Q1",AND(_xlfn.NUMBERVALUE(B12)>13,_xlfn.NUMBERVALUE(B12)<=26),"Q2", AND(_xlfn.NUMBERVALUE(B12)>26,_xlfn.NUMBERVALUE(B12)<=39),"Q3",_xlfn.NUMBERVALUE(B12)>39,"Q4")} -> Q1 | D12: =E11+1 -> 43897 | E12: =D12+6 -> 43903 | F12: 202006 | G12: =SUM(H12:I12) -> 0 | J12: =IFERROR(H12/G12,0) -> 0 | K12: =IFERROR(I12/G12,0) -> 0 | O12: =IFERROR(L12/$G12,0) -> 0 | P12: =IFERROR(M12/$G12,0) -> 0 | Q12: =IFERROR(N12/$G12,0) -> 0 | R12: =Forecast!J7 -> 0 | S12: =Forecast!N7 -> 0 | T12: =IF(OR(RIGHT(F12,2) = "01",G12 = 0),G12,T11+G12) -> 0 | U12: =IF(RIGHT(F12,2)="01",R12,R12+U11) -> 0 | V12: =IF(RIGHT(F12,2)="01",S12,S12+V11) -> 0 | W12: =X12+Y12 -> 0 | X12: ='Channel & Campaign Metrics'!AR11 -> 0 | Y12: ='Channel & Campaign Metrics'!BS11 -> 0 | AB12: ='Glass Metrics'!AC12 -> 0 | AC12: ='Glass Metrics'!I12 -> 0 | AD12: ='Glass Metrics'!N12 -> 0 | AE12: ='Glass Metrics'!S12 -> 0 | AF12: =IFERROR(AE12/AB12,"") | AG12: =IFERROR(AC12/AE12,"") | AH12: =IFERROR(AD12/AC12,"") | AI12: =IFERROR(G12/AB12,"") | AO12: =AJ12 -> 0 | AS12: =AP12 -> 0 | AV12: =SUM(AT12:AU12) -> 0 | BN12: =SUM(BL12:BM12) -> 0
A13: =LEFT(F13,4)+1 -> 2021 | B13: =RIGHT(F13,2) -> 07 | C13: {=_xlfn.IFS(_xlfn.NUMBERVALUE(B13)<=13,"Q1",AND(_xlfn.NUMBERVALUE(B13)>13,_xlfn.NUMBERVALUE(B13)<=26),"Q2", AND(_xlfn.NUMBERVALUE(B13)>26,_xlfn.NUMBERVALUE(B13)<=39),"Q3",_xlfn.NUMBERVALUE(B13)>39,"Q4")} -> Q1 | D13: =E12+1 -> 43904 | E13: =D13+6 -> 43910 | F13: 202007 | G13: =SUM(H13:I13) -> 0 | J13: =IFERROR(H13/G13,0) -> 0 | K13: =IFERROR(I13/G13,0) -> 0 | O13: =IFERROR(L13/$G13,0) -> 0 | P13: =IFERROR(M13/$G13,0) -> 0 | Q13: =IFERROR(N13/$G13,0) -> 0 | R13: =Forecast!J8 -> 0 | S13: =Forecast!N8 -> 0 | T13: =IF(OR(RIGHT(F13,2) = "01",G13 = 0),G13,T12+G13) -> 0 | U13: =IF(RIGHT(F13,2)="01",R13,R13+U12) -> 0 | V13: =IF(RIGHT(F13,2)="01",S13,S13+V12) -> 0 | W13: =X13+Y13 -> 0 | X13: ='Channel & Campaign Metrics'!AR12 -> 0 | Y13: ='Channel & Campaign Metrics'!BS12 -> 0 | AB13: ='Glass Metrics'!AC13 -> 0 | AC13: ='Glass Metrics'!I13 -> 0 | AD13: ='Glass Metrics'!N13 -> 0 | AE13: ='Glass Metrics'!S13 -> 0 | AF13: =IFERROR(AE13/AB13,"") | AG13: =IFERROR(AC13/AE13,"") | AH13: =IFERROR(AD13/AC13,"") | AI13: =IFERROR(G13/AB13,"") | AO13: =AJ13 -> 0 | AS13: =AP13 -> 0 | AV13: =SUM(AT13:AU13) -> 0 | BN13: =SUM(BL13:BM13) -> 0
A14: =LEFT(F14,4)+1 -> 2021 | B14: =RIGHT(F14,2) -> 08 | C14: {=_xlfn.IFS(_xlfn.NUMBERVALUE(B14)<=13,"Q1",AND(_xlfn.NUMBERVALUE(B14)>13,_xlfn.NUMBERVALUE(B14)<=26),"Q2", AND(_xlfn.NUMBERVALUE(B14)>26,_xlfn.NUMBERVALUE(B14)<=39),"Q3",_xlfn.NUMBERVALUE(B14)>39,"Q4")} -> Q1 | D14: =E13+1 -> 43911 | E14: =D14+6 -> 43917 | F14: 202008 | G14: =SUM(H14:I14) -> 0 | J14: =IFERROR(H14/G14,0) -> 0 | K14: =IFERROR(I14/G14,0) -> 0 | O14: =IFERROR(L14/$G14,0) -> 0 | P14: =IFERROR(M14/$G14,0) -> 0 | Q14: =IFERROR(N14/$G14,0) -> 0 | R14: =Forecast!J9 -> 0 | S14: =Forecast!N9 -> 0 | T14: =IF(OR(RIGHT(F14,2) = "01",G14 = 0),G14,T13+G14) -> 0 | U14: =IF(RIGHT(F14,2)="01",R14,R14+U13) -> 0 | V14: =IF(RIGHT(F14,2)="01",S14,S14+V13) -> 0 | W14: =X14+Y14 -> 0 | X14: ='Channel & Campaign Metrics'!AR13 -> 0 | Y14: ='Channel & Campaign Metrics'!BS13 -> 0 | AB14: ='Glass Metrics'!AC14 -> 0 | AC14: ='Glass Metrics'!I14 -> 0 | AD14: ='Glass Metrics'!N14 -> 0 | AE14: ='Glass Metrics'!S14 -> 0 | AF14: =IFERROR(AE14/AB14,"") | AG14: =IFERROR(AC14/AE14,"") | AH14: =IFERROR(AD14/AC14,"") | AI14: =IFERROR(G14/AB14,"") | AO14: =AJ14 -> 0 | AS14: =AP14 -> 0 | AV14: =SUM(AT14:AU14) -> 0 | BN14: =SUM(BL14:BM14) -> 0
A15: =LEFT(F15,4)+1 -> 2021 | B15: =RIGHT(F15,2) -> 09 | C15: {=_xlfn.IFS(_xlfn.NUMBERVALUE(B15)<=13,"Q1",AND(_xlfn.NUMBERVALUE(B15)>13,_xlfn.NUMBERVALUE(B15)<=26),"Q2", AND(_xlfn.NUMBERVALUE(B15)>26,_xlfn.NUMBERVALUE(B15)<=39),"Q3",_xlfn.NUMBERVALUE(B15)>39,"Q4")} -> Q1 | D15: =E14+1 -> 43918 | E15: =D15+6 -> 43924 | F15: 202009 | G15: =SUM(H15:I15) -> 0 | J15: =IFERROR(H15/G15,0) -> 0 | K15: =IFERROR(I15/G15,0) -> 0 | O15: =IFERROR(L15/$G15,0) -> 0 | P15: =IFERROR(M15/$G15,0) -> 0 | Q15: =IFERROR(N15/$G15,0) -> 0 | R15: =Forecast!J10 -> 0 | S15: =Forecast!N10 -> 0 | T15: =IF(OR(RIGHT(F15,2) = "01",G15 = 0),G15,T14+G15) -> 0 | U15: =IF(RIGHT(F15,2)="01",R15,R15+U14) -> 0 | V15: =IF(RIGHT(F15,2)="01",S15,S15+V14) -> 0 | W15: =X15+Y15 -> 0 | X15: ='Channel & Campaign Metrics'!AR14 -> 0 | Y15: ='Channel & Campaign Metrics'!BS14 -> 0 | AB15: ='Glass Metrics'!AC15 -> 0 | AC15: ='Glass Metrics'!I15 -> 0 | AD15: ='Glass Metrics'!N15 -> 0 | AE15: ='Glass Metrics'!S15 -> 0 | AF15: =IFERROR(AE15/AB15,"") | AG15: =IFERROR(AC15/AE15,"") | AH15: =IFERROR(AD15/AC15,"") | AI15: =IFERROR(G15/AB15,"") | AO15: =AJ15 -> 0 | AS15: =AP15 -> 0 | AV15: =SUM(AT15:AU15) -> 0 | BN15: =SUM(BL15:BM15) -> 0
A16: =LEFT(F16,4)+1 -> 2021 | B16: =RIGHT(F16,2) -> 10 | C16: {=_xlfn.IFS(_xlfn.NUMBERVALUE(B16)<=13,"Q1",AND(_xlfn.NUMBERVALUE(B16)>13,_xlfn.NUMBERVALUE(B16)<=26),"Q2", AND(_xlfn.NUMBERVALUE(B16)>26,_xlfn.NUMBERVALUE(B16)<=39),"Q3",_xlfn.NUMBERVALUE(B16)>39,"Q4")} -> Q1 | D16: =E15+1 -> 43925 | E16: =D16+6 -> 43931 | F16: 202010 | G16: =SUM(H16:I16) -> 0 | J16: =IFERROR(H16/G16,0) -> 0 | K16: =IFERROR(I16/G16,0) -> 0 | O16: =IFERROR(L16/$G16,0) -> 0 | P16: =IFERROR(M16/$G16,0) -> 0 | Q16: =IFERROR(N16/$G16,0) -> 0 | R16: =Forecast!J11 -> 0 | S16: =Forecast!N11 -> 0 | T16: =IF(OR(RIGHT(F16,2) = "01",G16 = 0),G16,T15+G16) -> 0 | U16: =IF(RIGHT(F16,2)="01",R16,R16+U15) -> 0 | V16: =IF(RIGHT(F16,2)="01",S16,S16+V15) -> 0 | W16: =X16+Y16 -> 0 | X16: ='Channel & Campaign Metrics'!AR15 -> 0 | Y16: ='Channel & Campaign Metrics'!BS15 -> 0 | AB16: ='Glass Metrics'!AC16 -> 0 | AC16: ='Glass Metrics'!I16 -> 0 | AD16: ='Glass Metrics'!N16 -> 0 | AE16: ='Glass Metrics'!S16 -> 0 | AF16: =IFERROR(AE16/AB16,"") | AG16: =IFERROR(AC16/AE16,"") | AH16: =IFERROR(AD16/AC16,"") | AI16: =IFERROR(G16/AB16,"") | AO16: =AJ16 -> 0 | AS16: =AP16 -> 0 | AV16: =SUM(AT16:AU16) -> 0 | BN16: =SUM(BL16:BM16) -> 0
A17: =LEFT(F17,4)+1 -> 2021 | B17: =RIGHT(F17,2) -> 11 | C17: {=_xlfn.IFS(_xlfn.NUMBERVALUE(B17)<=13,"Q1",AND(_xlfn.NUMBERVALUE(B17)>13,_xlfn.NUMBERVALUE(B17)<=26),"Q2", AND(_xlfn.NUMBERVALUE(B17)>26,_xlfn.NUMBERVALUE(B17)<=39),"Q3",_xlfn.NUMBERVALUE(B17)>39,"Q4")} -> Q1 | D17: =E16+1 -> 43932 | E17: =D17+6 -> 43938 | F17: 202011 | G17: =SUM(H17:I17) -> 0 | J17: =IFERROR(H17/G17,0) -> 0 | K17: =IFERROR(I17/G17,0) -> 0 | O17: =IFERROR(L17/$G17,0) -> 0 | P17: =IFERROR(M17/$G17,0) -> 0 | Q17: =IFERROR(N17/$G17,0) -> 0 | R17: =Forecast!J12 -> 0 | S17: =Forecast!N12 -> 0 | T17: =IF(OR(RIGHT(F17,2) = "01",G17 = 0),G17,T16+G17) -> 0 | U17: =IF(RIGHT(F17,2)="01",R17,R17+U16) -> 0 | V17: =IF(RIGHT(F17,2)="01",S17,S17+V16) -> 0 | W17: =X17+Y17 -> 0 | X17: ='Channel & Campaign Metrics'!AR16 -> 0 | Y17: ='Channel & Campaign Metrics'!BS16 -> 0 | AB17: ='Glass Metrics'!AC17 -> 0 | AC17: ='Glass Metrics'!I17 -> 0 | AD17: ='Glass Metrics'!N17 -> 0 | AE17: ='Glass Metrics'!S17 -> 0 | AF17: =IFERROR(AE17/AB17,"") | AG17: =IFERROR(AC17/AE17,"") | AH17: =IFERROR(AD17/AC17,"") | AI17: =IFERROR(G17/AB17,"") | AO17: =AJ17 -> 0 | AS17: =AP17 -> 0 | AV17: =SUM(AT17:AU17) -> 0 | BN17: =SUM(BL17:BM17) -> 0
A18: =LEFT(F18,4)+1 -> 2021 | B18: =RIGHT(F18,2) -> 12 | C18: {=_xlfn.IFS(_xlfn.NUMBERVALUE(B18)<=13,"Q1",AND(_xlfn.NUMBERVALUE(B18)>13,_xlfn.NUMBERVALUE(B18)<=26),"Q2", AND(_xlfn.NUMBERVALUE(B18)>26,_xlfn.NUMBERVALUE(B18)<=39),"Q3",_xlfn.NUMBERVALUE(B18)>39,"Q4")} -> Q1 | D18: =E17+1 -> 43939 | E18: =D18+6 -> 43945 | F18: 202012 | G18: =SUM(H18:I18) -> 0 | J18: =IFERROR(H18/G18,0) -> 0 | K18: =IFERROR(I18/G18,0) -> 0 | O18: =IFERROR(L18/$G18,0) -> 0 | P18: =IFERROR(M18/$G18,0) -> 0 | Q18: =IFERROR(N18/$G18,0) -> 0 | R18: =Forecast!J13 -> 0 | S18: =Forecast!N13 -> 0 | T18: =IF(OR(RIGHT(F18,2) = "01",G18 = 0),G18,T17+G18) -> 0 | U18: =IF(RIGHT(F18,2)="01",R18,R18+U17) -> 0 | V18: =IF(RIGHT(F18,2)="01",S18,S18+V17) -> 0 | W18: =X18+Y18 -> 0 | X18: ='Channel & Campaign Metrics'!AR17 -> 0 | Y18: ='Channel & Campaign Metrics'!BS17 -> 0 | AB18: ='Glass Metrics'!AC18 -> 0 | AC18: ='Glass Metrics'!I18 -> 0 | AD18: ='Glass Metrics'!N18 -> 0 | AE18: ='Glass Metrics'!S18 -> 0 | AF18: =IFERROR(AE18/AB18,"") | AG18: =IFERROR(AC18/AE18,"") | AH18: =IFERROR(AD18/AC18,"") | AI18: =IFERROR(G18/AB18,"") | AO18: =AJ18 -> 0 | AS18: =AP18 -> 0 | AV18: =SUM(AT18:AU18) -> 0 | BN18: =SUM(BL18:BM18) -> 0
A19: =LEFT(F19,4)+1 -> 2021 | B19: =RIGHT(F19,2) -> 13 | C19: {=_xlfn.IFS(_xlfn.NUMBERVALUE(B19)<=13,"Q1",AND(_xlfn.NUMBERVALUE(B19)>13,_xlfn.NUMBERVALUE(B19)<=26),"Q2", AND(_xlfn.NUMBERVALUE(B19)>26,_xlfn.NUMBERVALUE(B19)<=39),"Q3",_xlfn.NUMBERVALUE(B19)>39,"Q4")} -> Q1 | D19: =E18+1 -> 43946 | E19: =D19+6 -> 43952 | F19: 202013 | G19: =SUM(H19:I19) -> 0 | J19: =IFERROR(H19/G19,0) -> 0 | K19: =IFERROR(I19/G19,0) -> 0 | O19: =IFERROR(L19/$G19,0) -> 0 | P19: =IFERROR(M19/$G19,0) -> 0 | Q19: =IFERROR(N19/$G19,0) -> 0 | R19: =Forecast!J14 -> 0 | S19: =Forecast!N14 -> 0 | T19: =IF(OR(RIGHT(F19,2) = "01",G19 = 0),G19,T18+G19) -> 0 | U19: =IF(RIGHT(F19,2)="01",R19,R19+U18) -> 0 | V19: =IF(RIGHT(F19,2)="01",S19,S19+V18) -> 0 | W19: =X19+Y19 -> 0 | X19: ='Channel & Campaign Metrics'!AR18 -> 0 | Y19: ='Channel & Campaign Metrics'!BS18 -> 0 | AB19: ='Glass Metrics'!AC19 -> 0 | AC19: ='Glass Metrics'!I19 -> 0 | AD19: ='Glass Metrics'!N19 -> 0 | AE19: ='Glass Metrics'!S19 -> 0 | AF19: =IFERROR(AE19/AB19,"") | AG19: =IFERROR(AC19/AE19,"") | AH19: =IFERROR(AD19/AC19,"") | AI19: =IFERROR(G19/AB19,"") | AO19: =AJ19 -> 0 | AS19: =AP19 -> 0 | AV19: =SUM(AT19:AU19) -> 0 | BN19: =SUM(BL19:BM19) -> 0
... A58: =LEFT(F58,4)+1 -> 2021 | B58: =RIGHT(F58,2) -> 52 | C58: {=_xlfn.IFS(_xlfn.NUMBERVALUE(B58)<=13,"Q1",AND(_xlfn.NUMBERVALUE(B58)>13,_xlfn.NUMBERVALUE(B58)<=26),"Q2", AND(_xlfn.NUMBERVALUE(B58)>26,_xlfn.NUMBERVALUE(B58)<=39),"Q3",_xlfn.NUMBERVALUE(B58)>39,"Q4")} -> Q4 | D58: =E57+1 -> 44219 | E58: =D58+6 -> 44225 | F58: 202052 | G58: =SUM(H58:I58) -> 0 | J58: =IFERROR(H58/G58,0) -> 0 | K58: =IFERROR(I58/G58,0) -> 0 | O58: =IFERROR(L58/$G58,0) -> 0 | P58: =IFERROR(M58/$G58,0) -> 0 | Q58: =IFERROR(N58/$G58,0) -> 0 | R58: =Forecast!J53 -> 0 | S58: =Forecast!N53 -> 0 | T58: =IF(OR(RIGHT(F58,2) = "01",G58 = 0),G58,T57+G58) -> 0 | U58: =IF(RIGHT(F58,2)="01",R58,R58+U57) -> 0 | V58: =IF(RIGHT(F58,2)="01",S58,S58+V57) -> 0 | W58: =X58+Y58 -> 0 | X58: ='Channel & Campaign Metrics'!AR57 -> 0 | Y58: ='Channel & Campaign Metrics'!BS57 -> 0 | AB58: ='Glass Metrics'!AC58 -> 0 | AC58: ='Glass Metrics'!I58 -> 0 | AD58: ='Glass Metrics'!N58 -> 0 | AE58: ='Glass Metrics'!S58 -> 0 | AF58: =IFERROR(AE58/AB58,"") | AG58: =IFERROR(AC58/AE58,"") | AH58: =IFERROR(AD58/AC58,"") | AI58: =IFERROR(G58/AB58,"") | AO58: =AJ58 -> 0 | AS58: =AP58 -> 0 | AV58: =SUM(AT58:AU58) -> 0 | BN58: =SUM(BL58:BM58) -> 0
A59: =LEFT(F59,4)+1 -> 2022 | B59: =RIGHT(F59,2) -> 01 | C59: {=_xlfn.IFS(_xlfn.NUMBERVALUE(B59)<=13,"Q1",AND(_xlfn.NUMBERVALUE(B59)>13,_xlfn.NUMBERVALUE(B59)<=26),"Q2", AND(_xlfn.NUMBERVALUE(B59)>26,_xlfn.NUMBERVALUE(B59)<=39),"Q3",_xlfn.NUMBERVALUE(B59)>39,"Q4")} -> Q1 | D59: =E58+1 -> 44226 | E59: =D59+6 -> 44232 | F59: 202101 | G59: =SUM(H59:I59) -> 0 | J59: =IFERROR(H59/G59,0) -> 0 | K59: =IFERROR(I59/G59,0) -> 0 | O59: =IFERROR(L59/$G59,0) -> 0 | P59: =IFERROR(M59/$G59,0) -> 0 | Q59: =IFERROR(N59/$G59,0) -> 0 | R59: =Forecast!J54 -> 0 | S59: =Forecast!N54 -> 0 | T59: =IF(OR(RIGHT(F59,2) = "01",G59 = 0),G59,T58+G59) -> 0 | U59: =IF(RIGHT(F59,2)="01",R59,R59+U58) -> 0 | V59: =IF(RIGHT(F59,2)="01",S59,S59+V58) -> 0 | W59: =X59+Y59 -> 0 | X59: ='Channel & Campaign Metrics'!AR58 -> 0 | Y59: ='Channel & Campaign Metrics'!BS58 -> 0 | AB59: ='Glass Metrics'!AC59 -> 0 | AC59: ='Glass Metrics'!I59 -> 0 | AD59: ='Glass Metrics'!N59 -> 0 | AE59: ='Glass Metrics'!S59 -> 0 | AF59: =IFERROR(AE59/AB59,"") | AG59: =IFERROR(AC59/AE59,"") | AH59: =IFERROR(AD59/AC59,"") | AI59: =IFERROR(G59/AB59,"") | AJ59: =IFERROR(((AK59*AM59)+(AL59*AN59))/(AM59+AN59),"") | AO59: =IFERROR(((AM59*(AK59+0.1))+(AN59*AL59))/(AM59+AN59),"") | AS59: =IFERROR(((AM59*(AQ59+0.15))+(AN59*AR59))/(AM59+AN59),"") | AV59: =SUM(AT59:AU59) -> 0 | AZ59: =H59-(BB59+BD59) -> 0 | BA59: =I59-(BC59+BE59) -> 0 | BF59: =IFERROR(AZ59/L59,"-") -> - | BG59: =IFERROR(BA59/L59,"-") -> - | BH59: =IFERROR(BB59/M59,"-") -> - | BI59: =IFERROR(BC59/M59,"-") -> - | BJ59: =IFERROR(BD59/N59,"-") -> - | BK59: =IFERROR(BE59/N59,"-") -> - | BN59: =SUM(BL59:BM59) -> 0
A60: =LEFT(F60,4)+1 -> 2022 | B60: =RIGHT(F60,2) -> 02 | C60: {=_xlfn.IFS(_xlfn.NUMBERVALUE(B60)<=13,"Q1",AND(_xlfn.NUMBERVALUE(B60)>13,_xlfn.NUMBERVALUE(B60)<=26),"Q2", AND(_xlfn.NUMBERVALUE(B60)>26,_xlfn.NUMBERVALUE(B60)<=39),"Q3",_xlfn.NUMBERVALUE(B60)>39,"Q4")} -> Q1 | D60: =E59+1 -> 44233 | E60: =D60+6 -> 44239 | F60: 202102 | G60: =SUM(H60:I60) -> 0 | J60: =IFERROR(H60/G60,0) -> 0 | K60: =IFERROR(I60/G60,0) -> 0 | O60: =IFERROR(L60/$G60,0) -> 0 | P60: =IFERROR(M60/$G60,0) -> 0 | Q60: =IFERROR(N60/$G60,0) -> 0 | R60: =Forecast!J55 -> 0 | S60: =Forecast!N55 -> 0 | T60: =IF(OR(RIGHT(F60,2) = "01",G60 = 0),G60,T59+G60) -> 0 | U60: =IF(RIGHT(F60,2)="01",R60,R60+U59) -> 0 | V60: =IF(RIGHT(F60,2)="01",S60,S60+V59) -> 0 | W60: =X60+Y60 -> 0 | X60: ='Channel & Campaign Metrics'!AR59 -> 0 | Y60: ='Channel & Campaign Metrics'!BS59 -> 0 | AB60: ='Glass Metrics'!AC60 -> 0 | AC60: ='Glass Metrics'!I60 -> 0 | AD60: ='Glass Metrics'!N60 -> 0 | AE60: ='Glass Metrics'!S60 -> 0 | AF60: =IFERROR(AE60/AB60,"") | AG60: =IFERROR(AC60/AE60,"") | AH60: =IFERROR(AD60/AC60,"") | AI60: =IFERROR(G60/AB60,"") | AJ60: =IFERROR(((AK60*AM60)+(AL60*AN60))/(AM60+AN60),"") | AO60: =IFERROR(((AM60*(AK60+0.1))+(AN60*AL60))/(AM60+AN60),"") | AS60: =IFERROR(((AM60*(AQ60+0.15))+(AN60*AR60))/(AM60+AN60),"") | AV60: =SUM(AT60:AU60) -> 0 | AZ60: =H60-(BB60+BD60) -> 0 | BA60: =I60-(BC60+BE60) -> 0 | BF60: =IFERROR(AZ60/L60,"-") -> - | BG60: =IFERROR(BA60/L60,"-") -> - | BH60: =IFERROR(BB60/M60,"-") -> - | BI60: =IFERROR(BC60/M60,"-") -> - | BJ60: =IFERROR(BD60/N60,"-") -> - | BK60: =IFERROR(BE60/N60,"-") -> - | BN60: =SUM(BL60:BM60) -> 0
A61: =LEFT(F61,4)+1 -> 2022 | B61: =RIGHT(F61,2) -> 03 | C61: {=_xlfn.IFS(_xlfn.NUMBERVALUE(B61)<=13,"Q1",AND(_xlfn.NUMBERVALUE(B61)>13,_xlfn.NUMBERVALUE(B61)<=26),"Q2", AND(_xlfn.NUMBERVALUE(B61)>26,_xlfn.NUMBERVALUE(B61)<=39),"Q3",_xlfn.NUMBERVALUE(B61)>39,"Q4")} -> Q1 | D61: =E60+1 -> 44240 | E61: =D61+6 -> 44246 | F61: 202103 | G61: =SUM(H61:I61) -> 0 | J61: =IFERROR(H61/G61,0) -> 0 | K61: =IFERROR(I61/G61,0) -> 0 | O61: =IFERROR(L61/$G61,0) -> 0 | P61: =IFERROR(M61/$G61,0) -> 0 | Q61: =IFERROR(N61/$G61,0) -> 0 | R61: =Forecast!J56 -> 0 | S61: =Forecast!N56 -> 0 | T61: =IF(OR(RIGHT(F61,2) = "01",G61 = 0),G61,T60+G61) -> 0 | U61: =IF(RIGHT(F61,2)="01",R61,R61+U60) -> 0 | V61: =IF(RIGHT(F61,2)="01",S61,S61+V60) -> 0 | W61: =X61+Y61 -> 0 | X61: ='Channel & Campaign Metrics'!AR60 -> 0 | Y61: ='Channel & Campaign Metrics'!BS60 -> 0 | AB61: ='Glass Metrics'!AC61 -> 0 | AC61: ='Glass Metrics'!I61 -> 0 | AD61: ='Glass Metrics'!N61 -> 0 | AE61: ='Glass Metrics'!S61 -> 0 | AF61: =IFERROR(AE61/AB61,"") | AG61: =IFERROR(AC61/AE61,"") | AH61: =IFERROR(AD61/AC61,"") | AI61: =IFERROR(G61/AB61,"") | AJ61: =IFERROR(((AK61*AM61)+(AL61*AN61))/(AM61+AN61),"") | AO61: =IFERROR(((AM61*(AK61+0.1))+(AN61*AL61))/(AM61+AN61),"") | AS61: =IFERROR(((AM61*(AQ61+0.15))+(AN61*AR61))/(AM61+AN61),"") | AV61: =SUM(AT61:AU61) -> 0 | AZ61: =H61-(BB61+BD61) -> 0 | BA61: =I61-(BC61+BE61) -> 0 | BF61: =IFERROR(AZ61/L61,"-") -> - | BG61: =IFERROR(BA61/L61,"-") -> - | BH61: =IFERROR(BB61/M61,"-") -> - | BI61: =IFERROR(BC61/M61,"-") -> - | BJ61: =IFERROR(BD61/N61,"-") -> - | BK61: =IFERROR(BE61/N61,"-") -> - | BN61: =SUM(BL61:BM61) -> 0
A62: =LEFT(F62,4)+1 -> 2022 | B62: =RIGHT(F62,2) -> 04 | C62: {=_xlfn.IFS(_xlfn.NUMBERVALUE(B62)<=13,"Q1",AND(_xlfn.NUMBERVALUE(B62)>13,_xlfn.NUMBERVALUE(B62)<=26),"Q2", AND(_xlfn.NUMBERVALUE(B62)>26,_xlfn.NUMBERVALUE(B62)<=39),"Q3",_xlfn.NUMBERVALUE(B62)>39,"Q4")} -> Q1 | D62: =E61+1 -> 44247 | E62: =D62+6 -> 44253 | F62: 202104 | G62: =SUM(H62:I62) -> 0 | J62: =IFERROR(H62/G62,0) -> 0 | K62: =IFERROR(I62/G62,0) -> 0 | O62: =IFERROR(L62/$G62,0) -> 0 | P62: =IFERROR(M62/$G62,0) -> 0 | Q62: =IFERROR(N62/$G62,0) -> 0 | R62: =Forecast!J57 -> 0 | S62: =Forecast!N57 -> 0 | T62: =IF(OR(RIGHT(F62,2) = "01",G62 = 0),G62,T61+G62) -> 0 | U62: =IF(RIGHT(F62,2)="01",R62,R62+U61) -> 0 | V62: =IF(RIGHT(F62,2)="01",S62,S62+V61) -> 0 | W62: =X62+Y62 -> 0 | X62: ='Channel & Campaign Metrics'!AR61 -> 0 | Y62: ='Channel & Campaign Metrics'!BS61 -> 0 | AB62: ='Glass Metrics'!AC62 -> 0 | AC62: ='Glass Metrics'!I62 -> 0 | AD62: ='Glass Metrics'!N62 -> 0 | AE62: ='Glass Metrics'!S62 -> 0 | AF62: =IFERROR(AE62/AB62,"") | AG62: =IFERROR(AC62/AE62,"") | AH62: =IFERROR(AD62/AC62,"") | AI62: =IFERROR(G62/AB62,"") | AJ62: =IFERROR(((AK62*AM62)+(AL62*AN62))/(AM62+AN62),"") | AO62: =IFERROR(((AM62*(AK62+0.1))+(AN62*AL62))/(AM62+AN62),"") | AS62: =IFERROR(((AM62*(AQ62+0.15))+(AN62*AR62))/(AM62+AN62),"") | AV62: =SUM(AT62:AU62) -> 0 | AZ62: =H62-(BB62+BD62) -> 0 | BA62: =I62-(BC62+BE62) -> 0 | BF62: =IFERROR(AZ62/L62,"-") -> - | BG62: =IFERROR(BA62/L62,"-") -> - | BH62: =IFERROR(BB62/M62,"-") -> - | BI62: =IFERROR(BC62/M62,"-") -> - | BJ62: =IFERROR(BD62/N62,"-") -> - | BK62: =IFERROR(BE62/N62,"-") -> - | BN62: =SUM(BL62:BM62) -> 0
A63: =LEFT(F63,4)+1 -> 2022 | B63: =RIGHT(F63,2) -> 05 | C63: {=_xlfn.IFS(_xlfn.NUMBERVALUE(B63)<=13,"Q1",AND(_xlfn.NUMBERVALUE(B63)>13,_xlfn.NUMBERVALUE(B63)<=26),"Q2", AND(_xlfn.NUMBERVALUE(B63)>26,_xlfn.NUMBERVALUE(B63)<=39),"Q3",_xlfn.NUMBERVALUE(B63)>39,"Q4")} -> Q1 | D63: =E62+1 -> 44254 | E63: =D63+6 -> 44260 | F63: 202105 | G63: =SUM(H63:I63) -> 0 | J63: =IFERROR(H63/G63,0) -> 0 | K63: =IFERROR(I63/G63,0) -> 0 | O63: =IFERROR(L63/$G63,0) -> 0 | P63: =IFERROR(M63/$G63,0) -> 0 | Q63: =IFERROR(N63/$G63,0) -> 0 | R63: =Forecast!J58 -> 0 | S63: =Forecast!N58 -> 0 | T63: =IF(OR(RIGHT(F63,2) = "01",G63 = 0),G63,T62+G63) -> 0 | U63: =IF(RIGHT(F63,2)="01",R63,R63+U62) -> 0 | V63: =IF(RIGHT(F63,2)="01",S63,S63+V62) -> 0 | W63: =X63+Y63 -> 0 | X63: ='Channel & Campaign Metrics'!AR62 -> 0 | Y63: ='Channel & Campaign Metrics'!BS62 -> 0 | AB63: ='Glass Metrics'!AC63 -> 0 | AC63: ='Glass Metrics'!I63 -> 0 | AD63: ='Glass Metrics'!N63 -> 0 | AE63: ='Glass Metrics'!S63 -> 0 | AF63: =IFERROR(AE63/AB63,"") | AG63: =IFERROR(AC63/AE63,"") | AH63: =IFERROR(AD63/AC63,"") | AI63: =IFERROR(G63/AB63,"") | AJ63: =IFERROR(((AK63*AM63)+(AL63*AN63))/(AM63+AN63),"") | AO63: =IFERROR(((AM63*(AK63+0.1))+(AN63*AL63))/(AM63+AN63),"") | AS63: =IFERROR(((AM63*(AQ63+0.15))+(AN63*AR63))/(AM63+AN63),"") | AV63: =SUM(AT63:AU63) -> 0 | AZ63: =H63-(BB63+BD63) -> 0 | BA63: =I63-(BC63+BE63) -> 0 | BF63: =IFERROR(AZ63/L63,"-") -> - | BG63: =IFERROR(BA63/L63,"-") -> - | BH63: =IFERROR(BB63/M63,"-") -> - | BI63: =IFERROR(BC63/M63,"-") -> - | BJ63: =IFERROR(BD63/N63,"-") -> - | BK63: =IFERROR(BE63/N63,"-") -> - | BN63: =SUM(BL63:BM63) -> 0
A64: =LEFT(F64,4)+1 -> 2022 | B64: =RIGHT(F64,2) -> 06 | C64: {=_xlfn.IFS(_xlfn.NUMBERVALUE(B64)<=13,"Q1",AND(_xlfn.NUMBERVALUE(B64)>13,_xlfn.NUMBERVALUE(B64)<=26),"Q2", AND(_xlfn.NUMBERVALUE(B64)>26,_xlfn.NUMBERVALUE(B64)<=39),"Q3",_xlfn.NUMBERVALUE(B64)>39,"Q4")} -> Q1 | D64: =E63+1 -> 44261 | E64: =D64+6 -> 44267 | F64: 202106 | G64: =SUM(H64:I64) -> 0 | J64: =IFERROR(H64/G64,0) -> 0 | K64: =IFERROR(I64/G64,0) -> 0 | O64: =IFERROR(L64/$G64,0) -> 0 | P64: =IFERROR(M64/$G64,0) -> 0 | Q64: =IFERROR(N64/$G64,0) -> 0 | R64: =Forecast!J59 -> 0 | S64: =Forecast!N59 -> 0 | T64: =IF(OR(RIGHT(F64,2) = "01",G64 = 0),G64,T63+G64) -> 0 | U64: =IF(RIGHT(F64,2)="01",R64,R64+U63) -> 0 | V64: =IF(RIGHT(F64,2)="01",S64,S64+V63) -> 0 | W64: =X64+Y64 -> 0 | X64: ='Channel & Campaign Metrics'!AR63 -> 0 | Y64: ='Channel & Campaign Metrics'!BS63 -> 0 | AB64: ='Glass Metrics'!AC64 -> 0 | AC64: ='Glass Metrics'!I64 -> 0 | AD64: ='Glass Metrics'!N64 -> 0 | AE64: ='Glass Metrics'!S64 -> 0 | AF64: =IFERROR(AE64/AB64,"") | AG64: =IFERROR(AC64/AE64,"") | AH64: =IFERROR(AD64/AC64,"") | AI64: =IFERROR(G64/AB64,"") | AJ64: =IFERROR(((AK64*AM64)+(AL64*AN64))/(AM64+AN64),"") | AO64: =IFERROR(((AM64*(AK64+0.1))+(AN64*AL64))/(AM64+AN64),"") | AS64: =IFERROR(((AM64*(AQ64+0.15))+(AN64*AR64))/(AM64+AN64),"") | AV64: =SUM(AT64:AU64) -> 0 | AZ64: =H64-(BB64+BD64) -> 0 | BA64: =I64-(BC64+BE64) -> 0 | BF64: =IFERROR(AZ64/L64,"-") -> - | BG64: =IFERROR(BA64/L64,"-") -> - | BH64: =IFERROR(BB64/M64,"-") -> - | BI64: =IFERROR(BC64/M64,"-") -> - | BJ64: =IFERROR(BD64/N64,"-") -> - | BK64: =IFERROR(BE64/N64,"-") -> - | BN64: =SUM(BL64:BM64) -> 0
A65: =LEFT(F65,4)+1 -> 2022 | B65: =RIGHT(F65,2) -> 07 | C65: {=_xlfn.IFS(_xlfn.NUMBERVALUE(B65)<=13,"Q1",AND(_xlfn.NUMBERVALUE(B65)>13,_xlfn.NUMBERVALUE(B65)<=26),"Q2", AND(_xlfn.NUMBERVALUE(B65)>26,_xlfn.NUMBERVALUE(B65)<=39),"Q3",_xlfn.NUMBERVALUE(B65)>39,"Q4")} -> Q1 | D65: =E64+1 -> 44268 | E65: =D65+6 -> 44274 | F65: 202107 | G65: =SUM(H65:I65) -> 0 | J65: =IFERROR(H65/G65,0) -> 0 | K65: =IFERROR(I65/G65,0) -> 0 | O65: =IFERROR(L65/$G65,0) -> 0 | P65: =IFERROR(M65/$G65,0) -> 0 | Q65: =IFERROR(N65/$G65,0) -> 0 | R65: =Forecast!J60 -> 0 | S65: =Forecast!N60 -> 0 | T65: =IF(OR(RIGHT(F65,2) = "01",G65 = 0),G65,T64+G65) -> 0 | U65: =IF(RIGHT(F65,2)="01",R65,R65+U64) -> 0 | V65: =IF(RIGHT(F65,2)="01",S65,S65+V64) -> 0 | W65: =X65+Y65 -> 0 | X65: ='Channel & Campaign Metrics'!AR64 -> 0 | Y65: ='Channel & Campaign Metrics'!BS64 -> 0 | AB65: ='Glass Metrics'!AC65 -> 0 | AC65: ='Glass Metrics'!I65 -> 0 | AD65: ='Glass Metrics'!N65 -> 0 | AE65: ='Glass Metrics'!S65 -> 0 | AF65: =IFERROR(AE65/AB65,"") | AG65: =IFERROR(AC65/AE65,"") | AH65: =IFERROR(AD65/AC65,"") | AI65: =IFERROR(G65/AB65,"") | AJ65: =IFERROR(((AK65*AM65)+(AL65*AN65))/(AM65+AN65),"") | AO65: =IFERROR(((AM65*(AK65+0.1))+(AN65*AL65))/(AM65+AN65),"") | AS65: =IFERROR(((AM65*(AQ65+0.15))+(AN65*AR65))/(AM65+AN65),"") | AV65: =SUM(AT65:AU65) -> 0 | AZ65: =H65-(BB65+BD65) -> 0 | BA65: =I65-(BC65+BE65) -> 0 | BF65: =IFERROR(AZ65/L65,"-") -> - | BG65: =IFERROR(BA65/L65,"-") -> - | BH65: =IFERROR(BB65/M65,"-") -> - | BI65: =IFERROR(BC65/M65,"-") -> - | BJ65: =IFERROR(BD65/N65,"-") -> - | BK65: =IFERROR(BE65/N65,"-") -> - | BN65: =SUM(BL65:BM65) -> 0
A66: =LEFT(F66,4)+1 -> 2022 | B66: =RIGHT(F66,2) -> 08 | C66: {=_xlfn.IFS(_xlfn.NUMBERVALUE(B66)<=13,"Q1",AND(_xlfn.NUMBERVALUE(B66)>13,_xlfn.NUMBERVALUE(B66)<=26),"Q2", AND(_xlfn.NUMBERVALUE(B66)>26,_xlfn.NUMBERVALUE(B66)<=39),"Q3",_xlfn.NUMBERVALUE(B66)>39,"Q4")} -> Q1 | D66: =E65+1 -> 44275 | E66: =D66+6 -> 44281 | F66: 202108 | G66: =SUM(H66:I66) -> 0 | J66: =IFERROR(H66/G66,0) -> 0 | K66: =IFERROR(I66/G66,0) -> 0 | O66: =IFERROR(L66/$G66,0) -> 0 | P66: =IFERROR(M66/$G66,0) -> 0 | Q66: =IFERROR(N66/$G66,0) -> 0 | R66: =Forecast!J61 -> 0 | S66: =Forecast!N61 -> 0 | T66: =IF(OR(RIGHT(F66,2) = "01",G66 = 0),G66,T65+G66) -> 0 | U66: =IF(RIGHT(F66,2)="01",R66,R66+U65) -> 0 | V66: =IF(RIGHT(F66,2)="01",S66,S66+V65) -> 0 | W66: =X66+Y66 -> 0 | X66: ='Channel & Campaign Metrics'!AR65 -> 0 | Y66: ='Channel & Campaign Metrics'!BS65 -> 0 | AB66: ='Glass Metrics'!AC66 -> 0 | AC66: ='Glass Metrics'!I66 -> 0 | AD66: ='Glass Metrics'!N66 -> 0 | AE66: ='Glass Metrics'!S66 -> 0 | AF66: =IFERROR(AE66/AB66,"") | AG66: =IFERROR(AC66/AE66,"") | AH66: =IFERROR(AD66/AC66,"") | AI66: =IFERROR(G66/AB66,"") | AJ66: =IFERROR(((AK66*AM66)+(AL66*AN66))/(AM66+AN66),"") | AO66: =IFERROR(((AM66*(AK66+0.1))+(AN66*AL66))/(AM66+AN66),"") | AS66: =IFERROR(((AM66*(AQ66+0.15))+(AN66*AR66))/(AM66+AN66),"") | AV66: =SUM(AT66:AU66) -> 0 | AZ66: =H66-(BB66+BD66) -> 0 | BA66: =I66-(BC66+BE66) -> 0 | BF66: =IFERROR(AZ66/L66,"-") -> - | BG66: =IFERROR(BA66/L66,"-") -> - | BH66: =IFERROR(BB66/M66,"-") -> - | BI66: =IFERROR(BC66/M66,"-") -> - | BJ66: =IFERROR(BD66/N66,"-") -> - | BK66: =IFERROR(BE66/N66,"-") -> - | BN66: =SUM(BL66:BM66) -> 0
A67: =LEFT(F67,4)+1 -> 2022 | B67: =RIGHT(F67,2) -> 09 | C67: {=_xlfn.IFS(_xlfn.NUMBERVALUE(B67)<=13,"Q1",AND(_xlfn.NUMBERVALUE(B67)>13,_xlfn.NUMBERVALUE(B67)<=26),"Q2", AND(_xlfn.NUMBERVALUE(B67)>26,_xlfn.NUMBERVALUE(B67)<=39),"Q3",_xlfn.NUMBERVALUE(B67)>39,"Q4")} -> Q1 | D67: =E66+1 -> 44282 | E67: =D67+6 -> 44288 | F67: 202109 | G67: =SUM(H67:I67) -> 0 | J67: =IFERROR(H67/G67,0) -> 0 | K67: =IFERROR(I67/G67,0) -> 0 | O67: =IFERROR(L67/$G67,0) -> 0 | P67: =IFERROR(M67/$G67,0) -> 0 | Q67: =IFERROR(N67/$G67,0) -> 0 | R67: =Forecast!J62 -> 0 | S67: =Forecast!N62 -> 0 | T67: =IF(OR(RIGHT(F67,2) = "01",G67 = 0),G67,T66+G67) -> 0 | U67: =IF(RIGHT(F67,2)="01",R67,R67+U66) -> 0 | V67: =IF(RIGHT(F67,2)="01",S67,S67+V66) -> 0 | W67: =X67+Y67 -> 0 | X67: ='Channel & Campaign Metrics'!AR66 -> 0 | Y67: ='Channel & Campaign Metrics'!BS66 -> 0 | AB67: ='Glass Metrics'!AC67 -> 0 | AC67: ='Glass Metrics'!I67 -> 0 | AD67: ='Glass Metrics'!N67 -> 0 | AE67: ='Glass Metrics'!S67 -> 0 | AF67: =IFERROR(AE67/AB67,"") | AG67: =IFERROR(AC67/AE67,"") | AH67: =IFERROR(AD67/AC67,"") | AI67: =IFERROR(G67/AB67,"") | AJ67: =IFERROR(((AK67*AM67)+(AL67*AN67))/(AM67+AN67),"") | AO67: =IFERROR(((AM67*(AK67+0.1))+(AN67*AL67))/(AM67+AN67),"") | AS67: =IFERROR(((AM67*(AQ67+0.15))+(AN67*AR67))/(AM67+AN67),"") | AV67: =SUM(AT67:AU67) -> 0 | AZ67: =H67-(BB67+BD67) -> 0 | BA67: =I67-(BC67+BE67) -> 0 | BF67: =IFERROR(AZ67/L67,"-") -> - | BG67: =IFERROR(BA67/L67,"-") -> - | BH67: =IFERROR(BB67/M67,"-") -> - | BI67: =IFERROR(BC67/M67,"-") -> - | BJ67: =IFERROR(BD67/N67,"-") -> - | BK67: =IFERROR(BE67/N67,"-") -> - | BN67: =SUM(BL67:BM67) -> 0
A68: =LEFT(F68,4)+1 -> 2022 | B68: =RIGHT(F68,2) -> 10 | C68: {=_xlfn.IFS(_xlfn.NUMBERVALUE(B68)<=13,"Q1",AND(_xlfn.NUMBERVALUE(B68)>13,_xlfn.NUMBERVALUE(B68)<=26),"Q2", AND(_xlfn.NUMBERVALUE(B68)>26,_xlfn.NUMBERVALUE(B68)<=39),"Q3",_xlfn.NUMBERVALUE(B68)>39,"Q4")} -> Q1 | D68: =E67+1 -> 44289 | E68: =D68+6 -> 44295 | F68: 202110 | G68: =SUM(H68:I68) -> 0 | J68: =IFERROR(H68/G68,0) -> 0 | K68: =IFERROR(I68/G68,0) -> 0 | O68: =IFERROR(L68/$G68,0) -> 0 | P68: =IFERROR(M68/$G68,0) -> 0 | Q68: =IFERROR(N68/$G68,0) -> 0 | R68: =Forecast!J63 -> 0 | S68: =Forecast!N63 -> 0 | T68: =IF(OR(RIGHT(F68,2) = "01",G68 = 0),G68,T67+G68) -> 0 | U68: =IF(RIGHT(F68,2)="01",R68,R68+U67) -> 0 | V68: =IF(RIGHT(F68,2)="01",S68,S68+V67) -> 0 | W68: =X68+Y68 -> 0 | X68: ='Channel & Campaign Metrics'!AR67 -> 0 | Y68: ='Channel & Campaign Metrics'!BS67 -> 0 | AB68: ='Glass Metrics'!AC68 -> 0 | AC68: ='Glass Metrics'!I68 -> 0 | AD68: ='Glass Metrics'!N68 -> 0 | AE68: ='Glass Metrics'!S68 -> 0 | AF68: =IFERROR(AE68/AB68,"") | AG68: =IFERROR(AC68/AE68,"") | AH68: =IFERROR(AD68/AC68,"") | AI68: =IFERROR(G68/AB68,"") | AJ68: =IFERROR(((AK68*AM68)+(AL68*AN68))/(AM68+AN68),"") | AO68: =IFERROR(((AM68*(AK68+0.1))+(AN68*AL68))/(AM68+AN68),"") | AS68: =IFERROR(((AM68*(AQ68+0.15))+(AN68*AR68))/(AM68+AN68),"") | AV68: =SUM(AT68:AU68) -> 0 | AZ68: =H68-(BB68+BD68) -> 0 | BA68: =I68-(BC68+BE68) -> 0 | BF68: =IFERROR(AZ68/L68,"-") -> - | BG68: =IFERROR(BA68/L68,"-") -> - | BH68: =IFERROR(BB68/M68,"-") -> - | BI68: =IFERROR(BC68/M68,"-") -> - | BJ68: =IFERROR(BD68/N68,"-") -> - | BK68: =IFERROR(BE68/N68,"-") -> - | BN68: =SUM(BL68:BM68) -> 0
A69: =LEFT(F69,4)+1 -> 2022 | B69: =RIGHT(F69,2) -> 11 | C69: {=_xlfn.IFS(_xlfn.NUMBERVALUE(B69)<=13,"Q1",AND(_xlfn.NUMBERVALUE(B69)>13,_xlfn.NUMBERVALUE(B69)<=26),"Q2", AND(_xlfn.NUMBERVALUE(B69)>26,_xlfn.NUMBERVALUE(B69)<=39),"Q3",_xlfn.NUMBERVALUE(B69)>39,"Q4")} -> Q1 | D69: =E68+1 -> 44296 | E69: =D69+6 -> 44302 | F69: 202111 | G69: =SUM(H69:I69) -> 0 | J69: =IFERROR(H69/G69,0) -> 0 | K69: =IFERROR(I69/G69,0) -> 0 | O69: =IFERROR(L69/$G69,0) -> 0 | P69: =IFERROR(M69/$G69,0) -> 0 | Q69: =IFERROR(N69/$G69,0) -> 0 | R69: =Forecast!J64 -> 0 | S69: =Forecast!N64 -> 0 | T69: =IF(OR(RIGHT(F69,2) = "01",G69 = 0),G69,T68+G69) -> 0 | U69: =IF(RIGHT(F69,2)="01",R69,R69+U68) -> 0 | V69: =IF(RIGHT(F69,2)="01",S69,S69+V68) -> 0 | W69: =X69+Y69 -> 0 | X69: ='Channel & Campaign Metrics'!AR68 -> 0 | Y69: ='Channel & Campaign Metrics'!BS68 -> 0 | AB69: ='Glass Metrics'!AC69 -> 0 | AC69: ='Glass Metrics'!I69 -> 0 | AD69: ='Glass Metrics'!N69 -> 0 | AE69: ='Glass Metrics'!S69 -> 0 | AF69: =IFERROR(AE69/AB69,"") | AG69: =IFERROR(AC69/AE69,"") | AH69: =IFERROR(AD69/AC69,"") | AI69: =IFERROR(G69/AB69,"") | AJ69: =IFERROR(((AK69*AM69)+(AL69*AN69))/(AM69+AN69),"") | AO69: =IFERROR(((AM69*(AK69+0.1))+(AN69*AL69))/(AM69+AN69),"") | AS69: =IFERROR(((AM69*(AQ69+0.15))+(AN69*AR69))/(AM69+AN69),"") | AV69: =SUM(AT69:AU69) -> 0 | AZ69: =H69-(BB69+BD69) -> 0 | BA69: =I69-(BC69+BE69) -> 0 | BF69: =IFERROR(AZ69/L69,"-") -> - | BG69: =IFERROR(BA69/L69,"-") -> - | BH69: =IFERROR(BB69/M69,"-") -> - | BI69: =IFERROR(BC69/M69,"-") -> - | BJ69: =IFERROR(BD69/N69,"-") -> - | BK69: =IFERROR(BE69/N69,"-") -> - | BN69: =SUM(BL69:BM69) -> 0
A70: =LEFT(F70,4)+1 -> 2022 | B70: =RIGHT(F70,2) -> 12 | C70: {=_xlfn.IFS(_xlfn.NUMBERVALUE(B70)<=13,"Q1",AND(_xlfn.NUMBERVALUE(B70)>13,_xlfn.NUMBERVALUE(B70)<=26),"Q2", AND(_xlfn.NUMBERVALUE(B70)>26,_xlfn.NUMBERVALUE(B70)<=39),"Q3",_xlfn.NUMBERVALUE(B70)>39,"Q4")} -> Q1 | D70: =E69+1 -> 44303 | E70: =D70+6 -> 44309 | F70: 202112 | G70: =SUM(H70:I70) -> 0 | J70: =IFERROR(H70/G70,0) -> 0 | K70: =IFERROR(I70/G70,0) -> 0 | O70: =IFERROR(L70/$G70,0) -> 0 | P70: =IFERROR(M70/$G70,0) -> 0 | Q70: =IFERROR(N70/$G70,0) -> 0 | R70: =Forecast!J65 -> 0 | S70: =Forecast!N65 -> 0 | T70: =IF(OR(RIGHT(F70,2) = "01",G70 = 0),G70,T69+G70) -> 0 | U70: =IF(RIGHT(F70,2)="01",R70,R70+U69) -> 0 | V70: =IF(RIGHT(F70,2)="01",S70,S70+V69) -> 0 | W70: =X70+Y70 -> 0 | X70: ='Channel & Campaign Metrics'!AR69 -> 0 | Y70: ='Channel & Campaign Metrics'!BS69 -> 0 | AB70: ='Glass Metrics'!AC70 -> 0 | AC70: ='Glass Metrics'!I70 -> 0 | AD70: ='Glass Metrics'!N70 -> 0 | AE70: ='Glass Metrics'!S70 -> 0 | AF70: =IFERROR(AE70/AB70,"") | AG70: =IFERROR(AC70/AE70,"") | AH70: =IFERROR(AD70/AC70,"") | AI70: =IFERROR(G70/AB70,"") | AJ70: =IFERROR(((AK70*AM70)+(AL70*AN70))/(AM70+AN70),"") | AO70: =IFERROR(((AM70*(AK70+0.1))+(AN70*AL70))/(AM70+AN70),"") | AS70: =IFERROR(((AM70*(AQ70+0.15))+(AN70*AR70))/(AM70+AN70),"") | AV70: =SUM(AT70:AU70) -> 0 | AZ70: =H70-(BB70+BD70) -> 0 | BA70: =I70-(BC70+BE70) -> 0 | BF70: =IFERROR(AZ70/L70,"-") -> - | BG70: =IFERROR(BA70/L70,"-") -> - | BH70: =IFERROR(BB70/M70,"-") -> - | BI70: =IFERROR(BC70/M70,"-") -> - | BJ70: =IFERROR(BD70/N70,"-") -> - | BK70: =IFERROR(BE70/N70,"-") -> - | BN70: =SUM(BL70:BM70) -> 0
... A92: =LEFT(F92,4)+1 -> 2022 | B92: =RIGHT(F92,2) -> 34 | C92: {=_xlfn.IFS(_xlfn.NUMBERVALUE(B92)<=13,"Q1",AND(_xlfn.NUMBERVALUE(B92)>13,_xlfn.NUMBERVALUE(B92)<=26),"Q2", AND(_xlfn.NUMBERVALUE(B92)>26,_xlfn.NUMBERVALUE(B92)<=39),"Q3",_xlfn.NUMBERVALUE(B92)>39,"Q4")} -> Q3 | D92: =E91+1 -> 44457 | E92: =D92+6 -> 44463 | F92: 202134 | G92: =SUM(H92:I92) -> 0 | J92: =IFERROR(H92/G92,0) -> 0 | K92: =IFERROR(I92/G92,0) -> 0 | O92: =IFERROR(L92/$G92,0) -> 0 | P92: =IFERROR(M92/$G92,0) -> 0 | Q92: =IFERROR(N92/$G92,0) -> 0 | R92: =Forecast!J87 -> 0 | S92: =Forecast!N87 -> 0 | T92: =IF(OR(RIGHT(F92,2) = "01",G92 = 0),G92,T91+G92) -> 0 | U92: =IF(RIGHT(F92,2)="01",R92,R92+U91) -> 0 | V92: =IF(RIGHT(F92,2)="01",S92,S92+V91) -> 0 | W92: =X92+Y92 -> 0 | X92: ='Channel & Campaign Metrics'!AR91 -> 0 | Y92: ='Channel & Campaign Metrics'!BS91 -> 0 | AB92: ='Glass Metrics'!AC92 -> 0 | AC92: ='Glass Metrics'!I92 -> 0 | AD92: ='Glass Metrics'!N92 -> 0 | AE92: ='Glass Metrics'!S92 -> 0 | AF92: =IFERROR(AE92/AB92,"") | AG92: =IFERROR(AC92/AE92,"") | AH92: =IFERROR(AD92/AC92,"") | AI92: =IFERROR(G92/AB92,"") | AJ92: =IFERROR(((AK92*AM92)+(AL92*AN92))/(AM92+AN92),"") | AO92: =IFERROR(((AM92*(AK92+0.1))+(AN92*AL92))/(AM92+AN92),"") | AS92: =IFERROR(((AM92*(AQ92+0.15))+(AN92*AR92))/(AM92+AN92),"") | AV92: =SUM(AT92:AU92) -> 0 | AZ92: =H92-(BB92+BD92) -> 0 | BA92: =I92-(BC92+BE92) -> 0 | BF92: =IFERROR(AZ92/L92,"-") -> - | BG92: =IFERROR(BA92/L92,"-") -> - | BH92: =IFERROR(BB92/M92,"-") -> - | BI92: =IFERROR(BC92/M92,"-") -> - | BJ92: =IFERROR(BD92/N92,"-") -> - | BK92: =IFERROR(BE92/N92,"-") -> - | BN92: =SUM(BL92:BM92) -> 0
A93: =LEFT(F93,4)+1 -> 2022 | B93: =RIGHT(F93,2) -> 35 | C93: {=_xlfn.IFS(_xlfn.NUMBERVALUE(B93)<=13,"Q1",AND(_xlfn.NUMBERVALUE(B93)>13,_xlfn.NUMBERVALUE(B93)<=26),"Q2", AND(_xlfn.NUMBERVALUE(B93)>26,_xlfn.NUMBERVALUE(B93)<=39),"Q3",_xlfn.NUMBERVALUE(B93)>39,"Q4")} -> Q3 | D93: =E92+1 -> 44464 | E93: =D93+6 -> 44470 | F93: 202135 | G93: =SUM(H93:I93) -> 0 | J93: =IFERROR(H93/G93,0) -> 0 | K93: =IFERROR(I93/G93,0) -> 0 | O93: =IFERROR(L93/$G93,0) -> 0 | P93: =IFERROR(M93/$G93,0) -> 0 | Q93: =IFERROR(N93/$G93,0) -> 0 | R93: =Forecast!J88 -> 0 | S93: =Forecast!N88 -> 0 | T93: =IF(OR(RIGHT(F93,2) = "01",G93 = 0),G93,T92+G93) -> 0 | U93: =IF(RIGHT(F93,2)="01",R93,R93+U92) -> 0 | V93: =IF(RIGHT(F93,2)="01",S93,S93+V92) -> 0 | W93: =X93+Y93 -> 0 | X93: ='Channel & Campaign Metrics'!AR92 -> 0 | Y93: ='Channel & Campaign Metrics'!BS92 -> 0 | AB93: ='Glass Metrics'!AC93 -> 0 | AC93: ='Glass Metrics'!I93 -> 0 | AD93: ='Glass Metrics'!N93 -> 0 | AE93: ='Glass Metrics'!S93 -> 0 | AF93: =IFERROR(AE93/AB93,"") | AG93: =IFERROR(AC93/AE93,"") | AH93: =IFERROR(AD93/AC93,"") | AI93: =IFERROR(G93/AB93,"") | AJ93: =IFERROR(((AK93*AM93)+(AL93*AN93))/(AM93+AN93),"") | AO93: =IFERROR(((AM93*(AK93+0.1))+(AN93*AL93))/(AM93+AN93),"") | AS93: =AP93-10% -> -0.1 | AV93: =SUM(AT93:AU93) -> 0 | AZ93: =H93-(BB93+BD93) -> 0 | BA93: =I93-(BC93+BE93) -> 0 | BF93: =IFERROR(AZ93/L93,"-") -> - | BG93: =IFERROR(BA93/L93,"-") -> - | BH93: =IFERROR(BB93/M93,"-") -> - | BI93: =IFERROR(BC93/M93,"-") -> - | BJ93: =IFERROR(BD93/N93,"-") -> - | BK93: =IFERROR(BE93/N93,"-") -> - | BN93: =SUM(BL93:BM93) -> 0
A94: =LEFT(F94,4)+1 -> 2022 | B94: =RIGHT(F94,2) -> 36 | C94: {=_xlfn.IFS(_xlfn.NUMBERVALUE(B94)<=13,"Q1",AND(_xlfn.NUMBERVALUE(B94)>13,_xlfn.NUMBERVALUE(B94)<=26),"Q2", AND(_xlfn.NUMBERVALUE(B94)>26,_xlfn.NUMBERVALUE(B94)<=39),"Q3",_xlfn.NUMBERVALUE(B94)>39,"Q4")} -> Q3 | D94: =E93+1 -> 44471 | E94: =D94+6 -> 44477 | F94: 202136 | G94: =SUM(H94:I94) -> 0 | J94: =IFERROR(H94/G94,0) -> 0 | K94: =IFERROR(I94/G94,0) -> 0 | O94: =IFERROR(L94/$G94,0) -> 0 | P94: =IFERROR(M94/$G94,0) -> 0 | Q94: =IFERROR(N94/$G94,0) -> 0 | R94: =Forecast!J89 -> 0 | S94: =Forecast!N89 -> 0 | T94: =IF(OR(RIGHT(F94,2) = "01",G94 = 0),G94,T93+G94) -> 0 | U94: =IF(RIGHT(F94,2)="01",R94,R94+U93) -> 0 | V94: =IF(RIGHT(F94,2)="01",S94,S94+V93) -> 0 | W94: =X94+Y94 -> 0 | X94: ='Channel & Campaign Metrics'!AR93 -> 0 | Y94: ='Channel & Campaign Metrics'!BS93 -> 0 | AB94: ='Glass Metrics'!AC94 -> 0 | AC94: ='Glass Metrics'!I94 -> 0 | AD94: ='Glass Metrics'!N94 -> 0 | AE94: ='Glass Metrics'!S94 -> 0 | AF94: =IFERROR(AE94/AB94,"") | AG94: =IFERROR(AC94/AE94,"") | AH94: =IFERROR(AD94/AC94,"") | AI94: =IFERROR(G94/AB94,"") | AJ94: =IFERROR(((AK94*AM94)+(AL94*AN94))/(AM94+AN94),"") | AO94: =IFERROR(((AM94*(AK94+0.1))+(AN94*AL94))/(AM94+AN94),"") | AS94: =AP94-10% -> -0.1 | AV94: =SUM(AT94:AU94) -> 0 | AZ94: =H94-(BB94+BD94) -> 0 | BA94: =I94-(BC94+BE94) -> 0 | BF94: =IFERROR(AZ94/L94,"-") -> - | BG94: =IFERROR(BA94/L94,"-") -> - | BH94: =IFERROR(BB94/M94,"-") -> - | BI94: =IFERROR(BC94/M94,"-") -> - | BJ94: =IFERROR(BD94/N94,"-") -> - | BK94: =IFERROR(BE94/N94,"-") -> - | BN94: =SUM(BL94:BM94) -> 0
A95: =LEFT(F95,4)+1 -> 2022 | B95: =RIGHT(F95,2) -> 37 | C95: {=_xlfn.IFS(_xlfn.NUMBERVALUE(B95)<=13,"Q1",AND(_xlfn.NUMBERVALUE(B95)>13,_xlfn.NUMBERVALUE(B95)<=26),"Q2", AND(_xlfn.NUMBERVALUE(B95)>26,_xlfn.NUMBERVALUE(B95)<=39),"Q3",_xlfn.NUMBERVALUE(B95)>39,"Q4")} -> Q3 | D95: =E94+1 -> 44478 | E95: =D95+6 -> 44484 | F95: 202137 | G95: =SUM(H95:I95) -> 0 | J95: =IFERROR(H95/G95,0) -> 0 | K95: =IFERROR(I95/G95,0) -> 0 | O95: =IFERROR(L95/$G95,0) -> 0 | P95: =IFERROR(M95/$G95,0) -> 0 | Q95: =IFERROR(N95/$G95,0) -> 0 | R95: =Forecast!J90 -> 0 | S95: =Forecast!N90 -> 0 | T95: =IF(OR(RIGHT(F95,2) = "01",G95 = 0),G95,T94+G95) -> 0 | U95: =IF(RIGHT(F95,2)="01",R95,R95+U94) -> 0 | V95: =IF(RIGHT(F95,2)="01",S95,S95+V94) -> 0 | W95: =X95+Y95 -> 0 | X95: ='Channel & Campaign Metrics'!AR94 -> 0 | Y95: ='Channel & Campaign Metrics'!BS94 -> 0 | AB95: ='Glass Metrics'!AC95 -> 0 | AC95: ='Glass Metrics'!I95 -> 0 | AD95: ='Glass Metrics'!N95 -> 0 | AE95: ='Glass Metrics'!S95 -> 0 | AF95: =IFERROR(AE95/AB95,"") | AG95: =IFERROR(AC95/AE95,"") | AH95: =IFERROR(AD95/AC95,"") | AI95: =IFERROR(G95/AB95,"") | AJ95: =IFERROR(((AK95*AM95)+(AL95*AN95))/(AM95+AN95),"") | AO95: =IFERROR(((AM95*(AK95+0.1))+(AN95*AL95))/(AM95+AN95),"") | AS95: =AP95-10% -> -0.1 | AV95: =SUM(AT95:AU95) -> 0 | AZ95: =H95-(BB95+BD95) -> 0 | BA95: =I95-(BC95+BE95) -> 0 | BF95: =IFERROR(AZ95/L95,"-") -> - | BG95: =IFERROR(BA95/L95,"-") -> - | BH95: =IFERROR(BB95/M95,"-") -> - | BI95: =IFERROR(BC95/M95,"-") -> - | BJ95: =IFERROR(BD95/N95,"-") -> - | BK95: =IFERROR(BE95/N95,"-") -> - | BN95: =SUM(BL95:BM95) -> 0
A96: =LEFT(F96,4)+1 -> 2022 | B96: =RIGHT(F96,2) -> 38 | C96: {=_xlfn.IFS(_xlfn.NUMBERVALUE(B96)<=13,"Q1",AND(_xlfn.NUMBERVALUE(B96)>13,_xlfn.NUMBERVALUE(B96)<=26),"Q2", AND(_xlfn.NUMBERVALUE(B96)>26,_xlfn.NUMBERVALUE(B96)<=39),"Q3",_xlfn.NUMBERVALUE(B96)>39,"Q4")} -> Q3 | D96: =E95+1 -> 44485 | E96: =D96+6 -> 44491 | F96: 202138 | G96: =SUM(H96:I96) -> 0 | J96: =IFERROR(H96/G96,0) -> 0 | K96: =IFERROR(I96/G96,0) -> 0 | O96: =IFERROR(L96/$G96,0) -> 0 | P96: =IFERROR(M96/$G96,0) -> 0 | Q96: =IFERROR(N96/$G96,0) -> 0 | R96: =Forecast!J91 -> 0 | S96: =Forecast!N91 -> 0 | T96: =IF(OR(RIGHT(F96,2) = "01",G96 = 0),G96,T95+G96) -> 0 | U96: =IF(RIGHT(F96,2)="01",R96,R96+U95) -> 0 | V96: =IF(RIGHT(F96,2)="01",S96,S96+V95) -> 0 | W96: =X96+Y96 -> 0 | X96: ='Channel & Campaign Metrics'!AR95 -> 0 | Y96: ='Channel & Campaign Metrics'!BS95 -> 0 | AB96: ='Glass Metrics'!AC96 -> 0 | AC96: ='Glass Metrics'!I96 -> 0 | AD96: ='Glass Metrics'!N96 -> 0 | AE96: ='Glass Metrics'!S96 -> 0 | AF96: =IFERROR(AE96/AB96,"") | AG96: =IFERROR(AC96/AE96,"") | AH96: =IFERROR(AD96/AC96,"") | AI96: =IFERROR(G96/AB96,"") | AJ96: =IFERROR(((AK96*AM96)+(AL96*AN96))/(AM96+AN96),"") | AO96: =IFERROR(((AM96*(AK96+0.1))+(AN96*AL96))/(AM96+AN96),"") | AS96: =AP96-10% -> -0.1 | AV96: =SUM(AT96:AU96) -> 0 | AZ96: =H96-(BB96+BD96) -> 0 | BA96: =I96-(BC96+BE96) -> 0 | BF96: =IFERROR(AZ96/L96,"-") -> - | BG96: =IFERROR(BA96/L96,"-") -> - | BH96: =IFERROR(BB96/M96,"-") -> - | BI96: =IFERROR(BC96/M96,"-") -> - | BJ96: =IFERROR(BD96/N96,"-") -> - | BK96: =IFERROR(BE96/N96,"-") -> - | BN96: =SUM(BL96:BM96) -> 0
A97: =LEFT(F97,4)+1 -> 2022 | B97: =RIGHT(F97,2) -> 39 | C97: {=_xlfn.IFS(_xlfn.NUMBERVALUE(B97)<=13,"Q1",AND(_xlfn.NUMBERVALUE(B97)>13,_xlfn.NUMBERVALUE(B97)<=26),"Q2", AND(_xlfn.NUMBERVALUE(B97)>26,_xlfn.NUMBERVALUE(B97)<=39),"Q3",_xlfn.NUMBERVALUE(B97)>39,"Q4")} -> Q3 | D97: =E96+1 -> 44492 | E97: =D97+6 -> 44498 | F97: 202139 | G97: =SUM(H97:I97) -> 0 | J97: =IFERROR(H97/G97,0) -> 0 | K97: =IFERROR(I97/G97,0) -> 0 | O97: =IFERROR(L97/$G97,0) -> 0 | P97: =IFERROR(M97/$G97,0) -> 0 | Q97: =IFERROR(N97/$G97,0) -> 0 | R97: =Forecast!J92 -> 0 | S97: =Forecast!N92 -> 0 | T97: =IF(OR(RIGHT(F97,2) = "01",G97 = 0),G97,T96+G97) -> 0 | U97: =IF(RIGHT(F97,2)="01",R97,R97+U96) -> 0 | V97: =IF(RIGHT(F97,2)="01",S97,S97+V96) -> 0 | W97: =X97+Y97 -> 0 | X97: ='Channel & Campaign Metrics'!AR96 -> 0 | Y97: ='Channel & Campaign Metrics'!BS96 -> 0 | AB97: ='Glass Metrics'!AC97 -> 0 | AC97: ='Glass Metrics'!I97 -> 0 | AD97: ='Glass Metrics'!N97 -> 0 | AE97: ='Glass Metrics'!S97 -> 0 | AF97: =IFERROR(AE97/AB97,"") | AG97: =IFERROR(AC97/AE97,"") | AH97: =IFERROR(AD97/AC97,"") | AI97: =IFERROR(G97/AB97,"") | AJ97: =IFERROR(((AK97*AM97)+(AL97*AN97))/(AM97+AN97),"") | AO97: =IFERROR(((AM97*(AK97+0.1))+(AN97*AL97))/(AM97+AN97),"") | AS97: =AP97-10% -> -0.1 | AV97: =SUM(AT97:AU97) -> 0 | AZ97: =H97-(BB97+BD97) -> 0 | BA97: =I97-(BC97+BE97) -> 0 | BF97: =IFERROR(AZ97/L97,"-") -> - | BG97: =IFERROR(BA97/L97,"-") -> - | BH97: =IFERROR(BB97/M97,"-") -> - | BI97: =IFERROR(BC97/M97,"-") -> - | BJ97: =IFERROR(BD97/N97,"-") -> - | BK97: =IFERROR(BE97/N97,"-") -> - | BN97: =SUM(BL97:BM97) -> 0
A98: =LEFT(F98,4)+1 -> 2022 | B98: =RIGHT(F98,2) -> 40 | C98: {=_xlfn.IFS(_xlfn.NUMBERVALUE(B98)<=13,"Q1",AND(_xlfn.NUMBERVALUE(B98)>13,_xlfn.NUMBERVALUE(B98)<=26),"Q2", AND(_xlfn.NUMBERVALUE(B98)>26,_xlfn.NUMBERVALUE(B98)<=39),"Q3",_xlfn.NUMBERVALUE(B98)>39,"Q4")} -> Q4 | D98: =E97+1 -> 44499 | E98: =D98+6 -> 44505 | F98: 202140 | G98: =SUM(H98:I98) -> 0 | J98: =IFERROR(H98/G98,0) -> 0 | K98: =IFERROR(I98/G98,0) -> 0 | O98: =IFERROR(L98/$G98,0) -> 0 | P98: =IFERROR(M98/$G98,0) -> 0 | Q98: =IFERROR(N98/$G98,0) -> 0 | R98: =Forecast!J93 -> 0 | S98: =Forecast!N93 -> 0 | T98: =IF(OR(RIGHT(F98,2) = "01",G98 = 0),G98,T97+G98) -> 0 | U98: =IF(RIGHT(F98,2)="01",R98,R98+U97) -> 0 | V98: =IF(RIGHT(F98,2)="01",S98,S98+V97) -> 0 | W98: =X98+Y98 -> 0 | X98: ='Channel & Campaign Metrics'!AR97 -> 0 | Y98: ='Channel & Campaign Metrics'!BS97 -> 0 | AB98: ='Glass Metrics'!AC98 -> 0 | AC98: ='Glass Metrics'!I98 -> 0 | AD98: ='Glass Metrics'!N98 -> 0 | AE98: ='Glass Metrics'!S98 -> 0 | AF98: =IFERROR(AE98/AB98,"") | AG98: =IFERROR(AC98/AE98,"") | AH98: =IFERROR(AD98/AC98,"") | AI98: =IFERROR(G98/AB98,"") | AJ98: =IFERROR(((AK98*AM98)+(AL98*AN98))/(AM98+AN98),"") | AO98: =IFERROR(((AM98*(AK98+0.1))+(AN98*AL98))/(AM98+AN98),"") | AS98: =AP98-10% -> -0.1 | AV98: =SUM(AT98:AU98) -> 0 | AZ98: =H98-(BB98+BD98) -> 0 | BA98: =I98-(BC98+BE98) -> 0 | BF98: =IFERROR(AZ98/L98,"-") -> - | BG98: =IFERROR(BA98/L98,"-") -> - | BH98: =IFERROR(BB98/M98,"-") -> - | BI98: =IFERROR(BC98/M98,"-") -> - | BJ98: =IFERROR(BD98/N98,"-") -> - | BK98: =IFERROR(BE98/N98,"-") -> - | BN98: =SUM(BL98:BM98) -> 0
A99: =LEFT(F99,4)+1 -> 2022 | B99: =RIGHT(F99,2) -> 41 | C99: {=_xlfn.IFS(_xlfn.NUMBERVALUE(B99)<=13,"Q1",AND(_xlfn.NUMBERVALUE(B99)>13,_xlfn.NUMBERVALUE(B99)<=26),"Q2", AND(_xlfn.NUMBERVALUE(B99)>26,_xlfn.NUMBERVALUE(B99)<=39),"Q3",_xlfn.NUMBERVALUE(B99)>39,"Q4")} -> Q4 | D99: =E98+1 -> 44506 | E99: =D99+6 -> 44512 | F99: 202141 | G99: =SUM(H99:I99) -> 0 | J99: =IFERROR(H99/G99,0) -> 0 | K99: =IFERROR(I99/G99,0) -> 0 | O99: =IFERROR(L99/$G99,0) -> 0 | P99: =IFERROR(M99/$G99,0) -> 0 | Q99: =IFERROR(N99/$G99,0) -> 0 | R99: =Forecast!J94 -> 0 | S99: =Forecast!N94 -> 0 | T99: =IF(OR(RIGHT(F99,2) = "01",G99 = 0),G99,T98+G99) -> 0 | U99: =IF(RIGHT(F99,2)="01",R99,R99+U98) -> 0 | V99: =IF(RIGHT(F99,2)="01",S99,S99+V98) -> 0 | W99: =X99+Y99 -> 0 | X99: ='Channel & Campaign Metrics'!AR98 -> 0 | Y99: ='Channel & Campaign Metrics'!BS98 -> 0 | AB99: ='Glass Metrics'!AC99 -> 0 | AC99: ='Glass Metrics'!I99 -> 0 | AD99: ='Glass Metrics'!N99 -> 0 | AE99: ='Glass Metrics'!S99 -> 0 | AF99: =IFERROR(AE99/AB99,"") | AG99: =IFERROR(AC99/AE99,"") | AH99: =IFERROR(AD99/AC99,"") | AI99: =IFERROR(G99/AB99,"") | AJ99: =IFERROR(((AK99*AM99)+(AL99*AN99))/(AM99+AN99),"") | AO99: =IFERROR(((AM99*(AK99+0.1))+(AN99*AL99))/(AM99+AN99),"") | AS99: =AP99-10% -> -0.1 | AV99: =SUM(AT99:AU99) -> 0 | AZ99: =H99-(BB99+BD99) -> 0 | BA99: =I99-(BC99+BE99) -> 0 | BF99: =IFERROR(AZ99/L99,"-") -> - | BG99: =IFERROR(BA99/L99,"-") -> - | BH99: =IFERROR(BB99/M99,"-") -> - | BI99: =IFERROR(BC99/M99,"-") -> - | BJ99: =IFERROR(BD99/N99,"-") -> - | BK99: =IFERROR(BE99/N99,"-") -> - | BN99: =SUM(BL99:BM99) -> 0
A100: =LEFT(F100,4)+1 -> 2022 | B100: =RIGHT(F100,2) -> 42 | C100: {=_xlfn.IFS(_xlfn.NUMBERVALUE(B100)<=13,"Q1",AND(_xlfn.NUMBERVALUE(B100)>13,_xlfn.NUMBERVALUE(B100)<=26),"Q2", AND(_xlfn.NUMBERVALUE(B100)>26,_xlfn.NUMBERVALUE(B100)<=39),"Q3",_xlfn.NUMBERVALUE(B100)>39,"Q4")} -> Q4 | D100: =E99+1 -> 44513 | E100: =D100+6 -> 44519 | F100: 202142 | G100: =SUM(H100:I100) -> 0 | J100: =IFERROR(H100/G100,0) -> 0 | K100: =IFERROR(I100/G100,0) -> 0 | O100: =IFERROR(L100/$G100,0) -> 0 | P100: =IFERROR(M100/$G100,0) -> 0 | Q100: =IFERROR(N100/$G100,0) -> 0 | R100: =Forecast!J95 -> 0 | S100: =Forecast!N95 -> 0 | T100: =IF(OR(RIGHT(F100,2) = "01",G100 = 0),G100,T99+G100) -> 0 | U100: =IF(RIGHT(F100,2)="01",R100,R100+U99) -> 0 | V100: =IF(RIGHT(F100,2)="01",S100,S100+V99) -> 0 | W100: =X100+Y100 -> 0 | X100: ='Channel & Campaign Metrics'!AR99 -> 0 | Y100: ='Channel & Campaign Metrics'!BS99 -> 0 | AB100: ='Glass Metrics'!AC100 -> 0 | AC100: ='Glass Metrics'!I100 -> 0 | AD100: ='Glass Metrics'!N100 -> 0 | AE100: ='Glass Metrics'!S100 -> 0 | AF100: =IFERROR(AE100/AB100,"") | AG100: =IFERROR(AC100/AE100,"") | AH100: =IFERROR(AD100/AC100,"") | AI100: =IFERROR(G100/AB100,"") | AJ100: =IFERROR(((AK100*AM100)+(AL100*AN100))/(AM100+AN100),"") | AO100: =IFERROR(((AM100*(AK100+0.1))+(AN100*AL100))/(AM100+AN100),"") | AS100: =AP100-10% -> -0.1 | AV100: =SUM(AT100:AU100) -> 0 | AZ100: =H100-(BB100+BD100) -> 0 | BA100: =I100-(BC100+BE100) -> 0 | BF100: =IFERROR(AZ100/L100,"-") -> - | BG100: =IFERROR(BA100/L100,"-") -> - | BH100: =IFERROR(BB100/M100,"-") -> - | BI100: =IFERROR(BC100/M100,"-") -> - | BJ100: =IFERROR(BD100/N100,"-") -> - | BK100: =IFERROR(BE100/N100,"-") -> - | BN100: =SUM(BL100:BM100) -> 0
A101: =LEFT(F101,4)+1 -> 2022 | B101: =RIGHT(F101,2) -> 43 | C101: {=_xlfn.IFS(_xlfn.NUMBERVALUE(B101)<=13,"Q1",AND(_xlfn.NUMBERVALUE(B101)>13,_xlfn.NUMBERVALUE(B101)<=26),"Q2", AND(_xlfn.NUMBERVALUE(B101)>26,_xlfn.NUMBERVALUE(B101)<=39),"Q3",_xlfn.NUMBERVALUE(B101)>39,"Q4")} -> Q4 | D101: =E100+1 -> 44520 | E101: =D101+6 -> 44526 | F101: 202143 | G101: =SUM(H101:I101) -> 0 | J101: =IFERROR(H101/G101,0) -> 0 | K101: =IFERROR(I101/G101,0) -> 0 | O101: =IFERROR(L101/$G101,0) -> 0 | P101: =IFERROR(M101/$G101,0) -> 0 | Q101: =IFERROR(N101/$G101,0) -> 0 | R101: =Forecast!J96 -> 0 | S101: =Forecast!N96 -> 0 | T101: =IF(OR(RIGHT(F101,2) = "01",G101 = 0),G101,T100+G101) -> 0 | U101: =IF(RIGHT(F101,2)="01",R101,R101+U100) -> 0 | V101: =IF(RIGHT(F101,2)="01",S101,S101+V100) -> 0 | W101: =X101+Y101 -> 0 | X101: ='Channel & Campaign Metrics'!AR100 -> 0 | Y101: ='Channel & Campaign Metrics'!BS100 -> 0 | AB101: ='Glass Metrics'!AC101 -> 0 | AC101: ='Glass Metrics'!I101 -> 0 | AD101: ='Glass Metrics'!N101 -> 0 | AE101: ='Glass Metrics'!S101 -> 0 | AF101: =IFERROR(AE101/AB101,"") | AG101: =IFERROR(AC101/AE101,"") | AH101: =IFERROR(AD101/AC101,"") | AI101: =IFERROR(G101/AB101,"") | AJ101: =IFERROR(((AK101*AM101)+(AL101*AN101))/(AM101+AN101),"") | AO101: =IFERROR(((AM101*(AK101+0.1))+(AN101*AL101))/(AM101+AN101),"") | AS101: =AP101-10% -> -0.1 | AV101: =SUM(AT101:AU101) -> 0 | AZ101: =H101-(BB101+BD101) -> 0 | BA101: =I101-(BC101+BE101) -> 0 | BF101: =IFERROR(AZ101/L101,"-") -> - | BG101: =IFERROR(BA101/L101,"-") -> - | BH101: =IFERROR(BB101/M101,"-") -> - | BI101: =IFERROR(BC101/M101,"-") -> - | BJ101: =IFERROR(BD101/N101,"-") -> - | BK101: =IFERROR(BE101/N101,"-") -> - | BN101: =SUM(BL101:BM101) -> 0
A102: =LEFT(F102,4)+1 -> 2022 | B102: =RIGHT(F102,2) -> 44 | C102: {=_xlfn.IFS(_xlfn.NUMBERVALUE(B102)<=13,"Q1",AND(_xlfn.NUMBERVALUE(B102)>13,_xlfn.NUMBERVALUE(B102)<=26),"Q2", AND(_xlfn.NUMBERVALUE(B102)>26,_xlfn.NUMBERVALUE(B102)<=39),"Q3",_xlfn.NUMBERVALUE(B102)>39,"Q4")} -> Q4 | D102: =E101+1 -> 44527 | E102: =D102+6 -> 44533 | F102: 202144 | G102: =SUM(H102:I102) -> 0 | J102: =IFERROR(H102/G102,0) -> 0 | K102: =IFERROR(I102/G102,0) -> 0 | O102: =IFERROR(L102/$G102,0) -> 0 | P102: =IFERROR(M102/$G102,0) -> 0 | Q102: =IFERROR(N102/$G102,0) -> 0 | R102: =Forecast!J97 -> 0 | S102: =Forecast!N97 -> 0 | T102: =IF(OR(RIGHT(F102,2) = "01",G102 = 0),G102,T101+G102) -> 0 | U102: =IF(RIGHT(F102,2)="01",R102,R102+U101) -> 0 | V102: =IF(RIGHT(F102,2)="01",S102,S102+V101) -> 0 | W102: =X102+Y102 -> 0 | X102: ='Channel & Campaign Metrics'!AR101 -> 0 | Y102: ='Channel & Campaign Metrics'!BS101 -> 0 | AB102: ='Glass Metrics'!AC102 -> 0 | AC102: ='Glass Metrics'!I102 -> 0 | AD102: ='Glass Metrics'!N102 -> 0 | AE102: ='Glass Metrics'!S102 -> 0 | AF102: =IFERROR(AE102/AB102,"") | AG102: =IFERROR(AC102/AE102,"") | AH102: =IFERROR(AD102/AC102,"") | AI102: =IFERROR(G102/AB102,"") | AJ102: =IFERROR(((AK102*AM102)+(AL102*AN102))/(AM102+AN102),"") | AO102: =IFERROR(((AM102*(AK102+0.1))+(AN102*AL102))/(AM102+AN102),"") | AS102: =AP102-10% -> -0.1 | AV102: =SUM(AT102:AU102) -> 0 | AZ102: =H102-(BB102+BD102) -> 0 | BA102: =I102-(BC102+BE102) -> 0 | BF102: =IFERROR(AZ102/L102,"-") -> - | BG102: =IFERROR(BA102/L102,"-") -> - | BH102: =IFERROR(BB102/M102,"-") -> - | BI102: =IFERROR(BC102/M102,"-") -> - | BJ102: =IFERROR(BD102/N102,"-") -> - | BK102: =IFERROR(BE102/N102,"-") -> - | BN102: =SUM(BL102:BM102) -> 0
A103: =LEFT(F103,4)+1 -> 2022 | B103: =RIGHT(F103,2) -> 45 | C103: {=_xlfn.IFS(_xlfn.NUMBERVALUE(B103)<=13,"Q1",AND(_xlfn.NUMBERVALUE(B103)>13,_xlfn.NUMBERVALUE(B103)<=26),"Q2", AND(_xlfn.NUMBERVALUE(B103)>26,_xlfn.NUMBERVALUE(B103)<=39),"Q3",_xlfn.NUMBERVALUE(B103)>39,"Q4")} -> Q4 | D103: =E102+1 -> 44534 | E103: =D103+6 -> 44540 | F103: 202145 | G103: =SUM(H103:I103) -> 0 | J103: =IFERROR(H103/G103,0) -> 0 | K103: =IFERROR(I103/G103,0) -> 0 | O103: =IFERROR(L103/$G103,0) -> 0 | P103: =IFERROR(M103/$G103,0) -> 0 | Q103: =IFERROR(N103/$G103,0) -> 0 | R103: =Forecast!J98 -> 0 | S103: =Forecast!N98 -> 0 | T103: =IF(OR(RIGHT(F103,2) = "01",G103 = 0),G103,T102+G103) -> 0 | U103: =IF(RIGHT(F103,2)="01",R103,R103+U102) -> 0 | V103: =IF(RIGHT(F103,2)="01",S103,S103+V102) -> 0 | W103: =X103+Y103 -> 0 | X103: ='Channel & Campaign Metrics'!AR102 -> 0 | Y103: ='Channel & Campaign Metrics'!BS102 -> 0 | AB103: ='Glass Metrics'!AC103 -> 0 | AC103: ='Glass Metrics'!I103 -> 0 | AD103: ='Glass Metrics'!N103 -> 0 | AE103: ='Glass Metrics'!S103 -> 0 | AF103: =IFERROR(AE103/AB103,"") | AG103: =IFERROR(AC103/AE103,"") | AH103: =IFERROR(AD103/AC103,"") | AI103: =IFERROR(G103/AB103,"") | AJ103: =IFERROR(((AK103*AM103)+(AL103*AN103))/(AM103+AN103),"") | AO103: =IFERROR(((AM103*(AK103+0.1))+(AN103*AL103))/(AM103+AN103),"") | AS103: =AP103-10% -> -0.1 | AV103: =SUM(AT103:AU103) -> 0 | AZ103: =H103-(BB103+BD103) -> 0 | BA103: =I103-(BC103+BE103) -> 0 | BF103: =IFERROR(AZ103/L103,"-") -> - | BG103: =IFERROR(BA103/L103,"-") -> - | BH103: =IFERROR(BB103/M103,"-") -> - | BI103: =IFERROR(BC103/M103,"-") -> - | BJ103: =IFERROR(BD103/N103,"-") -> - | BK103: =IFERROR(BE103/N103,"-") -> - | BN103: =SUM(BL103:BM103) -> 0
A104: =LEFT(F104,4)+1 -> 2022 | B104: =RIGHT(F104,2) -> 46 | C104: {=_xlfn.IFS(_xlfn.NUMBERVALUE(B104)<=13,"Q1",AND(_xlfn.NUMBERVALUE(B104)>13,_xlfn.NUMBERVALUE(B104)<=26),"Q2", AND(_xlfn.NUMBERVALUE(B104)>26,_xlfn.NUMBERVALUE(B104)<=39),"Q3",_xlfn.NUMBERVALUE(B104)>39,"Q4")} -> Q4 | D104: =E103+1 -> 44541 | E104: =D104+6 -> 44547 | F104: 202146 | G104: =SUM(H104:I104) -> 0 | J104: =IFERROR(H104/G104,0) -> 0 | K104: =IFERROR(I104/G104,0) -> 0 | O104: =IFERROR(L104/$G104,0) -> 0 | P104: =IFERROR(M104/$G104,0) -> 0 | Q104: =IFERROR(N104/$G104,0) -> 0 | R104: =Forecast!J99 -> 0 | S104: =Forecast!N99 -> 0 | T104: =IF(OR(RIGHT(F104,2) = "01",G104 = 0),G104,T103+G104) -> 0 | U104: =IF(RIGHT(F104,2)="01",R104,R104+U103) -> 0 | V104: =IF(RIGHT(F104,2)="01",S104,S104+V103) -> 0 | W104: =X104+Y104 -> 0 | X104: ='Channel & Campaign Metrics'!AR103 -> 0 | Y104: ='Channel & Campaign Metrics'!BS103 -> 0 | AB104: ='Glass Metrics'!AC104 -> 0 | AC104: ='Glass Metrics'!I104 -> 0 | AD104: ='Glass Metrics'!N104 -> 0 | AE104: ='Glass Metrics'!S104 -> 0 | AF104: =IFERROR(AE104/AB104,"") | AG104: =IFERROR(AC104/AE104,"") | AH104: =IFERROR(AD104/AC104,"") | AI104: =IFERROR(G104/AB104,"") | AJ104: =IFERROR(((AK104*AM104)+(AL104*AN104))/(AM104+AN104),"") | AO104: =IFERROR(((AM104*(AK104+0.1))+(AN104*AL104))/(AM104+AN104),"") | AS104: =AP104-10% -> -0.1 | AV104: =SUM(AT104:AU104) -> 0 | AZ104: =H104-(BB104+BD104) -> 0 | BA104: =I104-(BC104+BE104) -> 0 | BF104: =IFERROR(AZ104/L104,"-") -> - | BG104: =IFERROR(BA104/L104,"-") -> - | BH104: =IFERROR(BB104/M104,"-") -> - | BI104: =IFERROR(BC104/M104,"-") -> - | BJ104: =IFERROR(BD104/N104,"-") -> - | BK104: =IFERROR(BE104/N104,"-") -> - | BN104: =SUM(BL104:BM104) -> 0
... A110: =LEFT(F110,4)+1 -> 2022 | B110: =RIGHT(F110,2) -> 52 | C110: {=_xlfn.IFS(_xlfn.NUMBERVALUE(B110)<=13,"Q1",AND(_xlfn.NUMBERVALUE(B110)>13,_xlfn.NUMBERVALUE(B110)<=26),"Q2", AND(_xlfn.NUMBERVALUE(B110)>26,_xlfn.NUMBERVALUE(B110)<=39),"Q3",_xlfn.NUMBERVALUE(B110)>39,"Q4")} -> Q4 | D110: =E109+1 -> 44583 | E110: =D110+6 -> 44589 | F110: 202152 | G110: =SUM(H110:I110) -> 0 | J110: =IFERROR(H110/G110,0) -> 0 | K110: =IFERROR(I110/G110,0) -> 0 | O110: =IFERROR(L110/$G110,0) -> 0 | P110: =IFERROR(M110/$G110,0) -> 0 | Q110: =IFERROR(N110/$G110,0) -> 0 | R110: =Forecast!J105 -> 0 | S110: =Forecast!N105 -> 0 | T110: =IF(OR(RIGHT(F110,2) = "01",G110 = 0),G110,T109+G110) -> 0 | U110: =IF(RIGHT(F110,2)="01",R110,R110+U109) -> 0 | V110: =IF(RIGHT(F110,2)="01",S110,S110+V109) -> 0 | W110: =X110+Y110 -> 0 | X110: ='Channel & Campaign Metrics'!AR109 -> 0 | Y110: ='Channel & Campaign Metrics'!BS109 -> 0 | AB110: ='Glass Metrics'!AC110 -> 0 | AC110: ='Glass Metrics'!I110 -> 0 | AD110: ='Glass Metrics'!N110 -> 0 | AE110: ='Glass Metrics'!S110 -> 0 | AF110: =IFERROR(AE110/AB110,"") | AG110: =IFERROR(AC110/AE110,"") | AH110: =IFERROR(AD110/AC110,"") | AI110: =IFERROR(G110/AB110,"") | AJ110: =IFERROR(((AK110*AM110)+(AL110*AN110))/(AM110+AN110),"") | AO110: =IFERROR(((AM110*(AK110+0.1))+(AN110*AL110))/(AM110+AN110),"") | AS110: =AP110-10% -> -0.1 | AV110: =SUM(AT110:AU110) -> 0 | AZ110: =H110-(BB110+BD110) -> 0 | BA110: =I110-(BC110+BE110) -> 0 | BF110: =IFERROR(AZ110/L110,"-") -> - | BG110: =IFERROR(BA110/L110,"-") -> - | BH110: =IFERROR(BB110/M110,"-") -> - | BI110: =IFERROR(BC110/M110,"-") -> - | BJ110: =IFERROR(BD110/N110,"-") -> - | BK110: =IFERROR(BE110/N110,"-") -> - | BN110: =SUM(BL110:BM110) -> 0
A111: =LEFT(F111,4)+1 -> 2023 | B111: =RIGHT(F111,2) -> 01 | C111: {=_xlfn.IFS(_xlfn.NUMBERVALUE(B111)<=13,"Q1",AND(_xlfn.NUMBERVALUE(B111)>13,_xlfn.NUMBERVALUE(B111)<=26),"Q2", AND(_xlfn.NUMBERVALUE(B111)>26,_xlfn.NUMBERVALUE(B111)<=39),"Q3",_xlfn.NUMBERVALUE(B111)>39,"Q4")} -> Q1 | D111: =E110+1 -> 44590 | E111: =D111+6 -> 44596 | F111: 202201 | G111: =SUM(H111:I111) -> 0 | J111: =IFERROR(H111/G111,0) -> 0 | K111: =IFERROR(I111/G111,0) -> 0 | O111: =IFERROR(L111/$G111,0) -> 0 | P111: =IFERROR(M111/$G111,0) -> 0 | Q111: =IFERROR(N111/$G111,0) -> 0 | R111: =Forecast!J106 -> 0 | S111: =Forecast!N106 -> 0 | T111: =IF(OR(RIGHT(F111,2) = "01",G111 = 0),G111,T110+G111) -> 0 | U111: =IF(RIGHT(F111,2)="01",R111,R111+U110) -> 0 | V111: =IF(RIGHT(F111,2)="01",S111,S111+V110) -> 0 | W111: =X111+Y111 -> 0 | X111: ='Channel & Campaign Metrics'!AR110 -> 0 | Y111: ='Channel & Campaign Metrics'!BS110 -> 0 | AB111: ='Glass Metrics'!AC111 -> 0 | AC111: ='Glass Metrics'!I111 -> 0 | AD111: ='Glass Metrics'!N111 -> 0 | AE111: ='Glass Metrics'!S111 -> 0 | AF111: =IFERROR(AE111/AB111,"") | AG111: =IFERROR(AC111/AE111,"") | AH111: =IFERROR(AD111/AC111,"") | AI111: =IFERROR(G111/AB111,"") | AJ111: =IFERROR(((AK111*AM111)+(AL111*AN111))/(AM111+AN111),"") | AO111: =AJ111 | AS111: =AP111-10% -> -0.1 | AV111: =SUM(AT111:AU111) -> 0 | AW111: =BD111-AT111 -> 0 | AX111: =BE111-AU111 -> 0 | AY111: =SUM(AW111,AX111) -> 0 | AZ111: =H111-(BB111+BD111) -> 0 | BA111: =I111-(BC111+BE111) -> 0 | BF111: =IFERROR(AZ111/L111,"-") -> - | BG111: =IFERROR(BA111/L111,"-") -> - | BH111: =IFERROR(BB111/M111,"-") -> - | BI111: =IFERROR(BC111/M111,"-") -> - | BJ111: =IFERROR(BD111/N111,"-") -> - | BK111: =IFERROR(BE111/N111,"-") -> - | BN111: =SUM(BL111:BM111) -> 0
A112: =LEFT(F112,4)+1 -> 2023 | B112: =RIGHT(F112,2) -> 02 | C112: {=_xlfn.IFS(_xlfn.NUMBERVALUE(B112)<=13,"Q1",AND(_xlfn.NUMBERVALUE(B112)>13,_xlfn.NUMBERVALUE(B112)<=26),"Q2", AND(_xlfn.NUMBERVALUE(B112)>26,_xlfn.NUMBERVALUE(B112)<=39),"Q3",_xlfn.NUMBERVALUE(B112)>39,"Q4")} -> Q1 | D112: =E111+1 -> 44597 | E112: =D112+6 -> 44603 | F112: 202202 | G112: =SUM(H112:I112) -> 0 | J112: =IFERROR(H112/G112,0) -> 0 | K112: =IFERROR(I112/G112,0) -> 0 | O112: =IFERROR(L112/$G112,0) -> 0 | P112: =IFERROR(M112/$G112,0) -> 0 | Q112: =IFERROR(N112/$G112,0) -> 0 | R112: =Forecast!J107 -> 0 | S112: =Forecast!N107 -> 0 | T112: =IF(OR(RIGHT(F112,2) = "01",G112 = 0),G112,T111+G112) -> 0 | U112: =IF(RIGHT(F112,2)="01",R112,R112+U111) -> 0 | V112: =IF(RIGHT(F112,2)="01",S112,S112+V111) -> 0 | W112: =X112+Y112 -> 0 | X112: ='Channel & Campaign Metrics'!AR111 -> 0 | Y112: ='Channel & Campaign Metrics'!BS111 -> 0 | AB112: ='Glass Metrics'!AC112 -> 0 | AC112: ='Glass Metrics'!I112 -> 0 | AD112: ='Glass Metrics'!N112 -> 0 | AE112: ='Glass Metrics'!S112 -> 0 | AF112: =IFERROR(AE112/AB112,"") | AG112: =IFERROR(AC112/AE112,"") | AH112: =IFERROR(AD112/AC112,"") | AI112: =IFERROR(G112/AB112,"") | AJ112: =IFERROR(((AK112*AM112)+(AL112*AN112))/(AM112+AN112),"") | AO112: =AJ112 | AS112: =AP112-10% -> -0.1 | AV112: =SUM(AT112:AU112) -> 0 | AW112: =BD112-AT112 -> 0 | AX112: =BE112-AU112 -> 0 | AY112: =SUM(AW112,AX112) -> 0 | AZ112: =H112-(BB112+BD112) -> 0 | BA112: =I112-(BC112+BE112) -> 0 | BF112: =IFERROR(AZ112/L112,"-") -> - | BG112: =IFERROR(BA112/L112,"-") -> - | BH112: =IFERROR(BB112/M112,"-") -> - | BI112: =IFERROR(BC112/M112,"-") -> - | BJ112: =IFERROR(BD112/N112,"-") -> - | BK112: =IFERROR(BE112/N112,"-") -> - | BN112: =SUM(BL112:BM112) -> 0
A113: =LEFT(F113,4)+1 -> 2023 | B113: =RIGHT(F113,2) -> 03 | C113: {=_xlfn.IFS(_xlfn.NUMBERVALUE(B113)<=13,"Q1",AND(_xlfn.NUMBERVALUE(B113)>13,_xlfn.NUMBERVALUE(B113)<=26),"Q2", AND(_xlfn.NUMBERVALUE(B113)>26,_xlfn.NUMBERVALUE(B113)<=39),"Q3",_xlfn.NUMBERVALUE(B113)>39,"Q4")} -> Q1 | D113: =E112+1 -> 44604 | E113: =D113+6 -> 44610 | F113: 202203 | G113: =SUM(H113:I113) -> 0 | J113: =IFERROR(H113/G113,0) -> 0 | K113: =IFERROR(I113/G113,0) -> 0 | O113: =IFERROR(L113/$G113,0) -> 0 | P113: =IFERROR(M113/$G113,0) -> 0 | Q113: =IFERROR(N113/$G113,0) -> 0 | R113: =Forecast!J108 -> 0 | S113: =Forecast!N108 -> 0 | T113: =IF(OR(RIGHT(F113,2) = "01",G113 = 0),G113,T112+G113) -> 0 | U113: =IF(RIGHT(F113,2)="01",R113,R113+U112) -> 0 | V113: =IF(RIGHT(F113,2)="01",S113,S113+V112) -> 0 | W113: =X113+Y113 -> 0 | X113: ='Channel & Campaign Metrics'!AR112 -> 0 | Y113: ='Channel & Campaign Metrics'!BS112 -> 0 | AB113: ='Glass Metrics'!AC113 -> 0 | AC113: ='Glass Metrics'!I113 -> 0 | AD113: ='Glass Metrics'!N113 -> 0 | AE113: ='Glass Metrics'!S113 -> 0 | AF113: =IFERROR(AE113/AB113,"") | AG113: =IFERROR(AC113/AE113,"") | AH113: =IFERROR(AD113/AC113,"") | AI113: =IFERROR(G113/AB113,"") | AJ113: =IFERROR(((AK113*AM113)+(AL113*AN113))/(AM113+AN113),"") | AO113: =AJ113 | AS113: =AP113-10% -> -0.1 | AV113: =SUM(AT113:AU113) -> 0 | AW113: =BD113-AT113 -> 0 | AX113: =BE113-AU113 -> 0 | AY113: =SUM(AW113,AX113) -> 0 | AZ113: =H113-(BB113+BD113) -> 0 | BA113: =I113-(BC113+BE113) -> 0 | BF113: =IFERROR(AZ113/L113,"-") -> - | BG113: =IFERROR(BA113/L113,"-") -> - | BH113: =IFERROR(BB113/M113,"-") -> - | BI113: =IFERROR(BC113/M113,"-") -> - | BJ113: =IFERROR(BD113/N113,"-") -> - | BK113: =IFERROR(BE113/N113,"-") -> - | BN113: =SUM(BL113:BM113) -> 0
A114: =LEFT(F114,4)+1 -> 2023 | B114: =RIGHT(F114,2) -> 04 | C114: {=_xlfn.IFS(_xlfn.NUMBERVALUE(B114)<=13,"Q1",AND(_xlfn.NUMBERVALUE(B114)>13,_xlfn.NUMBERVALUE(B114)<=26),"Q2", AND(_xlfn.NUMBERVALUE(B114)>26,_xlfn.NUMBERVALUE(B114)<=39),"Q3",_xlfn.NUMBERVALUE(B114)>39,"Q4")} -> Q1 | D114: =E113+1 -> 44611 | E114: =D114+6 -> 44617 | F114: 202204 | G114: =SUM(H114:I114) -> 0 | J114: =IFERROR(H114/G114,0) -> 0 | K114: =IFERROR(I114/G114,0) -> 0 | O114: =IFERROR(L114/$G114,0) -> 0 | P114: =IFERROR(M114/$G114,0) -> 0 | Q114: =IFERROR(N114/$G114,0) -> 0 | R114: =Forecast!J109 -> 0 | S114: =Forecast!N109 -> 0 | T114: =IF(OR(RIGHT(F114,2) = "01",G114 = 0),G114,T113+G114) -> 0 | U114: =IF(RIGHT(F114,2)="01",R114,R114+U113) -> 0 | V114: =IF(RIGHT(F114,2)="01",S114,S114+V113) -> 0 | W114: =X114+Y114 -> 0 | X114: ='Channel & Campaign Metrics'!AR113 -> 0 | Y114: ='Channel & Campaign Metrics'!BS113 -> 0 | AB114: ='Glass Metrics'!AC114 -> 0 | AC114: ='Glass Metrics'!I114 -> 0 | AD114: ='Glass Metrics'!N114 -> 0 | AE114: ='Glass Metrics'!S114 -> 0 | AF114: =IFERROR(AE114/AB114,"") | AG114: =IFERROR(AC114/AE114,"") | AH114: =IFERROR(AD114/AC114,"") | AI114: =IFERROR(G114/AB114,"") | AJ114: =IFERROR(((AK114*AM114)+(AL114*AN114))/(AM114+AN114),"") | AO114: =AJ114 | AS114: =AP114-10% -> -0.1 | AV114: =SUM(AT114:AU114) -> 0 | AW114: =BD114-AT114 -> 0 | AX114: =BE114-AU114 -> 0 | AY114: =SUM(AW114,AX114) -> 0 | AZ114: =H114-(BB114+BD114) -> 0 | BA114: =I114-(BC114+BE114) -> 0 | BF114: =IFERROR(AZ114/L114,"-") -> - | BG114: =IFERROR(BA114/L114,"-") -> - | BH114: =IFERROR(BB114/M114,"-") -> - | BI114: =IFERROR(BC114/M114,"-") -> - | BJ114: =IFERROR(BD114/N114,"-") -> - | BK114: =IFERROR(BE114/N114,"-") -> - | BN114: =SUM(BL114:BM114) -> 0
A115: =LEFT(F115,4)+1 -> 2023 | B115: =RIGHT(F115,2) -> 05 | C115: {=_xlfn.IFS(_xlfn.NUMBERVALUE(B115)<=13,"Q1",AND(_xlfn.NUMBERVALUE(B115)>13,_xlfn.NUMBERVALUE(B115)<=26),"Q2", AND(_xlfn.NUMBERVALUE(B115)>26,_xlfn.NUMBERVALUE(B115)<=39),"Q3",_xlfn.NUMBERVALUE(B115)>39,"Q4")} -> Q1 | D115: =E114+1 -> 44618 | E115: =D115+6 -> 44624 | F115: 202205 | G115: =SUM(H115:I115) -> 0 | J115: =IFERROR(H115/G115,0) -> 0 | K115: =IFERROR(I115/G115,0) -> 0 | O115: =IFERROR(L115/$G115,0) -> 0 | P115: =IFERROR(M115/$G115,0) -> 0 | Q115: =IFERROR(N115/$G115,0) -> 0 | R115: =Forecast!J110 -> 0 | S115: =Forecast!N110 -> 0 | T115: =IF(OR(RIGHT(F115,2) = "01",G115 = 0),G115,T114+G115) -> 0 | U115: =IF(RIGHT(F115,2)="01",R115,R115+U114) -> 0 | V115: =IF(RIGHT(F115,2)="01",S115,S115+V114) -> 0 | W115: =X115+Y115 -> 0 | X115: ='Channel & Campaign Metrics'!AR114 -> 0 | Y115: ='Channel & Campaign Metrics'!BS114 -> 0 | AB115: ='Glass Metrics'!AC115 -> 0 | AC115: ='Glass Metrics'!I115 -> 0 | AD115: ='Glass Metrics'!N115 -> 0 | AE115: ='Glass Metrics'!S115 -> 0 | AF115: =IFERROR(AE115/AB115,"") | AG115: =IFERROR(AC115/AE115,"") | AH115: =IFERROR(AD115/AC115,"") | AI115: =IFERROR(G115/AB115,"") | AJ115: =IFERROR(((AK115*AM115)+(AL115*AN115))/(AM115+AN115),"") | AO115: =AJ115 | AS115: =AP115-10% -> -0.1 | AV115: =SUM(AT115:AU115) -> 0 | AW115: =BD115-AT115 -> 0 | AX115: =BE115-AU115 -> 0 | AY115: =SUM(AW115,AX115) -> 0 | AZ115: =H115-(BB115+BD115) -> 0 | BA115: =I115-(BC115+BE115) -> 0 | BF115: =IFERROR(AZ115/L115,"-") -> - | BG115: =IFERROR(BA115/L115,"-") -> - | BH115: =IFERROR(BB115/M115,"-") -> - | BI115: =IFERROR(BC115/M115,"-") -> - | BJ115: =IFERROR(BD115/N115,"-") -> - | BK115: =IFERROR(BE115/N115,"-") -> - | BN115: =SUM(BL115:BM115) -> 0
A116: =LEFT(F116,4)+1 -> 2023 | B116: =RIGHT(F116,2) -> 06 | C116: {=_xlfn.IFS(_xlfn.NUMBERVALUE(B116)<=13,"Q1",AND(_xlfn.NUMBERVALUE(B116)>13,_xlfn.NUMBERVALUE(B116)<=26),"Q2", AND(_xlfn.NUMBERVALUE(B116)>26,_xlfn.NUMBERVALUE(B116)<=39),"Q3",_xlfn.NUMBERVALUE(B116)>39,"Q4")} -> Q1 | D116: =E115+1 -> 44625 | E116: =D116+6 -> 44631 | F116: 202206 | G116: =SUM(H116:I116) -> 0 | J116: =IFERROR(H116/G116,0) -> 0 | K116: =IFERROR(I116/G116,0) -> 0 | O116: =IFERROR(L116/$G116,0) -> 0 | P116: =IFERROR(M116/$G116,0) -> 0 | Q116: =IFERROR(N116/$G116,0) -> 0 | R116: =Forecast!J111 -> 0 | S116: =Forecast!N111 -> 0 | T116: =IF(OR(RIGHT(F116,2) = "01",G116 = 0),G116,T115+G116) -> 0 | U116: =IF(RIGHT(F116,2)="01",R116,R116+U115) -> 0 | V116: =IF(RIGHT(F116,2)="01",S116,S116+V115) -> 0 | W116: =X116+Y116 -> 0 | X116: ='Channel & Campaign Metrics'!AR115 -> 0 | Y116: ='Channel & Campaign Metrics'!BS115 -> 0 | AB116: ='Glass Metrics'!AC116 -> 0 | AC116: ='Glass Metrics'!I116 -> 0 | AD116: ='Glass Metrics'!N116 -> 0 | AE116: ='Glass Metrics'!S116 -> 0 | AF116: =IFERROR(AE116/AB116,"") | AG116: =IFERROR(AC116/AE116,"") | AH116: =IFERROR(AD116/AC116,"") | AI116: =IFERROR(G116/AB116,"") | AJ116: =IFERROR(((AK116*AM116)+(AL116*AN116))/(AM116+AN116),"") | AO116: =AJ116 | AS116: =AP116-10% -> -0.1 | AV116: =SUM(AT116:AU116) -> 0 | AW116: =BD116-AT116 -> 0 | AX116: =BE116-AU116 -> 0 | AY116: =SUM(AW116,AX116) -> 0 | AZ116: =H116-(BB116+BD116) -> 0 | BA116: =I116-(BC116+BE116) -> 0 | BF116: =IFERROR(AZ116/L116,"-") -> - | BG116: =IFERROR(BA116/L116,"-") -> - | BH116: =IFERROR(BB116/M116,"-") -> - | BI116: =IFERROR(BC116/M116,"-") -> - | BJ116: =IFERROR(BD116/N116,"-") -> - | BK116: =IFERROR(BE116/N116,"-") -> - | BN116: =SUM(BL116:BM116) -> 0
A117: =LEFT(F117,4)+1 -> 2023 | B117: =RIGHT(F117,2) -> 07 | C117: {=_xlfn.IFS(_xlfn.NUMBERVALUE(B117)<=13,"Q1",AND(_xlfn.NUMBERVALUE(B117)>13,_xlfn.NUMBERVALUE(B117)<=26),"Q2", AND(_xlfn.NUMBERVALUE(B117)>26,_xlfn.NUMBERVALUE(B117)<=39),"Q3",_xlfn.NUMBERVALUE(B117)>39,"Q4")} -> Q1 | D117: =E116+1 -> 44632 | E117: =D117+6 -> 44638 | F117: 202207 | G117: =SUM(H117:I117) -> 0 | J117: =IFERROR(H117/G117,0) -> 0 | K117: =IFERROR(I117/G117,0) -> 0 | O117: =IFERROR(L117/$G117,0) -> 0 | P117: =IFERROR(M117/$G117,0) -> 0 | Q117: =IFERROR(N117/$G117,0) -> 0 | R117: =Forecast!J112 -> 0 | S117: =Forecast!N112 -> 0 | T117: =IF(OR(RIGHT(F117,2) = "01",G117 = 0),G117,T116+G117) -> 0 | U117: =IF(RIGHT(F117,2)="01",R117,R117+U116) -> 0 | V117: =IF(RIGHT(F117,2)="01",S117,S117+V116) -> 0 | W117: =X117+Y117 -> 0 | X117: ='Channel & Campaign Metrics'!AR116 -> 0 | Y117: ='Channel & Campaign Metrics'!BS116 -> 0 | AB117: ='Glass Metrics'!AC117 -> 0 | AC117: ='Glass Metrics'!I117 -> 0 | AD117: ='Glass Metrics'!N117 -> 0 | AE117: ='Glass Metrics'!S117 -> 0 | AF117: =IFERROR(AE117/AB117,"") | AG117: =IFERROR(AC117/AE117,"") | AH117: =IFERROR(AD117/AC117,"") | AI117: =IFERROR(G117/AB117,"") | AJ117: =IFERROR(((AK117*AM117)+(AL117*AN117))/(AM117+AN117),"") | AO117: =AJ117 | AS117: =AP117-10% -> -0.1 | AV117: =SUM(AT117:AU117) -> 0 | AW117: =BD117-AT117 -> 0 | AX117: =BE117-AU117 -> 0 | AY117: =SUM(AW117,AX117) -> 0 | AZ117: =H117-(BB117+BD117) -> 0 | BA117: =I117-(BC117+BE117) -> 0 | BF117: =IFERROR(AZ117/L117,"-") -> - | BG117: =IFERROR(BA117/L117,"-") -> - | BH117: =IFERROR(BB117/M117,"-") -> - | BI117: =IFERROR(BC117/M117,"-") -> - | BJ117: =IFERROR(BD117/N117,"-") -> - | BK117: =IFERROR(BE117/N117,"-") -> - | BN117: =SUM(BL117:BM117) -> 0
A118: =LEFT(F118,4)+1 -> 2023 | B118: =RIGHT(F118,2) -> 08 | C118: {=_xlfn.IFS(_xlfn.NUMBERVALUE(B118)<=13,"Q1",AND(_xlfn.NUMBERVALUE(B118)>13,_xlfn.NUMBERVALUE(B118)<=26),"Q2", AND(_xlfn.NUMBERVALUE(B118)>26,_xlfn.NUMBERVALUE(B118)<=39),"Q3",_xlfn.NUMBERVALUE(B118)>39,"Q4")} -> Q1 | D118: =E117+1 -> 44639 | E118: =D118+6 -> 44645 | F118: 202208 | G118: =SUM(H118:I118) -> 0 | J118: =IFERROR(H118/G118,0) -> 0 | K118: =IFERROR(I118/G118,0) -> 0 | O118: =IFERROR(L118/$G118,0) -> 0 | P118: =IFERROR(M118/$G118,0) -> 0 | Q118: =IFERROR(N118/$G118,0) -> 0 | R118: =Forecast!J113 -> 0 | S118: =Forecast!N113 -> 0 | T118: =IF(OR(RIGHT(F118,2) = "01",G118 = 0),G118,T117+G118) -> 0 | U118: =IF(RIGHT(F118,2)="01",R118,R118+U117) -> 0 | V118: =IF(RIGHT(F118,2)="01",S118,S118+V117) -> 0 | W118: =X118+Y118 -> 0 | X118: ='Channel & Campaign Metrics'!AR117 -> 0 | Y118: ='Channel & Campaign Metrics'!BS117 -> 0 | AB118: ='Glass Metrics'!AC118 -> 0 | AC118: ='Glass Metrics'!I118 -> 0 | AD118: ='Glass Metrics'!N118 -> 0 | AE118: ='Glass Metrics'!S118 -> 0 | AF118: =IFERROR(AE118/AB118,"") | AG118: =IFERROR(AC118/AE118,"") | AH118: =IFERROR(AD118/AC118,"") | AI118: =IFERROR(G118/AB118,"") | AJ118: =IFERROR(((AK118*AM118)+(AL118*AN118))/(AM118+AN118),"") | AO118: =AJ118 | AS118: =AP118-10% -> -0.1 | AV118: =SUM(AT118:AU118) -> 0 | AW118: =BD118-AT118 -> 0 | AX118: =BE118-AU118 -> 0 | AY118: =SUM(AW118,AX118) -> 0 | AZ118: =H118-(BB118+BD118) -> 0 | BA118: =I118-(BC118+BE118) -> 0 | BF118: =IFERROR(AZ118/L118,"-") -> - | BG118: =IFERROR(BA118/L118,"-") -> - | BH118: =IFERROR(BB118/M118,"-") -> - | BI118: =IFERROR(BC118/M118,"-") -> - | BJ118: =IFERROR(BD118/N118,"-") -> - | BK118: =IFERROR(BE118/N118,"-") -> - | BN118: =SUM(BL118:BM118) -> 0
A119: =LEFT(F119,4)+1 -> 2023 | B119: =RIGHT(F119,2) -> 09 | C119: {=_xlfn.IFS(_xlfn.NUMBERVALUE(B119)<=13,"Q1",AND(_xlfn.NUMBERVALUE(B119)>13,_xlfn.NUMBERVALUE(B119)<=26),"Q2", AND(_xlfn.NUMBERVALUE(B119)>26,_xlfn.NUMBERVALUE(B119)<=39),"Q3",_xlfn.NUMBERVALUE(B119)>39,"Q4")} -> Q1 | D119: =E118+1 -> 44646 | E119: =D119+6 -> 44652 | F119: 202209 | G119: =SUM(H119:I119) -> 0 | J119: =IFERROR(H119/G119,0) -> 0 | K119: =IFERROR(I119/G119,0) -> 0 | O119: =IFERROR(L119/$G119,0) -> 0 | P119: =IFERROR(M119/$G119,0) -> 0 | Q119: =IFERROR(N119/$G119,0) -> 0 | R119: =Forecast!J114 -> 0 | S119: =Forecast!N114 -> 0 | T119: =IF(OR(RIGHT(F119,2) = "01",G119 = 0),G119,T118+G119) -> 0 | U119: =IF(RIGHT(F119,2)="01",R119,R119+U118) -> 0 | V119: =IF(RIGHT(F119,2)="01",S119,S119+V118) -> 0 | W119: =X119+Y119 -> 0 | X119: ='Channel & Campaign Metrics'!AR118 -> 0 | Y119: ='Channel & Campaign Metrics'!BS118 -> 0 | AB119: ='Glass Metrics'!AC119 -> 0 | AC119: ='Glass Metrics'!I119 -> 0 | AD119: ='Glass Metrics'!N119 -> 0 | AE119: ='Glass Metrics'!S119 -> 0 | AF119: =IFERROR(AE119/AB119,"") | AG119: =IFERROR(AC119/AE119,"") | AH119: =IFERROR(AD119/AC119,"") | AI119: =IFERROR(G119/AB119,"") | AJ119: =IFERROR(((AK119*AM119)+(AL119*AN119))/(AM119+AN119),"") | AO119: =AJ119 | AS119: =AP119-10% -> -0.1 | AV119: =SUM(AT119:AU119) -> 0 | AW119: =BD119-AT119 -> 0 | AX119: =BE119-AU119 -> 0 | AY119: =SUM(AW119,AX119) -> 0 | AZ119: =H119-(BB119+BD119) -> 0 | BA119: =I119-(BC119+BE119) -> 0 | BF119: =IFERROR(AZ119/L119,"-") -> - | BG119: =IFERROR(BA119/L119,"-") -> - | BH119: =IFERROR(BB119/M119,"-") -> - | BI119: =IFERROR(BC119/M119,"-") -> - | BJ119: =IFERROR(BD119/N119,"-") -> - | BK119: =IFERROR(BE119/N119,"-") -> - | BN119: =SUM(BL119:BM119) -> 0
A120: =LEFT(F120,4)+1 -> 2023 | B120: =RIGHT(F120,2) -> 10 | C120: {=_xlfn.IFS(_xlfn.NUMBERVALUE(B120)<=13,"Q1",AND(_xlfn.NUMBERVALUE(B120)>13,_xlfn.NUMBERVALUE(B120)<=26),"Q2", AND(_xlfn.NUMBERVALUE(B120)>26,_xlfn.NUMBERVALUE(B120)<=39),"Q3",_xlfn.NUMBERVALUE(B120)>39,"Q4")} -> Q1 | D120: =E119+1 -> 44653 | E120: =D120+6 -> 44659 | F120: 202210 | G120: =SUM(H120:I120) -> 0 | J120: =IFERROR(H120/G120,0) -> 0 | K120: =IFERROR(I120/G120,0) -> 0 | O120: =IFERROR(L120/$G120,0) -> 0 | P120: =IFERROR(M120/$G120,0) -> 0 | Q120: =IFERROR(N120/$G120,0) -> 0 | R120: =Forecast!J115 -> 0 | S120: =Forecast!N115 -> 0 | T120: =IF(OR(RIGHT(F120,2) = "01",G120 = 0),G120,T119+G120) -> 0 | U120: =IF(RIGHT(F120,2)="01",R120,R120+U119) -> 0 | V120: =IF(RIGHT(F120,2)="01",S120,S120+V119) -> 0 | W120: =X120+Y120 -> 0 | X120: ='Channel & Campaign Metrics'!AR119 -> 0 | Y120: ='Channel & Campaign Metrics'!BS119 -> 0 | AB120: ='Glass Metrics'!AC120 -> 0 | AC120: ='Glass Metrics'!I120 -> 0 | AD120: ='Glass Metrics'!N120 -> 0 | AE120: ='Glass Metrics'!S120 -> 0 | AF120: =IFERROR(AE120/AB120,"") | AG120: =IFERROR(AC120/AE120,"") | AH120: =IFERROR(AD120/AC120,"") | AI120: =IFERROR(G120/AB120,"") | AJ120: =IFERROR(((AK120*AM120)+(AL120*AN120))/(AM120+AN120),"") | AO120: =AJ120 | AS120: =AP120-10% -> -0.1 | AV120: =SUM(AT120:AU120) -> 0 | AW120: =BD120-AT120 -> 0 | AX120: =BE120-AU120 -> 0 | AY120: =SUM(AW120,AX120) -> 0 | AZ120: =H120-(BB120+BD120) -> 0 | BA120: =I120-(BC120+BE120) -> 0 | BF120: =IFERROR(AZ120/L120,"-") -> - | BG120: =IFERROR(BA120/L120,"-") -> - | BH120: =IFERROR(BB120/M120,"-") -> - | BI120: =IFERROR(BC120/M120,"-") -> - | BJ120: =IFERROR(BD120/N120,"-") -> - | BK120: =IFERROR(BE120/N120,"-") -> - | BN120: =SUM(BL120:BM120) -> 0
A121: =LEFT(F121,4)+1 -> 2023 | B121: =RIGHT(F121,2) -> 11 | C121: {=_xlfn.IFS(_xlfn.NUMBERVALUE(B121)<=13,"Q1",AND(_xlfn.NUMBERVALUE(B121)>13,_xlfn.NUMBERVALUE(B121)<=26),"Q2", AND(_xlfn.NUMBERVALUE(B121)>26,_xlfn.NUMBERVALUE(B121)<=39),"Q3",_xlfn.NUMBERVALUE(B121)>39,"Q4")} -> Q1 | D121: =E120+1 -> 44660 | E121: =D121+6 -> 44666 | F121: 202211 | G121: =SUM(H121:I121) -> 0 | J121: =IFERROR(H121/G121,0) -> 0 | K121: =IFERROR(I121/G121,0) -> 0 | O121: =IFERROR(L121/$G121,0) -> 0 | P121: =IFERROR(M121/$G121,0) -> 0 | Q121: =IFERROR(N121/$G121,0) -> 0 | R121: =Forecast!J116 -> 0 | S121: =Forecast!N116 -> 0 | T121: =IF(OR(RIGHT(F121,2) = "01",G121 = 0),G121,T120+G121) -> 0 | U121: =IF(RIGHT(F121,2)="01",R121,R121+U120) -> 0 | V121: =IF(RIGHT(F121,2)="01",S121,S121+V120) -> 0 | W121: =X121+Y121 -> 0 | X121: ='Channel & Campaign Metrics'!AR120 -> 0 | Y121: ='Channel & Campaign Metrics'!BS120 -> 0 | AB121: ='Glass Metrics'!AC121 -> 0 | AC121: ='Glass Metrics'!I121 -> 0 | AD121: ='Glass Metrics'!N121 -> 0 | AE121: ='Glass Metrics'!S121 -> 0 | AF121: =IFERROR(AE121/AB121,"") | AG121: =IFERROR(AC121/AE121,"") | AH121: =IFERROR(AD121/AC121,"") | AI121: =IFERROR(G121/AB121,"") | AJ121: =IFERROR(((AK121*AM121)+(AL121*AN121))/(AM121+AN121),"") | AO121: =AJ121 | AS121: =AP121-10% -> -0.1 | AV121: =SUM(AT121:AU121) -> 0 | AW121: =BD121-AT121 -> 0 | AX121: =BE121-AU121 -> 0 | AY121: =SUM(AW121,AX121) -> 0 | AZ121: =H121-(BB121+BD121) -> 0 | BA121: =I121-(BC121+BE121) -> 0 | BF121: =IFERROR(AZ121/L121,"-") -> - | BG121: =IFERROR(BA121/L121,"-") -> - | BH121: =IFERROR(BB121/M121,"-") -> - | BI121: =IFERROR(BC121/M121,"-") -> - | BJ121: =IFERROR(BD121/N121,"-") -> - | BK121: =IFERROR(BE121/N121,"-") -> - | BN121: =SUM(BL121:BM121) -> 0
A122: =LEFT(F122,4)+1 -> 2023 | B122: =RIGHT(F122,2) -> 12 | C122: {=_xlfn.IFS(_xlfn.NUMBERVALUE(B122)<=13,"Q1",AND(_xlfn.NUMBERVALUE(B122)>13,_xlfn.NUMBERVALUE(B122)<=26),"Q2", AND(_xlfn.NUMBERVALUE(B122)>26,_xlfn.NUMBERVALUE(B122)<=39),"Q3",_xlfn.NUMBERVALUE(B122)>39,"Q4")} -> Q1 | D122: =E121+1 -> 44667 | E122: =D122+6 -> 44673 | F122: 202212 | G122: =SUM(H122:I122) -> 0 | J122: =IFERROR(H122/G122,0) -> 0 | K122: =IFERROR(I122/G122,0) -> 0 | O122: =IFERROR(L122/$G122,0) -> 0 | P122: =IFERROR(M122/$G122,0) -> 0 | Q122: =IFERROR(N122/$G122,0) -> 0 | R122: =Forecast!J117 -> 0 | S122: =Forecast!N117 -> 0 | T122: =IF(OR(RIGHT(F122,2) = "01",G122 = 0),G122,T121+G122) -> 0 | U122: =IF(RIGHT(F122,2)="01",R122,R122+U121) -> 0 | V122: =IF(RIGHT(F122,2)="01",S122,S122+V121) -> 0 | W122: =X122+Y122 -> 0 | X122: ='Channel & Campaign Metrics'!AR121 -> 0 | Y122: ='Channel & Campaign Metrics'!BS121 -> 0 | AB122: ='Glass Metrics'!AC122 -> 0 | AC122: ='Glass Metrics'!I122 -> 0 | AD122: ='Glass Metrics'!N122 -> 0 | AE122: ='Glass Metrics'!S122 -> 0 | AF122: =IFERROR(AE122/AB122,"") | AG122: =IFERROR(AC122/AE122,"") | AH122: =IFERROR(AD122/AC122,"") | AI122: =IFERROR(G122/AB122,"") | AJ122: =IFERROR(((AK122*AM122)+(AL122*AN122))/(AM122+AN122),"") | AO122: =AJ122 | AS122: =AP122-10% -> -0.1 | AV122: =SUM(AT122:AU122) -> 0 | AW122: =BD122-AT122 -> 0 | AX122: =BE122-AU122 -> 0 | AY122: =SUM(AW122,AX122) -> 0 | AZ122: =H122-(BB122+BD122) -> 0 | BA122: =I122-(BC122+BE122) -> 0 | BF122: =IFERROR(AZ122/L122,"-") -> - | BG122: =IFERROR(BA122/L122,"-") -> - | BH122: =IFERROR(BB122/M122,"-") -> - | BI122: =IFERROR(BC122/M122,"-") -> - | BJ122: =IFERROR(BD122/N122,"-") -> - | BK122: =IFERROR(BE122/N122,"-") -> - | BN122: =SUM(BL122:BM122) -> 0
... A144: =LEFT(F144,4)+1 -> 2023 | B144: =RIGHT(F144,2) -> 34 | C144: {=_xlfn.IFS(_xlfn.NUMBERVALUE(B144)<=13,"Q1",AND(_xlfn.NUMBERVALUE(B144)>13,_xlfn.NUMBERVALUE(B144)<=26),"Q2", AND(_xlfn.NUMBERVALUE(B144)>26,_xlfn.NUMBERVALUE(B144)<=39),"Q3",_xlfn.NUMBERVALUE(B144)>39,"Q4")} -> Q3 | D144: =E143+1 -> 44821 | E144: =D144+6 -> 44827 | F144: 202234 | G144: =SUM(H144:I144) -> 0 | J144: =IFERROR(H144/G144,0) -> 0 | K144: =IFERROR(I144/G144,0) -> 0 | O144: =IFERROR(L144/$G144,0) -> 0 | P144: =IFERROR(M144/$G144,0) -> 0 | Q144: =IFERROR(N144/$G144,0) -> 0 | R144: =Forecast!J139 -> 0 | S144: =Forecast!N139 -> 0 | T144: =IF(OR(RIGHT(F144,2) = "01",G144 = 0),G144,T143+G144) -> 0 | U144: =IF(RIGHT(F144,2)="01",R144,R144+U143) -> 0 | V144: =IF(RIGHT(F144,2)="01",S144,S144+V143) -> 0 | W144: =X144+Y144 -> 0 | X144: ='Channel & Campaign Metrics'!AR143 -> 0 | Y144: ='Channel & Campaign Metrics'!BS143 -> 0 | AB144: ='Glass Metrics'!AC144 -> 0 | AC144: ='Glass Metrics'!I144 -> 0 | AD144: ='Glass Metrics'!N144 -> 0 | AE144: ='Glass Metrics'!S144 -> 0 | AF144: =IFERROR(AE144/AB144,"") | AG144: =IFERROR(AC144/AE144,"") | AH144: =IFERROR(AD144/AC144,"") | AI144: =IFERROR(G144/AB144,"") | AJ144: =IFERROR(((AK144*AM144)+(AL144*AN144))/(AM144+AN144),"") | AO144: =AJ144 | AS144: =AP144-10% -> -0.1 | AV144: =SUM(AT144:AU144) -> 0 | AW144: =BD144-AT144 -> 0 | AX144: =BE144-AU144 -> 0 | AY144: =SUM(AW144,AX144) -> 0 | AZ144: =H144-(BB144+BD144) -> 0 | BA144: =I144-(BC144+BE144) -> 0 | BF144: =IFERROR(AZ144/L144,"-") -> - | BG144: =IFERROR(BA144/L144,"-") -> - | BH144: =IFERROR(BB144/M144,"-") -> - | BI144: =IFERROR(BC144/M144,"-") -> - | BJ144: =IFERROR(BD144/N144,"-") -> - | BK144: =IFERROR(BE144/N144,"-") -> - | BN144: =SUM(BL144:BM144) -> 0
A145: =LEFT(F145,4)+1 -> 2023 | B145: =RIGHT(F145,2) -> 35 | C145: {=_xlfn.IFS(_xlfn.NUMBERVALUE(B145)<=13,"Q1",AND(_xlfn.NUMBERVALUE(B145)>13,_xlfn.NUMBERVALUE(B145)<=26),"Q2", AND(_xlfn.NUMBERVALUE(B145)>26,_xlfn.NUMBERVALUE(B145)<=39),"Q3",_xlfn.NUMBERVALUE(B145)>39,"Q4")} -> Q3 | D145: =E144+1 -> 44828 | E145: =D145+6 -> 44834 | F145: 202235 | G145: =SUM(H145:I145) -> 0 | J145: =IFERROR(H145/G145,0) -> 0 | K145: =IFERROR(I145/G145,0) -> 0 | O145: =IFERROR(L145/$G145,0) -> 0 | P145: =IFERROR(M145/$G145,0) -> 0 | Q145: =IFERROR(N145/$G145,0) -> 0 | R145: =Forecast!J140 -> 0 | S145: =Forecast!N140 -> 0 | T145: =IF(OR(RIGHT(F145,2) = "01",G145 = 0),G145,T144+G145) -> 0 | U145: =IF(RIGHT(F145,2)="01",R145,R145+U144) -> 0 | V145: =IF(RIGHT(F145,2)="01",S145,S145+V144) -> 0 | W145: =X145+Y145 -> 0 | X145: ='Channel & Campaign Metrics'!AR144 -> 0 | Y145: ='Channel & Campaign Metrics'!BS144 -> 0 | AB145: ='Glass Metrics'!AC145 -> 0 | AC145: ='Glass Metrics'!I145 -> 0 | AD145: ='Glass Metrics'!N145 -> 0 | AE145: ='Glass Metrics'!S145 -> 0 | AF145: =IFERROR(AE145/AB145,"") | AG145: =IFERROR(AC145/AE145,"") | AH145: =IFERROR(AD145/AC145,"") | AI145: =IFERROR(G145/AB145,"") | AJ145: =IFERROR(((AK145*AM145)+(AL145*AN145))/(AM145+AN145),"") | AO145: =AJ145 | AS145: =AP145 -> 0 | AV145: =SUM(AT145:AU145) -> 0 | AW145: =BD145-AT145 -> 0 | AX145: =BE145-AU145 -> 0 | AY145: =SUM(AW145,AX145) -> 0 | AZ145: =H145-(BB145+BD145) -> 0 | BA145: =I145-(BC145+BE145) -> 0 | BF145: =IFERROR(AZ145/L145,"-") -> - | BG145: =IFERROR(BA145/L145,"-") -> - | BH145: =IFERROR(BB145/M145,"-") -> - | BI145: =IFERROR(BC145/M145,"-") -> - | BJ145: =IFERROR(BD145/N145,"-") -> - | BK145: =IFERROR(BE145/N145,"-") -> - | BN145: =SUM(BL145:BM145) -> 0
A146: =LEFT(F146,4)+1 -> 2023 | B146: =RIGHT(F146,2) -> 36 | C146: {=_xlfn.IFS(_xlfn.NUMBERVALUE(B146)<=13,"Q1",AND(_xlfn.NUMBERVALUE(B146)>13,_xlfn.NUMBERVALUE(B146)<=26),"Q2", AND(_xlfn.NUMBERVALUE(B146)>26,_xlfn.NUMBERVALUE(B146)<=39),"Q3",_xlfn.NUMBERVALUE(B146)>39,"Q4")} -> Q3 | D146: =E145+1 -> 44835 | E146: =D146+6 -> 44841 | F146: 202236 | G146: =SUM(H146:I146) -> 0 | J146: =IFERROR(H146/G146,0) -> 0 | K146: =IFERROR(I146/G146,0) -> 0 | O146: =IFERROR(L146/$G146,0) -> 0 | P146: =IFERROR(M146/$G146,0) -> 0 | Q146: =IFERROR(N146/$G146,0) -> 0 | R146: =Forecast!J141 -> 0 | S146: =Forecast!N141 -> 0 | T146: =IF(OR(RIGHT(F146,2) = "01",G146 = 0),G146,T145+G146) -> 0 | U146: =IF(RIGHT(F146,2)="01",R146,R146+U145) -> 0 | V146: =IF(RIGHT(F146,2)="01",S146,S146+V145) -> 0 | W146: =X146+Y146 -> 0 | X146: ='Channel & Campaign Metrics'!AR145 -> 0 | Y146: ='Channel & Campaign Metrics'!BS145 -> 0 | AB146: ='Glass Metrics'!AC146 -> 0 | AC146: ='Glass Metrics'!I146 -> 0 | AD146: ='Glass Metrics'!N146 -> 0 | AE146: ='Glass Metrics'!S146 -> 0 | AF146: =IFERROR(AE146/AB146,"") | AG146: =IFERROR(AC146/AE146,"") | AH146: =IFERROR(AD146/AC146,"") | AI146: =IFERROR(G146/AB146,"") | AJ146: =IFERROR(((AK146*AM146)+(AL146*AN146))/(AM146+AN146),"") | AO146: =AJ146 | AS146: =AP146 -> 0 | AV146: =SUM(AT146:AU146) -> 0 | AW146: =BD146-AT146 -> 0 | AX146: =BE146-AU146 -> 0 | AY146: =SUM(AW146,AX146) -> 0 | AZ146: =H146-(BB146+BD146) -> 0 | BA146: =I146-(BC146+BE146) -> 0 | BF146: =IFERROR(AZ146/L146,"-") -> - | BG146: =IFERROR(BA146/L146,"-") -> - | BH146: =IFERROR(BB146/M146,"-") -> - | BI146: =IFERROR(BC146/M146,"-") -> - | BJ146: =IFERROR(BD146/N146,"-") -> - | BK146: =IFERROR(BE146/N146,"-") -> - | BN146: =SUM(BL146:BM146) -> 0
A147: =LEFT(F147,4)+1 -> 2023 | B147: =RIGHT(F147,2) -> 37 | C147: {=_xlfn.IFS(_xlfn.NUMBERVALUE(B147)<=13,"Q1",AND(_xlfn.NUMBERVALUE(B147)>13,_xlfn.NUMBERVALUE(B147)<=26),"Q2", AND(_xlfn.NUMBERVALUE(B147)>26,_xlfn.NUMBERVALUE(B147)<=39),"Q3",_xlfn.NUMBERVALUE(B147)>39,"Q4")} -> Q3 | D147: =E146+1 -> 44842 | E147: =D147+6 -> 44848 | F147: 202237 | G147: =SUM(H147:I147) -> 0 | J147: =IFERROR(H147/G147,0) -> 0 | K147: =IFERROR(I147/G147,0) -> 0 | O147: =IFERROR(L147/$G147,0) -> 0 | P147: =IFERROR(M147/$G147,0) -> 0 | Q147: =IFERROR(N147/$G147,0) -> 0 | R147: =Forecast!J142 -> 0 | S147: =Forecast!N142 -> 0 | T147: =IF(OR(RIGHT(F147,2) = "01",G147 = 0),G147,T146+G147) -> 0 | U147: =IF(RIGHT(F147,2)="01",R147,R147+U146) -> 0 | V147: =IF(RIGHT(F147,2)="01",S147,S147+V146) -> 0 | W147: =X147+Y147 -> 0 | X147: ='Channel & Campaign Metrics'!AR146 -> 0 | Y147: ='Channel & Campaign Metrics'!BS146 -> 0 | AB147: ='Glass Metrics'!AC147 -> 0 | AC147: ='Glass Metrics'!I147 -> 0 | AD147: ='Glass Metrics'!N147 -> 0 | AE147: ='Glass Metrics'!S147 -> 0 | AF147: =IFERROR(AE147/AB147,"") | AG147: =IFERROR(AC147/AE147,"") | AH147: =IFERROR(AD147/AC147,"") | AI147: =IFERROR(G147/AB147,"") | AJ147: =IFERROR(((AK147*AM147)+(AL147*AN147))/(AM147+AN147),"") | AO147: =AJ147 | AS147: =AP147 -> 0 | AV147: =SUM(AT147:AU147) -> 0 | AW147: =BD147-AT147 -> 0 | AX147: =BE147-AU147 -> 0 | AY147: =SUM(AW147,AX147) -> 0 | AZ147: =H147-(BB147+BD147) -> 0 | BA147: =I147-(BC147+BE147) -> 0 | BF147: =IFERROR(AZ147/L147,"-") -> - | BG147: =IFERROR(BA147/L147,"-") -> - | BH147: =IFERROR(BB147/M147,"-") -> - | BI147: =IFERROR(BC147/M147,"-") -> - | BJ147: =IFERROR(BD147/N147,"-") -> - | BK147: =IFERROR(BE147/N147,"-") -> - | BN147: =SUM(BL147:BM147) -> 0
A148: =LEFT(F148,4)+1 -> 2023 | B148: =RIGHT(F148,2) -> 38 | C148: {=_xlfn.IFS(_xlfn.NUMBERVALUE(B148)<=13,"Q1",AND(_xlfn.NUMBERVALUE(B148)>13,_xlfn.NUMBERVALUE(B148)<=26),"Q2", AND(_xlfn.NUMBERVALUE(B148)>26,_xlfn.NUMBERVALUE(B148)<=39),"Q3",_xlfn.NUMBERVALUE(B148)>39,"Q4")} -> Q3 | D148: =E147+1 -> 44849 | E148: =D148+6 -> 44855 | F148: 202238 | G148: =SUM(H148:I148) -> 0 | J148: =IFERROR(H148/G148,0) -> 0 | K148: =IFERROR(I148/G148,0) -> 0 | O148: =IFERROR(L148/$G148,0) -> 0 | P148: =IFERROR(M148/$G148,0) -> 0 | Q148: =IFERROR(N148/$G148,0) -> 0 | R148: =Forecast!J143 -> 0 | S148: =Forecast!N143 -> 0 | T148: =IF(OR(RIGHT(F148,2) = "01",G148 = 0),G148,T147+G148) -> 0 | U148: =IF(RIGHT(F148,2)="01",R148,R148+U147) -> 0 | V148: =IF(RIGHT(F148,2)="01",S148,S148+V147) -> 0 | W148: =X148+Y148 -> 0 | X148: ='Channel & Campaign Metrics'!AR147 -> 0 | Y148: ='Channel & Campaign Metrics'!BS147 -> 0 | AB148: ='Glass Metrics'!AC148 -> 0 | AC148: ='Glass Metrics'!I148 -> 0 | AD148: ='Glass Metrics'!N148 -> 0 | AE148: ='Glass Metrics'!S148 -> 0 | AF148: =IFERROR(AE148/AB148,"") | AG148: =IFERROR(AC148/AE148,"") | AH148: =IFERROR(AD148/AC148,"") | AI148: =IFERROR(G148/AB148,"") | AJ148: =IFERROR(((AK148*AM148)+(AL148*AN148))/(AM148+AN148),"") | AO148: =AJ148 | AS148: =AP148 -> 0 | AV148: =SUM(AT148:AU148) -> 0 | AW148: =BD148-AT148 -> 0 | AX148: =BE148-AU148 -> 0 | AY148: =SUM(AW148,AX148) -> 0 | AZ148: =H148-(BB148+BD148) -> 0 | BA148: =I148-(BC148+BE148) -> 0 | BF148: =IFERROR(AZ148/L148,"-") -> - | BG148: =IFERROR(BA148/L148,"-") -> - | BH148: =IFERROR(BB148/M148,"-") -> - | BI148: =IFERROR(BC148/M148,"-") -> - | BJ148: =IFERROR(BD148/N148,"-") -> - | BK148: =IFERROR(BE148/N148,"-") -> - | BN148: =SUM(BL148:BM148) -> 0
A149: =LEFT(F149,4)+1 -> 2023 | B149: =RIGHT(F149,2) -> 39 | C149: {=_xlfn.IFS(_xlfn.NUMBERVALUE(B149)<=13,"Q1",AND(_xlfn.NUMBERVALUE(B149)>13,_xlfn.NUMBERVALUE(B149)<=26),"Q2", AND(_xlfn.NUMBERVALUE(B149)>26,_xlfn.NUMBERVALUE(B149)<=39),"Q3",_xlfn.NUMBERVALUE(B149)>39,"Q4")} -> Q3 | D149: =E148+1 -> 44856 | E149: =D149+6 -> 44862 | F149: 202239 | G149: =SUM(H149:I149) -> 0 | J149: =IFERROR(H149/G149,0) -> 0 | K149: =IFERROR(I149/G149,0) -> 0 | O149: =IFERROR(L149/$G149,0) -> 0 | P149: =IFERROR(M149/$G149,0) -> 0 | Q149: =IFERROR(N149/$G149,0) -> 0 | R149: =Forecast!J144 -> 0 | S149: =Forecast!N144 -> 0 | T149: =IF(OR(RIGHT(F149,2) = "01",G149 = 0),G149,T148+G149) -> 0 | U149: =IF(RIGHT(F149,2)="01",R149,R149+U148) -> 0 | V149: =IF(RIGHT(F149,2)="01",S149,S149+V148) -> 0 | W149: =X149+Y149 -> 0 | X149: ='Channel & Campaign Metrics'!AR148 -> 0 | Y149: ='Channel & Campaign Metrics'!BS148 -> 0 | AB149: ='Glass Metrics'!AC149 -> 0 | AC149: ='Glass Metrics'!I149 -> 0 | AD149: ='Glass Metrics'!N149 -> 0 | AE149: ='Glass Metrics'!S149 -> 0 | AF149: =IFERROR(AE149/AB149,"") | AG149: =IFERROR(AC149/AE149,"") | AH149: =IFERROR(AD149/AC149,"") | AI149: =IFERROR(G149/AB149,"") | AJ149: =IFERROR(((AK149*AM149)+(AL149*AN149))/(AM149+AN149),"") | AO149: =AJ149 | AS149: =AP149 -> 0 | AV149: =SUM(AT149:AU149) -> 0 | AW149: =BD149-AT149 -> 0 | AX149: =BE149-AU149 -> 0 | AY149: =SUM(AW149,AX149) -> 0 | AZ149: =H149-(BB149+BD149) -> 0 | BA149: =I149-(BC149+BE149) -> 0 | BF149: =IFERROR(AZ149/L149,"-") -> - | BG149: =IFERROR(BA149/L149,"-") -> - | BH149: =IFERROR(BB149/M149,"-") -> - | BI149: =IFERROR(BC149/M149,"-") -> - | BJ149: =IFERROR(BD149/N149,"-") -> - | BK149: =IFERROR(BE149/N149,"-") -> - | BN149: =SUM(BL149:BM149) -> 0
A150: =LEFT(F150,4)+1 -> 2023 | B150: =RIGHT(F150,2) -> 40 | C150: {=_xlfn.IFS(_xlfn.NUMBERVALUE(B150)<=13,"Q1",AND(_xlfn.NUMBERVALUE(B150)>13,_xlfn.NUMBERVALUE(B150)<=26),"Q2", AND(_xlfn.NUMBERVALUE(B150)>26,_xlfn.NUMBERVALUE(B150)<=39),"Q3",_xlfn.NUMBERVALUE(B150)>39,"Q4")} -> Q4 | D150: =E149+1 -> 44863 | E150: =D150+6 -> 44869 | F150: 202240 | G150: =SUM(H150:I150) -> 0 | J150: =IFERROR(H150/G150,0) -> 0 | K150: =IFERROR(I150/G150,0) -> 0 | O150: =IFERROR(L150/$G150,0) -> 0 | P150: =IFERROR(M150/$G150,0) -> 0 | Q150: =IFERROR(N150/$G150,0) -> 0 | R150: =Forecast!J145 -> 0 | S150: =Forecast!N145 -> 0 | T150: =IF(OR(RIGHT(F150,2) = "01",G150 = 0),G150,T149+G150) -> 0 | U150: =IF(RIGHT(F150,2)="01",R150,R150+U149) -> 0 | V150: =IF(RIGHT(F150,2)="01",S150,S150+V149) -> 0 | W150: =X150+Y150 -> 0 | X150: ='Channel & Campaign Metrics'!AR149 -> 0 | Y150: ='Channel & Campaign Metrics'!BS149 -> 0 | AB150: ='Glass Metrics'!AC150 -> 0 | AC150: ='Glass Metrics'!I150 -> 0 | AD150: ='Glass Metrics'!N150 -> 0 | AE150: ='Glass Metrics'!S150 -> 0 | AF150: =IFERROR(AE150/AB150,"") | AG150: =IFERROR(AC150/AE150,"") | AH150: =IFERROR(AD150/AC150,"") | AI150: =IFERROR(G150/AB150,"") | AJ150: =IFERROR(((AK150*AM150)+(AL150*AN150))/(AM150+AN150),"") | AO150: =AJ150 | AS150: =AP150 -> 0 | AV150: =SUM(AT150:AU150) -> 0 | AW150: =BD150-AT150 -> 0 | AX150: =BE150-AU150 -> 0 | AY150: =SUM(AW150,AX150) -> 0 | AZ150: =H150-(BB150+BD150) -> 0 | BA150: =I150-(BC150+BE150) -> 0 | BF150: =IFERROR(AZ150/L150,"-") -> - | BG150: =IFERROR(BA150/L150,"-") -> - | BH150: =IFERROR(BB150/M150,"-") -> - | BI150: =IFERROR(BC150/M150,"-") -> - | BJ150: =IFERROR(BD150/N150,"-") -> - | BK150: =IFERROR(BE150/N150,"-") -> - | BN150: =SUM(BL150:BM150) -> 0
A151: =LEFT(F151,4)+1 -> 2023 | B151: =RIGHT(F151,2) -> 41 | C151: {=_xlfn.IFS(_xlfn.NUMBERVALUE(B151)<=13,"Q1",AND(_xlfn.NUMBERVALUE(B151)>13,_xlfn.NUMBERVALUE(B151)<=26),"Q2", AND(_xlfn.NUMBERVALUE(B151)>26,_xlfn.NUMBERVALUE(B151)<=39),"Q3",_xlfn.NUMBERVALUE(B151)>39,"Q4")} -> Q4 | D151: =E150+1 -> 44870 | E151: =D151+6 -> 44876 | F151: 202241 | G151: =SUM(H151:I151) -> 0 | J151: =IFERROR(H151/G151,0) -> 0 | K151: =IFERROR(I151/G151,0) -> 0 | O151: =IFERROR(L151/$G151,0) -> 0 | P151: =IFERROR(M151/$G151,0) -> 0 | Q151: =IFERROR(N151/$G151,0) -> 0 | R151: =Forecast!J146 -> 0 | S151: =Forecast!N146 -> 0 | T151: =IF(OR(RIGHT(F151,2) = "01",G151 = 0),G151,T150+G151) -> 0 | U151: =IF(RIGHT(F151,2)="01",R151,R151+U150) -> 0 | V151: =IF(RIGHT(F151,2)="01",S151,S151+V150) -> 0 | W151: =X151+Y151 -> 0 | X151: ='Channel & Campaign Metrics'!AR150 -> 0 | Y151: ='Channel & Campaign Metrics'!BS150 -> 0 | AB151: ='Glass Metrics'!AC151 -> 0 | AC151: ='Glass Metrics'!I151 -> 0 | AD151: ='Glass Metrics'!N151 -> 0 | AE151: ='Glass Metrics'!S151 -> 0 | AF151: =IFERROR(AE151/AB151,"") | AG151: =IFERROR(AC151/AE151,"") | AH151: =IFERROR(AD151/AC151,"") | AI151: =IFERROR(G151/AB151,"") | AJ151: =IFERROR(((AK151*AM151)+(AL151*AN151))/(AM151+AN151),"") | AO151: =AJ151 | AS151: =AP151 -> 0 | AV151: =SUM(AT151:AU151) -> 0 | AW151: =BD151-AT151 -> 0 | AX151: =BE151-AU151 -> 0 | AY151: =SUM(AW151,AX151) -> 0 | AZ151: =H151-(BB151+BD151) -> 0 | BA151: =I151-(BC151+BE151) -> 0 | BF151: =IFERROR(AZ151/L151,"-") -> - | BG151: =IFERROR(BA151/L151,"-") -> - | BH151: =IFERROR(BB151/M151,"-") -> - | BI151: =IFERROR(BC151/M151,"-") -> - | BJ151: =IFERROR(BD151/N151,"-") -> - | BK151: =IFERROR(BE151/N151,"-") -> - | BN151: =SUM(BL151:BM151) -> 0
A152: =LEFT(F152,4)+1 -> 2023 | B152: =RIGHT(F152,2) -> 42 | C152: {=_xlfn.IFS(_xlfn.NUMBERVALUE(B152)<=13,"Q1",AND(_xlfn.NUMBERVALUE(B152)>13,_xlfn.NUMBERVALUE(B152)<=26),"Q2", AND(_xlfn.NUMBERVALUE(B152)>26,_xlfn.NUMBERVALUE(B152)<=39),"Q3",_xlfn.NUMBERVALUE(B152)>39,"Q4")} -> Q4 | D152: =E151+1 -> 44877 | E152: =D152+6 -> 44883 | F152: 202242 | G152: =SUM(H152:I152) -> 0 | J152: =IFERROR(H152/G152,0) -> 0 | K152: =IFERROR(I152/G152,0) -> 0 | O152: =IFERROR(L152/$G152,0) -> 0 | P152: =IFERROR(M152/$G152,0) -> 0 | Q152: =IFERROR(N152/$G152,0) -> 0 | R152: =Forecast!J147 -> 0 | S152: =Forecast!N147 -> 0 | T152: =IF(OR(RIGHT(F152,2) = "01",G152 = 0),G152,T151+G152) -> 0 | U152: =IF(RIGHT(F152,2)="01",R152,R152+U151) -> 0 | V152: =IF(RIGHT(F152,2)="01",S152,S152+V151) -> 0 | W152: =X152+Y152 -> 0 | X152: ='Channel & Campaign Metrics'!AR151 -> 0 | Y152: ='Channel & Campaign Metrics'!BS151 -> 0 | AB152: ='Glass Metrics'!AC152 -> 0 | AC152: ='Glass Metrics'!I152 -> 0 | AD152: ='Glass Metrics'!N152 -> 0 | AE152: ='Glass Metrics'!S152 -> 0 | AF152: =IFERROR(AE152/AB152,"") | AG152: =IFERROR(AC152/AE152,"") | AH152: =IFERROR(AD152/AC152,"") | AI152: =IFERROR(G152/AB152,"") | AJ152: =IFERROR(((AK152*AM152)+(AL152*AN152))/(AM152+AN152),"") | AO152: =AJ152 | AS152: =AP152 -> 0 | AV152: =SUM(AT152:AU152) -> 0 | AW152: =BD152-AT152 -> 0 | AX152: =BE152-AU152 -> 0 | AY152: =SUM(AW152,AX152) -> 0 | AZ152: =H152-(BB152+BD152) -> 0 | BA152: =I152-(BC152+BE152) -> 0 | BF152: =IFERROR(AZ152/L152,"-") -> - | BG152: =IFERROR(BA152/L152,"-") -> - | BH152: =IFERROR(BB152/M152,"-") -> - | BI152: =IFERROR(BC152/M152,"-") -> - | BJ152: =IFERROR(BD152/N152,"-") -> - | BK152: =IFERROR(BE152/N152,"-") -> - | BN152: =SUM(BL152:BM152) -> 0
A153: =LEFT(F153,4)+1 -> 2023 | B153: =RIGHT(F153,2) -> 43 | C153: {=_xlfn.IFS(_xlfn.NUMBERVALUE(B153)<=13,"Q1",AND(_xlfn.NUMBERVALUE(B153)>13,_xlfn.NUMBERVALUE(B153)<=26),"Q2", AND(_xlfn.NUMBERVALUE(B153)>26,_xlfn.NUMBERVALUE(B153)<=39),"Q3",_xlfn.NUMBERVALUE(B153)>39,"Q4")} -> Q4 | D153: =E152+1 -> 44884 | E153: =D153+6 -> 44890 | F153: 202243 | G153: =SUM(H153:I153) -> 0 | J153: =IFERROR(H153/G153,0) -> 0 | K153: =IFERROR(I153/G153,0) -> 0 | O153: =IFERROR(L153/$G153,0) -> 0 | P153: =IFERROR(M153/$G153,0) -> 0 | Q153: =IFERROR(N153/$G153,0) -> 0 | R153: =Forecast!J148 -> 0 | S153: =Forecast!N148 -> 0 | T153: =IF(OR(RIGHT(F153,2) = "01",G153 = 0),G153,T152+G153) -> 0 | U153: =IF(RIGHT(F153,2)="01",R153,R153+U152) -> 0 | V153: =IF(RIGHT(F153,2)="01",S153,S153+V152) -> 0 | W153: =X153+Y153 -> 0 | X153: ='Channel & Campaign Metrics'!AR152 -> 0 | Y153: ='Channel & Campaign Metrics'!BS152 -> 0 | AB153: ='Glass Metrics'!AC153 -> 0 | AC153: ='Glass Metrics'!I153 -> 0 | AD153: ='Glass Metrics'!N153 -> 0 | AE153: ='Glass Metrics'!S153 -> 0 | AF153: =IFERROR(AE153/AB153,"") | AG153: =IFERROR(AC153/AE153,"") | AH153: =IFERROR(AD153/AC153,"") | AI153: =IFERROR(G153/AB153,"") | AJ153: =IFERROR(((AK153*AM153)+(AL153*AN153))/(AM153+AN153),"") | AO153: =AJ153 | AS153: =AP153 -> 0 | AV153: =SUM(AT153:AU153) -> 0 | AW153: =BD153-AT153 -> 0 | AX153: =BE153-AU153 -> 0 | AY153: =SUM(AW153,AX153) -> 0 | AZ153: =H153-(BB153+BD153) -> 0 | BA153: =I153-(BC153+BE153) -> 0 | BF153: =IFERROR(AZ153/L153,"-") -> - | BG153: =IFERROR(BA153/L153,"-") -> - | BH153: =IFERROR(BB153/M153,"-") -> - | BI153: =IFERROR(BC153/M153,"-") -> - | BJ153: =IFERROR(BD153/N153,"-") -> - | BK153: =IFERROR(BE153/N153,"-") -> - | BN153: =SUM(BL153:BM153) -> 0
A154: =LEFT(F154,4)+1 -> 2023 | B154: =RIGHT(F154,2) -> 44 | C154: {=_xlfn.IFS(_xlfn.NUMBERVALUE(B154)<=13,"Q1",AND(_xlfn.NUMBERVALUE(B154)>13,_xlfn.NUMBERVALUE(B154)<=26),"Q2", AND(_xlfn.NUMBERVALUE(B154)>26,_xlfn.NUMBERVALUE(B154)<=39),"Q3",_xlfn.NUMBERVALUE(B154)>39,"Q4")} -> Q4 | D154: =E153+1 -> 44891 | E154: =D154+6 -> 44897 | F154: 202244 | G154: =SUM(H154:I154) -> 0 | J154: =IFERROR(H154/G154,0) -> 0 | K154: =IFERROR(I154/G154,0) -> 0 | O154: =IFERROR(L154/$G154,0) -> 0 | P154: =IFERROR(M154/$G154,0) -> 0 | Q154: =IFERROR(N154/$G154,0) -> 0 | R154: =Forecast!J149 -> 0 | S154: =Forecast!N149 -> 0 | T154: =IF(OR(RIGHT(F154,2) = "01",G154 = 0),G154,T153+G154) -> 0 | U154: =IF(RIGHT(F154,2)="01",R154,R154+U153) -> 0 | V154: =IF(RIGHT(F154,2)="01",S154,S154+V153) -> 0 | W154: =X154+Y154 -> 0 | X154: ='Channel & Campaign Metrics'!AR153 -> 0 | Y154: ='Channel & Campaign Metrics'!BS153 -> 0 | AB154: ='Glass Metrics'!AC154 -> 0 | AC154: ='Glass Metrics'!I154 -> 0 | AD154: ='Glass Metrics'!N154 -> 0 | AE154: ='Glass Metrics'!S154 -> 0 | AF154: =IFERROR(AE154/AB154,"") | AG154: =IFERROR(AC154/AE154,"") | AH154: =IFERROR(AD154/AC154,"") | AI154: =IFERROR(G154/AB154,"") | AJ154: =IFERROR(((AK154*AM154)+(AL154*AN154))/(AM154+AN154),"") | AO154: =AJ154 | AS154: =AP154 -> 0 | AV154: =SUM(AT154:AU154) -> 0 | AW154: =BD154-AT154 -> 0 | AX154: =BE154-AU154 -> 0 | AY154: =SUM(AW154,AX154) -> 0 | AZ154: =H154-(BB154+BD154) -> 0 | BA154: =I154-(BC154+BE154) -> 0 | BF154: =IFERROR(AZ154/L154,"-") -> - | BG154: =IFERROR(BA154/L154,"-") -> - | BH154: =IFERROR(BB154/M154,"-") -> - | BI154: =IFERROR(BC154/M154,"-") -> - | BJ154: =IFERROR(BD154/N154,"-") -> - | BK154: =IFERROR(BE154/N154,"-") -> - | BN154: =SUM(BL154:BM154) -> 0
A155: =LEFT(F155,4)+1 -> 2023 | B155: =RIGHT(F155,2) -> 45 | C155: {=_xlfn.IFS(_xlfn.NUMBERVALUE(B155)<=13,"Q1",AND(_xlfn.NUMBERVALUE(B155)>13,_xlfn.NUMBERVALUE(B155)<=26),"Q2", AND(_xlfn.NUMBERVALUE(B155)>26,_xlfn.NUMBERVALUE(B155)<=39),"Q3",_xlfn.NUMBERVALUE(B155)>39,"Q4")} -> Q4 | D155: =E154+1 -> 44898 | E155: =D155+6 -> 44904 | F155: 202245 | G155: =SUM(H155:I155) -> 0 | J155: =IFERROR(H155/G155,0) -> 0 | K155: =IFERROR(I155/G155,0) -> 0 | O155: =IFERROR(L155/$G155,0) -> 0 | P155: =IFERROR(M155/$G155,0) -> 0 | Q155: =IFERROR(N155/$G155,0) -> 0 | R155: =Forecast!J150 -> 0 | S155: =Forecast!N150 -> 0 | T155: =IF(OR(RIGHT(F155,2) = "01",G155 = 0),G155,T154+G155) -> 0 | U155: =IF(RIGHT(F155,2)="01",R155,R155+U154) -> 0 | V155: =IF(RIGHT(F155,2)="01",S155,S155+V154) -> 0 | W155: =X155+Y155 -> 0 | X155: ='Channel & Campaign Metrics'!AR154 -> 0 | Y155: ='Channel & Campaign Metrics'!BS154 -> 0 | AB155: ='Glass Metrics'!AC155 -> 0 | AC155: ='Glass Metrics'!I155 -> 0 | AD155: ='Glass Metrics'!N155 -> 0 | AE155: ='Glass Metrics'!S155 -> 0 | AF155: =IFERROR(AE155/AB155,"") | AG155: =IFERROR(AC155/AE155,"") | AH155: =IFERROR(AD155/AC155,"") | AI155: =IFERROR(G155/AB155,"") | AJ155: =IFERROR(((AK155*AM155)+(AL155*AN155))/(AM155+AN155),"") | AO155: =AJ155 | AS155: =AP155 -> 0 | AV155: =SUM(AT155:AU155) -> 0 | AW155: =BD155-AT155 -> 0 | AX155: =BE155-AU155 -> 0 | AY155: =SUM(AW155,AX155) -> 0 | AZ155: =H155-(BB155+BD155) -> 0 | BA155: =I155-(BC155+BE155) -> 0 | BF155: =IFERROR(AZ155/L155,"-") -> - | BG155: =IFERROR(BA155/L155,"-") -> - | BH155: =IFERROR(BB155/M155,"-") -> - | BI155: =IFERROR(BC155/M155,"-") -> - | BJ155: =IFERROR(BD155/N155,"-") -> - | BK155: =IFERROR(BE155/N155,"-") -> - | BN155: =SUM(BL155:BM155) -> 0
A156: =LEFT(F156,4)+1 -> 2023 | B156: =RIGHT(F156,2) -> 46 | C156: {=_xlfn.IFS(_xlfn.NUMBERVALUE(B156)<=13,"Q1",AND(_xlfn.NUMBERVALUE(B156)>13,_xlfn.NUMBERVALUE(B156)<=26),"Q2", AND(_xlfn.NUMBERVALUE(B156)>26,_xlfn.NUMBERVALUE(B156)<=39),"Q3",_xlfn.NUMBERVALUE(B156)>39,"Q4")} -> Q4 | D156: =E155+1 -> 44905 | E156: =D156+6 -> 44911 | F156: 202246 | G156: =SUM(H156:I156) -> 0 | J156: =IFERROR(H156/G156,0) -> 0 | K156: =IFERROR(I156/G156,0) -> 0 | O156: =IFERROR(L156/$G156,0) -> 0 | P156: =IFERROR(M156/$G156,0) -> 0 | Q156: =IFERROR(N156/$G156,0) -> 0 | R156: =Forecast!J151 -> 0 | S156: =Forecast!N151 -> 0 | T156: =IF(OR(RIGHT(F156,2) = "01",G156 = 0),G156,T155+G156) -> 0 | U156: =IF(RIGHT(F156,2)="01",R156,R156+U155) -> 0 | V156: =IF(RIGHT(F156,2)="01",S156,S156+V155) -> 0 | W156: =X156+Y156 -> 0 | X156: ='Channel & Campaign Metrics'!AR155 -> 0 | Y156: ='Channel & Campaign Metrics'!BS155 -> 0 | AB156: ='Glass Metrics'!AC156 -> 0 | AC156: ='Glass Metrics'!I156 -> 0 | AD156: ='Glass Metrics'!N156 -> 0 | AE156: ='Glass Metrics'!S156 -> 0 | AF156: =IFERROR(AE156/AB156,"") | AG156: =IFERROR(AC156/AE156,"") | AH156: =IFERROR(AD156/AC156,"") | AI156: =IFERROR(G156/AB156,"") | AJ156: =IFERROR(((AK156*AM156)+(AL156*AN156))/(AM156+AN156),"") | AO156: =AJ156 | AS156: =AP156 -> 0 | AV156: =SUM(AT156:AU156) -> 0 | AW156: =BD156-AT156 -> 0 | AX156: =BE156-AU156 -> 0 | AY156: =SUM(AW156,AX156) -> 0 | AZ156: =H156-(BB156+BD156) -> 0 | BA156: =I156-(BC156+BE156) -> 0 | BF156: =IFERROR(AZ156/L156,"-") -> - | BG156: =IFERROR(BA156/L156,"-") -> - | BH156: =IFERROR(BB156/M156,"-") -> - | BI156: =IFERROR(BC156/M156,"-") -> - | BJ156: =IFERROR(BD156/N156,"-") -> - | BK156: =IFERROR(BE156/N156,"-") -> - | BN156: =SUM(BL156:BM156) -> 0
... A193: =LEFT(F193,4)+1 -> 2024 | B193: =RIGHT(F193,2) -> 31 | C193: {=_xlfn.IFS(_xlfn.NUMBERVALUE(B193)<=13,"Q1",AND(_xlfn.NUMBERVALUE(B193)>13,_xlfn.NUMBERVALUE(B193)<=26),"Q2", AND(_xlfn.NUMBERVALUE(B193)>26,_xlfn.NUMBERVALUE(B193)<=39),"Q3",_xlfn.NUMBERVALUE(B193)>39,"Q4")} -> Q3 | D193: =E192+1 -> 45164 | E193: =D193+6 -> 45170 | F193: 202331 | G193: =SUM(H193:I193) -> 0 | J193: =IFERROR(H193/G193,0) -> 0 | K193: =IFERROR(I193/G193,0) -> 0 | O193: =IFERROR(L193/$G193,0) -> 0 | P193: =IFERROR(M193/$G193,0) -> 0 | Q193: =IFERROR(N193/$G193,0) -> 0 | R193: =Forecast!J188 -> 0 | S193: =Forecast!N188 -> 0 | T193: =IF(OR(RIGHT(F193,2) = "01",G193 = 0),G193,T192+G193) -> 0 | U193: =IF(RIGHT(F193,2)="01",R193,R193+U192) -> 0 | V193: =IF(RIGHT(F193,2)="01",S193,S193+V192) -> 0 | W193: =X193+Y193 -> 0 | X193: ='Channel & Campaign Metrics'!AR192 -> 0 | Y193: ='Channel & Campaign Metrics'!BS192 -> 0 | AB193: ='Glass Metrics'!AC193 -> 0 | AC193: ='Glass Metrics'!I193 -> 0 | AD193: ='Glass Metrics'!N193 -> 0 | AE193: ='Glass Metrics'!S193 -> 0 | AF193: =IFERROR(AE193/AB193,"") | AG193: =IFERROR(AC193/AE193,"") | AH193: =IFERROR(AD193/AC193,"") | AI193: =IFERROR(G193/AB193,"") | AJ193: =IFERROR(((AK193*AM193)+(AL193*AN193))/(AM193+AN193),"") | AO193: =AJ193 | AS193: =AP193 -> 0 | AV193: =SUM(AT193:AU193) -> 0 | AW193: =BD193-AT193 -> 0 | AX193: =BE193-AU193 -> 0 | AY193: =SUM(AW193,AX193) -> 0 | AZ193: =H193-(BB193+BD193) -> 0 | BA193: =I193-(BC193+BE193) -> 0 | BF193: =IFERROR(AZ193/L193,"-") -> - | BG193: =IFERROR(BA193/L193,"-") -> - | BH193: =IFERROR(BB193/M193,"-") -> - | BI193: =IFERROR(BC193/M193,"-") -> - | BJ193: =IFERROR(BD193/N193,"-") -> - | BK193: =IFERROR(BE193/N193,"-") -> - | BN193: =SUM(BL193:BM193) -> 0
A194: =LEFT(F194,4)+1 -> 2024 | B194: =RIGHT(F194,2) -> 32 | C194: {=_xlfn.IFS(_xlfn.NUMBERVALUE(B194)<=13,"Q1",AND(_xlfn.NUMBERVALUE(B194)>13,_xlfn.NUMBERVALUE(B194)<=26),"Q2", AND(_xlfn.NUMBERVALUE(B194)>26,_xlfn.NUMBERVALUE(B194)<=39),"Q3",_xlfn.NUMBERVALUE(B194)>39,"Q4")} -> Q3 | D194: =E193+1 -> 45171 | E194: =D194+6 -> 45177 | F194: 202332 | G194: =SUM(H194:I194) -> 0 | J194: =IFERROR(H194/G194,0) -> 0 | K194: =IFERROR(I194/G194,0) -> 0 | O194: =IFERROR(L194/$G194,0) -> 0 | P194: =IFERROR(M194/$G194,0) -> 0 | Q194: =IFERROR(N194/$G194,0) -> 0 | R194: =Forecast!J189 -> 0 | S194: =Forecast!N189 -> 0 | T194: =IF(OR(RIGHT(F194,2) = "01",G194 = 0),G194,T193+G194) -> 0 | U194: =IF(RIGHT(F194,2)="01",R194,R194+U193) -> 0 | V194: =IF(RIGHT(F194,2)="01",S194,S194+V193) -> 0 | W194: =X194+Y194 -> 367979.29 | X194: 318667.59 | Y194: 49311.7 | AB194: ='Glass Metrics'!AC194 -> 0 | AC194: ='Glass Metrics'!I194 -> 0 | AD194: ='Glass Metrics'!N194 -> 0 | AE194: ='Glass Metrics'!S194 -> 0 | AF194: =IFERROR(AE194/AB194,"") | AG194: =IFERROR(AC194/AE194,"") | AH194: =IFERROR(AD194/AC194,"") | AI194: =IFERROR(G194/AB194,"") | AJ194: =IFERROR(((AK194*AM194)+(AL194*AN194))/(AM194+AN194),"") | AO194: =AJ194 | AS194: =AP194 -> 0 | AV194: =SUM(AT194:AU194) -> 0 | AW194: =BD194-AT194 -> 0 | AX194: =BE194-AU194 -> 0 | AY194: =SUM(AW194,AX194) -> 0 | AZ194: =H194-(BB194+BD194) -> 0 | BA194: =I194-(BC194+BE194) -> 0 | BF194: =IFERROR(AZ194/L194,"-") -> - | BG194: =IFERROR(BA194/L194,"-") -> - | BH194: =IFERROR(BB194/M194,"-") -> - | BI194: =IFERROR(BC194/M194,"-") -> - | BJ194: =IFERROR(BD194/N194,"-") -> - | BK194: =IFERROR(BE194/N194,"-") -> - | BN194: =SUM(BL194:BM194) -> 0
A195: =LEFT(F195,4)+1 -> 2024 | B195: =RIGHT(F195,2) -> 33 | C195: {=_xlfn.IFS(_xlfn.NUMBERVALUE(B195)<=13,"Q1",AND(_xlfn.NUMBERVALUE(B195)>13,_xlfn.NUMBERVALUE(B195)<=26),"Q2", AND(_xlfn.NUMBERVALUE(B195)>26,_xlfn.NUMBERVALUE(B195)<=39),"Q3",_xlfn.NUMBERVALUE(B195)>39,"Q4")} -> Q3 | D195: =E194+1 -> 45178 | E195: =D195+6 -> 45184 | F195: 202333 | G195: =SUM(H195:I195) -> 0 | J195: =IFERROR(H195/G195,0) -> 0 | K195: =IFERROR(I195/G195,0) -> 0 | O195: =IFERROR(L195/$G195,0) -> 0 | P195: =IFERROR(M195/$G195,0) -> 0 | Q195: =IFERROR(N195/$G195,0) -> 0 | R195: =Forecast!J190 -> 0 | S195: =Forecast!N190 -> 0 | T195: =IF(OR(RIGHT(F195,2) = "01",G195 = 0),G195,T194+G195) -> 0 | U195: =IF(RIGHT(F195,2)="01",R195,R195+U194) -> 0 | V195: =IF(RIGHT(F195,2)="01",S195,S195+V194) -> 0 | W195: =X195+Y195 -> 0 | X195: ='Channel & Campaign Metrics'!AR194 -> 0 | Y195: ='Channel & Campaign Metrics'!BS194 -> 0 | AB195: ='Glass Metrics'!AC195 -> 0 | AC195: ='Glass Metrics'!I195 -> 0 | AD195: ='Glass Metrics'!N195 -> 0 | AE195: ='Glass Metrics'!S195 -> 0 | AF195: =IFERROR(AE195/AB195,"") | AG195: =IFERROR(AC195/AE195,"") | AH195: =IFERROR(AD195/AC195,"") | AI195: =IFERROR(G195/AB195,"") | AJ195: =IFERROR(((AK195*AM195)+(AL195*AN195))/(AM195+AN195),"") | AO195: =AJ195 | AS195: =AP195 -> 0 | AV195: =SUM(AT195:AU195) -> 0 | AW195: =BD195-AT195 -> 0 | AX195: =BE195-AU195 -> 0 | AY195: =SUM(AW195,AX195) -> 0 | AZ195: =H195-(BB195+BD195) -> 0 | BA195: =I195-(BC195+BE195) -> 0 | BF195: =IFERROR(AZ195/L195,"-") -> - | BG195: =IFERROR(BA195/L195,"-") -> - | BH195: =IFERROR(BB195/M195,"-") -> - | BI195: =IFERROR(BC195/M195,"-") -> - | BJ195: =IFERROR(BD195/N195,"-") -> - | BK195: =IFERROR(BE195/N195,"-") -> - | BN195: =SUM(BL195:BM195) -> 0
A196: =LEFT(F196,4)+1 -> 2024 | B196: =RIGHT(F196,2) -> 34 | C196: {=_xlfn.IFS(_xlfn.NUMBERVALUE(B196)<=13,"Q1",AND(_xlfn.NUMBERVALUE(B196)>13,_xlfn.NUMBERVALUE(B196)<=26),"Q2", AND(_xlfn.NUMBERVALUE(B196)>26,_xlfn.NUMBERVALUE(B196)<=39),"Q3",_xlfn.NUMBERVALUE(B196)>39,"Q4")} -> Q3 | D196: =E195+1 -> 45185 | E196: =D196+6 -> 45191 | F196: 202334 | G196: =SUM(H196:I196) -> 0 | J196: =IFERROR(H196/G196,0) -> 0 | K196: =IFERROR(I196/G196,0) -> 0 | O196: =IFERROR(L196/$G196,0) -> 0 | P196: =IFERROR(M196/$G196,0) -> 0 | Q196: =IFERROR(N196/$G196,0) -> 0 | R196: =Forecast!J191 -> 0 | S196: =Forecast!N191 -> 0 | T196: =IF(OR(RIGHT(F196,2) = "01",G196 = 0),G196,T195+G196) -> 0 | U196: =IF(RIGHT(F196,2)="01",R196,R196+U195) -> 0 | V196: =IF(RIGHT(F196,2)="01",S196,S196+V195) -> 0 | W196: =X196+Y196 -> 0 | X196: ='Channel & Campaign Metrics'!AR195 -> 0 | Y196: ='Channel & Campaign Metrics'!BS195 -> 0 | AB196: ='Glass Metrics'!AC196 -> 0 | AC196: ='Glass Metrics'!I196 -> 0 | AD196: ='Glass Metrics'!N196 -> 0 | AE196: ='Glass Metrics'!S196 -> 0 | AF196: =IFERROR(AE196/AB196,"") | AG196: =IFERROR(AC196/AE196,"") | AH196: =IFERROR(AD196/AC196,"") | AI196: =IFERROR(G196/AB196,"") | AJ196: =IFERROR(((AK196*AM196)+(AL196*AN196))/(AM196+AN196),"") | AO196: =AJ196 | AS196: =AP196 -> 0 | AV196: =SUM(AT196:AU196) -> 0 | AW196: =BD196-AT196 -> 0 | AX196: =BE196-AU196 -> 0 | AY196: =SUM(AW196,AX196) -> 0 | AZ196: =H196-(BB196+BD196) -> 0 | BA196: =I196-(BC196+BE196) -> 0 | BF196: =IFERROR(AZ196/L196,"-") -> - | BG196: =IFERROR(BA196/L196,"-") -> - | BH196: =IFERROR(BB196/M196,"-") -> - | BI196: =IFERROR(BC196/M196,"-") -> - | BJ196: =IFERROR(BD196/N196,"-") -> - | BK196: =IFERROR(BE196/N196,"-") -> - | BN196: =SUM(BL196:BM196) -> 0
A197: =LEFT(F197,4)+1 -> 2024 | B197: =RIGHT(F197,2) -> 35 | C197: {=_xlfn.IFS(_xlfn.NUMBERVALUE(B197)<=13,"Q1",AND(_xlfn.NUMBERVALUE(B197)>13,_xlfn.NUMBERVALUE(B197)<=26),"Q2", AND(_xlfn.NUMBERVALUE(B197)>26,_xlfn.NUMBERVALUE(B197)<=39),"Q3",_xlfn.NUMBERVALUE(B197)>39,"Q4")} -> Q3 | D197: =E196+1 -> 45192 | E197: =D197+6 -> 45198 | F197: 202335 | G197: =SUM(H197:I197) -> 0 | J197: =IFERROR(H197/G197,0) -> 0 | K197: =IFERROR(I197/G197,0) -> 0 | O197: =IFERROR(L197/$G197,0) -> 0 | P197: =IFERROR(M197/$G197,0) -> 0 | Q197: =IFERROR(N197/$G197,0) -> 0 | R197: =Forecast!J192 -> 0 | S197: =Forecast!N192 -> 0 | T197: =IF(OR(RIGHT(F197,2) = "01",G197 = 0),G197,T196+G197) -> 0 | U197: =IF(RIGHT(F197,2)="01",R197,R197+U196) -> 0 | V197: =IF(RIGHT(F197,2)="01",S197,S197+V196) -> 0 | W197: =X197+Y197 -> 0 | X197: ='Channel & Campaign Metrics'!AR196 -> 0 | Y197: ='Channel & Campaign Metrics'!BS196 -> 0 | AB197: ='Glass Metrics'!AC197 -> 0 | AC197: ='Glass Metrics'!I197 -> 0 | AD197: ='Glass Metrics'!N197 -> 0 | AE197: ='Glass Metrics'!S197 -> 0 | AF197: =IFERROR(AE197/AB197,"") | AG197: =IFERROR(AC197/AE197,"") | AH197: =IFERROR(AD197/AC197,"") | AI197: =IFERROR(G197/AB197,"") | AJ197: =IFERROR(((AK197*AM197)+(AL197*AN197))/(AM197+AN197),"") | AO197: =AJ197 | AS197: =AP197 -> 0 | AV197: =SUM(AT197:AU197) -> 0 | AW197: =BD197-AT197 -> 0 | AX197: =BE197-AU197 -> 0 | AY197: =SUM(AW197,AX197) -> 0 | AZ197: =H197-(BB197+BD197) -> 0 | BA197: =I197-(BC197+BE197) -> 0 | BF197: =IFERROR(AZ197/L197,"-") -> - | BG197: =IFERROR(BA197/L197,"-") -> - | BH197: =IFERROR(BB197/M197,"-") -> - | BI197: =IFERROR(BC197/M197,"-") -> - | BJ197: =IFERROR(BD197/N197,"-") -> - | BK197: =IFERROR(BE197/N197,"-") -> - | BN197: =SUM(BL197:BM197) -> 0
A198: =LEFT(F198,4)+1 -> 2024 | B198: =RIGHT(F198,2) -> 36 | C198: {=_xlfn.IFS(_xlfn.NUMBERVALUE(B198)<=13,"Q1",AND(_xlfn.NUMBERVALUE(B198)>13,_xlfn.NUMBERVALUE(B198)<=26),"Q2", AND(_xlfn.NUMBERVALUE(B198)>26,_xlfn.NUMBERVALUE(B198)<=39),"Q3",_xlfn.NUMBERVALUE(B198)>39,"Q4")} -> Q3 | D198: =E197+1 -> 45199 | E198: =D198+6 -> 45205 | F198: 202336 | G198: =SUM(H198:I198) -> 0 | J198: =IFERROR(H198/G198,0) -> 0 | K198: =IFERROR(I198/G198,0) -> 0 | O198: =IFERROR(L198/$G198,0) -> 0 | P198: =IFERROR(M198/$G198,0) -> 0 | Q198: =IFERROR(N198/$G198,0) -> 0 | R198: =Forecast!J193 -> 0 | S198: =Forecast!N193 -> 0 | T198: =IF(OR(RIGHT(F198,2) = "01",G198 = 0),G198,T197+G198) -> 0 | U198: =IF(RIGHT(F198,2)="01",R198,R198+U197) -> 0 | V198: =IF(RIGHT(F198,2)="01",S198,S198+V197) -> 0 | W198: =X198+Y198 -> 0 | X198: ='Channel & Campaign Metrics'!AR197 -> 0 | Y198: ='Channel & Campaign Metrics'!BS197 -> 0 | AB198: ='Glass Metrics'!AC198 -> 0 | AC198: ='Glass Metrics'!I198 -> 0 | AD198: ='Glass Metrics'!N198 -> 0 | AE198: ='Glass Metrics'!S198 -> 0 | AF198: =IFERROR(AE198/AB198,"") | AG198: =IFERROR(AC198/AE198,"") | AH198: =IFERROR(AD198/AC198,"") | AI198: =IFERROR(G198/AB198,"") | AJ198: =IFERROR(((AK198*AM198)+(AL198*AN198))/(AM198+AN198),"") | AO198: =AJ198 | AS198: =AP198 -> 0 | AV198: =SUM(AT198:AU198) -> 0 | AW198: =BD198-AT198 -> 0 | AX198: =BE198-AU198 -> 0 | AY198: =SUM(AW198,AX198) -> 0 | AZ198: =H198-(BB198+BD198) -> 0 | BA198: =I198-(BC198+BE198) -> 0 | BF198: =IFERROR(AZ198/L198,"-") -> - | BG198: =IFERROR(BA198/L198,"-") -> - | BH198: =IFERROR(BB198/M198,"-") -> - | BI198: =IFERROR(BC198/M198,"-") -> - | BJ198: =IFERROR(BD198/N198,"-") -> - | BK198: =IFERROR(BE198/N198,"-") -> - | BN198: =SUM(BL198:BM198) -> 0
A199: =LEFT(F199,4)+1 -> 2024 | B199: =RIGHT(F199,2) -> 37 | C199: {=_xlfn.IFS(_xlfn.NUMBERVALUE(B199)<=13,"Q1",AND(_xlfn.NUMBERVALUE(B199)>13,_xlfn.NUMBERVALUE(B199)<=26),"Q2", AND(_xlfn.NUMBERVALUE(B199)>26,_xlfn.NUMBERVALUE(B199)<=39),"Q3",_xlfn.NUMBERVALUE(B199)>39,"Q4")} -> Q3 | D199: =E198+1 -> 45206 | E199: =D199+6 -> 45212 | F199: 202337 | G199: =SUM(H199:I199) -> 0 | J199: =IFERROR(H199/G199,0) -> 0 | K199: =IFERROR(I199/G199,0) -> 0 | O199: =IFERROR(L199/$G199,0) -> 0 | P199: =IFERROR(M199/$G199,0) -> 0 | Q199: =IFERROR(N199/$G199,0) -> 0 | R199: =Forecast!J194 -> 0 | S199: =Forecast!N194 -> 0 | T199: =IF(OR(RIGHT(F199,2) = "01",G199 = 0),G199,T198+G199) -> 0 | U199: =IF(RIGHT(F199,2)="01",R199,R199+U198) -> 0 | V199: =IF(RIGHT(F199,2)="01",S199,S199+V198) -> 0 | W199: =X199+Y199 -> 0 | X199: ='Channel & Campaign Metrics'!AR198 -> 0 | Y199: ='Channel & Campaign Metrics'!BS198 -> 0 | AB199: ='Glass Metrics'!AC199 -> 0 | AC199: ='Glass Metrics'!I199 -> 0 | AD199: ='Glass Metrics'!N199 -> 0 | AE199: ='Glass Metrics'!S199 -> 0 | AF199: =IFERROR(AE199/AB199,"") | AG199: =IFERROR(AC199/AE199,"") | AH199: =IFERROR(AD199/AC199,"") | AI199: =IFERROR(G199/AB199,"") | AJ199: =IFERROR(((AK199*AM199)+(AL199*AN199))/(AM199+AN199),"") | AO199: =AJ199 | AS199: =AP199 -> 0 | AV199: =SUM(AT199:AU199) -> 0 | AW199: =BD199-AT199 -> 0 | AX199: =BE199-AU199 -> 0 | AY199: =SUM(AW199,AX199) -> 0 | AZ199: =H199-(BB199+BD199) -> 0 | BA199: =I199-(BC199+BE199) -> 0 | BF199: =IFERROR(AZ199/L199,"-") -> - | BG199: =IFERROR(BA199/L199,"-") -> - | BH199: =IFERROR(BB199/M199,"-") -> - | BI199: =IFERROR(BC199/M199,"-") -> - | BJ199: =IFERROR(BD199/N199,"-") -> - | BK199: =IFERROR(BE199/N199,"-") -> - | BN199: =SUM(BL199:BM199) -> 0
A200: =LEFT(F200,4)+1 -> 2024 | B200: =RIGHT(F200,2) -> 38 | C200: {=_xlfn.IFS(_xlfn.NUMBERVALUE(B200)<=13,"Q1",AND(_xlfn.NUMBERVALUE(B200)>13,_xlfn.NUMBERVALUE(B200)<=26),"Q2", AND(_xlfn.NUMBERVALUE(B200)>26,_xlfn.NUMBERVALUE(B200)<=39),"Q3",_xlfn.NUMBERVALUE(B200)>39,"Q4")} -> Q3 | D200: =E199+1 -> 45213 | E200: =D200+6 -> 45219 | F200: 202338 | G200: =SUM(H200:I200) -> 0 | J200: =IFERROR(H200/G200,0) -> 0 | K200: =IFERROR(I200/G200,0) -> 0 | O200: =IFERROR(L200/$G200,0) -> 0 | P200: =IFERROR(M200/$G200,0) -> 0 | Q200: =IFERROR(N200/$G200,0) -> 0 | R200: =Forecast!J195 -> 0 | S200: =Forecast!N195 -> 0 | T200: =IF(OR(RIGHT(F200,2) = "01",G200 = 0),G200,T199+G200) -> 0 | U200: =IF(RIGHT(F200,2)="01",R200,R200+U199) -> 0 | V200: =IF(RIGHT(F200,2)="01",S200,S200+V199) -> 0 | W200: =X200+Y200 -> 0 | X200: ='Channel & Campaign Metrics'!AR199 -> 0 | Y200: ='Channel & Campaign Metrics'!BS199 -> 0 | AB200: ='Glass Metrics'!AC200 -> 0 | AC200: ='Glass Metrics'!I200 -> 0 | AD200: ='Glass Metrics'!N200 -> 0 | AE200: ='Glass Metrics'!S200 -> 0 | AF200: =IFERROR(AE200/AB200,"") | AG200: =IFERROR(AC200/AE200,"") | AH200: =IFERROR(AD200/AC200,"") | AI200: =IFERROR(G200/AB200,"") | AJ200: =IFERROR(((AK200*AM200)+(AL200*AN200))/(AM200+AN200),"") | AO200: =AJ200 | AS200: =AP200 -> 0 | AV200: =SUM(AT200:AU200) -> 0 | AW200: =BD200-AT200 -> 0 | AX200: =BE200-AU200 -> 0 | AY200: =SUM(AW200,AX200) -> 0 | AZ200: =H200-(BB200+BD200) -> 0 | BA200: =I200-(BC200+BE200) -> 0 | BF200: =IFERROR(AZ200/L200,"-") -> - | BG200: =IFERROR(BA200/L200,"-") -> - | BH200: =IFERROR(BB200/M200,"-") -> - | BI200: =IFERROR(BC200/M200,"-") -> - | BJ200: =IFERROR(BD200/N200,"-") -> - | BK200: =IFERROR(BE200/N200,"-") -> - | BN200: =SUM(BL200:BM200) -> 0
A201: =LEFT(F201,4)+1 -> 2024 | B201: =RIGHT(F201,2) -> 39 | C201: {=_xlfn.IFS(_xlfn.NUMBERVALUE(B201)<=13,"Q1",AND(_xlfn.NUMBERVALUE(B201)>13,_xlfn.NUMBERVALUE(B201)<=26),"Q2", AND(_xlfn.NUMBERVALUE(B201)>26,_xlfn.NUMBERVALUE(B201)<=39),"Q3",_xlfn.NUMBERVALUE(B201)>39,"Q4")} -> Q3 | D201: =E200+1 -> 45220 | E201: =D201+6 -> 45226 | F201: 202339 | G201: =SUM(H201:I201) -> 0 | J201: =IFERROR(H201/G201,0) -> 0 | K201: =IFERROR(I201/G201,0) -> 0 | O201: =IFERROR(L201/$G201,0) -> 0 | P201: =IFERROR(M201/$G201,0) -> 0 | Q201: =IFERROR(N201/$G201,0) -> 0 | R201: =Forecast!J196 -> 0 | S201: =Forecast!N196 -> 0 | T201: =IF(OR(RIGHT(F201,2) = "01",G201 = 0),G201,T200+G201) -> 0 | U201: =IF(RIGHT(F201,2)="01",R201,R201+U200) -> 0 | V201: =IF(RIGHT(F201,2)="01",S201,S201+V200) -> 0 | W201: =X201+Y201 -> 0 | X201: ='Channel & Campaign Metrics'!AR200 -> 0 | Y201: ='Channel & Campaign Metrics'!BS200 -> 0 | AB201: ='Glass Metrics'!AC201 -> 0 | AC201: ='Glass Metrics'!I201 -> 0 | AD201: ='Glass Metrics'!N201 -> 0 | AE201: ='Glass Metrics'!S201 -> 0 | AF201: =IFERROR(AE201/AB201,"") | AG201: =IFERROR(AC201/AE201,"") | AH201: =IFERROR(AD201/AC201,"") | AI201: =IFERROR(G201/AB201,"") | AJ201: =IFERROR(((AK201*AM201)+(AL201*AN201))/(AM201+AN201),"") | AO201: =AJ201 | AS201: =AP201 -> 0 | AV201: =SUM(AT201:AU201) -> 0 | AW201: =BD201-AT201 -> 0 | AX201: =BE201-AU201 -> 0 | AY201: =SUM(AW201,AX201) -> 0 | AZ201: =H201-(BB201+BD201) -> 0 | BA201: =I201-(BC201+BE201) -> 0 | BF201: =IFERROR(AZ201/L201,"-") -> - | BG201: =IFERROR(BA201/L201,"-") -> - | BH201: =IFERROR(BB201/M201,"-") -> - | BI201: =IFERROR(BC201/M201,"-") -> - | BJ201: =IFERROR(BD201/N201,"-") -> - | BK201: =IFERROR(BE201/N201,"-") -> - | BN201: =SUM(BL201:BM201) -> 0
A202: =LEFT(F202,4)+1 -> 2024 | B202: =RIGHT(F202,2) -> 40 | C202: {=_xlfn.IFS(_xlfn.NUMBERVALUE(B202)<=13,"Q1",AND(_xlfn.NUMBERVALUE(B202)>13,_xlfn.NUMBERVALUE(B202)<=26),"Q2", AND(_xlfn.NUMBERVALUE(B202)>26,_xlfn.NUMBERVALUE(B202)<=39),"Q3",_xlfn.NUMBERVALUE(B202)>39,"Q4")} -> Q4 | D202: =E201+1 -> 45227 | E202: =D202+6 -> 45233 | F202: 202340 | G202: =SUM(H202:I202) -> 0 | J202: =IFERROR(H202/G202,0) -> 0 | K202: =IFERROR(I202/G202,0) -> 0 | O202: =IFERROR(L202/$G202,0) -> 0 | P202: =IFERROR(M202/$G202,0) -> 0 | Q202: =IFERROR(N202/$G202,0) -> 0 | R202: =Forecast!J197 -> 0 | S202: =Forecast!N197 -> 0 | T202: =IF(OR(RIGHT(F202,2) = "01",G202 = 0),G202,T201+G202) -> 0 | U202: =IF(RIGHT(F202,2)="01",R202,R202+U201) -> 0 | V202: =IF(RIGHT(F202,2)="01",S202,S202+V201) -> 0 | W202: =X202+Y202 -> 0 | X202: ='Channel & Campaign Metrics'!AR201 -> 0 | Y202: ='Channel & Campaign Metrics'!BS201 -> 0 | AB202: ='Glass Metrics'!AC202 -> 0 | AC202: ='Glass Metrics'!I202 -> 0 | AD202: ='Glass Metrics'!N202 -> 0 | AE202: ='Glass Metrics'!S202 -> 0 | AF202: =IFERROR(AE202/AB202,"") | AG202: =IFERROR(AC202/AE202,"") | AH202: =IFERROR(AD202/AC202,"") | AI202: =IFERROR(G202/AB202,"") | AJ202: =IFERROR(((AK202*AM202)+(AL202*AN202))/(AM202+AN202),"") | AO202: =AJ202 | AS202: =AP202 -> 0 | AV202: =SUM(AT202:AU202) -> 0 | AW202: =BD202-AT202 -> 0 | AX202: =BE202-AU202 -> 0 | AY202: =SUM(AW202,AX202) -> 0 | AZ202: =H202-(BB202+BD202) -> 0 | BA202: =I202-(BC202+BE202) -> 0 | BF202: =IFERROR(AZ202/L202,"-") -> - | BG202: =IFERROR(BA202/L202,"-") -> - | BH202: =IFERROR(BB202/M202,"-") -> - | BI202: =IFERROR(BC202/M202,"-") -> - | BJ202: =IFERROR(BD202/N202,"-") -> - | BK202: =IFERROR(BE202/N202,"-") -> - | BN202: =SUM(BL202:BM202) -> 0
A203: =LEFT(F203,4)+1 -> 2024 | B203: =RIGHT(F203,2) -> 41 | C203: {=_xlfn.IFS(_xlfn.NUMBERVALUE(B203)<=13,"Q1",AND(_xlfn.NUMBERVALUE(B203)>13,_xlfn.NUMBERVALUE(B203)<=26),"Q2", AND(_xlfn.NUMBERVALUE(B203)>26,_xlfn.NUMBERVALUE(B203)<=39),"Q3",_xlfn.NUMBERVALUE(B203)>39,"Q4")} -> Q4 | D203: =E202+1 -> 45234 | E203: =D203+6 -> 45240 | F203: 202341 | G203: =SUM(H203:I203) -> 0 | J203: =IFERROR(H203/G203,0) -> 0 | K203: =IFERROR(I203/G203,0) -> 0 | O203: =IFERROR(L203/$G203,0) -> 0 | P203: =IFERROR(M203/$G203,0) -> 0 | Q203: =IFERROR(N203/$G203,0) -> 0 | R203: =Forecast!J198 -> 0 | S203: =Forecast!N198 -> 0 | T203: =IF(OR(RIGHT(F203,2) = "01",G203 = 0),G203,T202+G203) -> 0 | U203: =IF(RIGHT(F203,2)="01",R203,R203+U202) -> 0 | V203: =IF(RIGHT(F203,2)="01",S203,S203+V202) -> 0 | W203: =X203+Y203 -> 0 | X203: ='Channel & Campaign Metrics'!AR202 -> 0 | Y203: ='Channel & Campaign Metrics'!BS202 -> 0 | AB203: ='Glass Metrics'!AC203 -> 0 | AC203: ='Glass Metrics'!I203 -> 0 | AD203: ='Glass Metrics'!N203 -> 0 | AE203: ='Glass Metrics'!S203 -> 0 | AF203: =IFERROR(AE203/AB203,"") | AG203: =IFERROR(AC203/AE203,"") | AH203: =IFERROR(AD203/AC203,"") | AI203: =IFERROR(G203/AB203,"") | AJ203: =IFERROR(((AK203*AM203)+(AL203*AN203))/(AM203+AN203),"") | AO203: =AJ203 | AS203: =AP203 -> 0 | AV203: =SUM(AT203:AU203) -> 0 | AW203: =BD203-AT203 -> 0 | AX203: =BE203-AU203 -> 0 | AY203: =SUM(AW203,AX203) -> 0 | AZ203: =H203-(BB203+BD203) -> 0 | BA203: =I203-(BC203+BE203) -> 0 | BF203: =IFERROR(AZ203/L203,"-") -> - | BG203: =IFERROR(BA203/L203,"-") -> - | BH203: =IFERROR(BB203/M203,"-") -> - | BI203: =IFERROR(BC203/M203,"-") -> - | BJ203: =IFERROR(BD203/N203,"-") -> - | BK203: =IFERROR(BE203/N203,"-") -> - | BN203: =SUM(BL203:BM203) -> 0
A204: =LEFT(F204,4)+1 -> 2024 | B204: =RIGHT(F204,2) -> 42 | C204: {=_xlfn.IFS(_xlfn.NUMBERVALUE(B204)<=13,"Q1",AND(_xlfn.NUMBERVALUE(B204)>13,_xlfn.NUMBERVALUE(B204)<=26),"Q2", AND(_xlfn.NUMBERVALUE(B204)>26,_xlfn.NUMBERVALUE(B204)<=39),"Q3",_xlfn.NUMBERVALUE(B204)>39,"Q4")} -> Q4 | D204: =E203+1 -> 45241 | E204: =D204+6 -> 45247 | F204: 202342 | G204: =SUM(H204:I204) -> 0 | J204: =IFERROR(H204/G204,0) -> 0 | K204: =IFERROR(I204/G204,0) -> 0 | O204: =IFERROR(L204/$G204,0) -> 0 | P204: =IFERROR(M204/$G204,0) -> 0 | Q204: =IFERROR(N204/$G204,0) -> 0 | R204: =Forecast!J199 -> 0 | S204: =Forecast!N199 -> 0 | T204: =IF(OR(RIGHT(F204,2) = "01",G204 = 0),G204,T203+G204) -> 0 | U204: =IF(RIGHT(F204,2)="01",R204,R204+U203) -> 0 | V204: =IF(RIGHT(F204,2)="01",S204,S204+V203) -> 0 | W204: =X204+Y204 -> 0 | X204: ='Channel & Campaign Metrics'!AR203 -> 0 | Y204: ='Channel & Campaign Metrics'!BS203 -> 0 | AB204: ='Glass Metrics'!AC204 -> 0 | AC204: ='Glass Metrics'!I204 -> 0 | AD204: ='Glass Metrics'!N204 -> 0 | AE204: ='Glass Metrics'!S204 -> 0 | AF204: =IFERROR(AE204/AB204,"") | AG204: =IFERROR(AC204/AE204,"") | AH204: =IFERROR(AD204/AC204,"") | AI204: =IFERROR(G204/AB204,"") | AJ204: =IFERROR(((AK204*AM204)+(AL204*AN204))/(AM204+AN204),"") | AO204: =AJ204 | AS204: =AP204 -> 0 | AV204: =SUM(AT204:AU204) -> 0 | AW204: =BD204-AT204 -> 0 | AX204: =BE204-AU204 -> 0 | AY204: =SUM(AW204,AX204) -> 0 | AZ204: =H204-(BB204+BD204) -> 0 | BA204: =I204-(BC204+BE204) -> 0 | BF204: =IFERROR(AZ204/L204,"-") -> - | BG204: =IFERROR(BA204/L204,"-") -> - | BH204: =IFERROR(BB204/M204,"-") -> - | BI204: =IFERROR(BC204/M204,"-") -> - | BJ204: =IFERROR(BD204/N204,"-") -> - | BK204: =IFERROR(BE204/N204,"-") -> - | BN204: =SUM(BL204:BM204) -> 0
A205: =LEFT(F205,4)+1 -> 2024 | B205: =RIGHT(F205,2) -> 43 | C205: {=_xlfn.IFS(_xlfn.NUMBERVALUE(B205)<=13,"Q1",AND(_xlfn.NUMBERVALUE(B205)>13,_xlfn.NUMBERVALUE(B205)<=26),"Q2", AND(_xlfn.NUMBERVALUE(B205)>26,_xlfn.NUMBERVALUE(B205)<=39),"Q3",_xlfn.NUMBERVALUE(B205)>39,"Q4")} -> Q4 | D205: =E204+1 -> 45248 | E205: =D205+6 -> 45254 | F205: 202343 | G205: =SUM(H205:I205) -> 0 | J205: =IFERROR(H205/G205,0) -> 0 | K205: =IFERROR(I205/G205,0) -> 0 | O205: =IFERROR(L205/$G205,0) -> 0 | P205: =IFERROR(M205/$G205,0) -> 0 | Q205: =IFERROR(N205/$G205,0) -> 0 | R205: =Forecast!J200 -> 0 | S205: =Forecast!N200 -> 0 | T205: =IF(OR(RIGHT(F205,2) = "01",G205 = 0),G205,T204+G205) -> 0 | U205: =IF(RIGHT(F205,2)="01",R205,R205+U204) -> 0 | V205: =IF(RIGHT(F205,2)="01",S205,S205+V204) -> 0 | W205: =X205+Y205 -> 0 | X205: ='Channel & Campaign Metrics'!AR204 -> 0 | Y205: ='Channel & Campaign Metrics'!BS204 -> 0 | AB205: ='Glass Metrics'!AC205 -> 0 | AC205: ='Glass Metrics'!I205 -> 0 | AD205: ='Glass Metrics'!N205 -> 0 | AE205: ='Glass Metrics'!S205 -> 0 | AF205: =IFERROR(AE205/AB205,"") | AG205: =IFERROR(AC205/AE205,"") | AH205: =IFERROR(AD205/AC205,"") | AI205: =IFERROR(G205/AB205,"") | AJ205: =IFERROR(((AK205*AM205)+(AL205*AN205))/(AM205+AN205),"") | AO205: =AJ205 | AS205: =AP205 -> 0 | AV205: =SUM(AT205:AU205) -> 0 | AW205: =BD205-AT205 -> 0 | AX205: =BE205-AU205 -> 0 | AY205: =SUM(AW205,AX205) -> 0 | AZ205: =H205-(BB205+BD205) -> 0 | BA205: =I205-(BC205+BE205) -> 0 | BF205: =IFERROR(AZ205/L205,"-") -> - | BG205: =IFERROR(BA205/L205,"-") -> - | BH205: =IFERROR(BB205/M205,"-") -> - | BI205: =IFERROR(BC205/M205,"-") -> - | BJ205: =IFERROR(BD205/N205,"-") -> - | BK205: =IFERROR(BE205/N205,"-") -> - | BN205: =SUM(BL205:BM205) -> 0
A206: =LEFT(F206,4)+1 -> 2024 | B206: =RIGHT(F206,2) -> 44 | C206: {=_xlfn.IFS(_xlfn.NUMBERVALUE(B206)<=13,"Q1",AND(_xlfn.NUMBERVALUE(B206)>13,_xlfn.NUMBERVALUE(B206)<=26),"Q2", AND(_xlfn.NUMBERVALUE(B206)>26,_xlfn.NUMBERVALUE(B206)<=39),"Q3",_xlfn.NUMBERVALUE(B206)>39,"Q4")} -> Q4 | D206: =E205+1 -> 45255 | E206: =D206+6 -> 45261 | F206: 202344 | G206: =SUM(H206:I206) -> 0 | J206: =IFERROR(H206/G206,0) -> 0 | K206: =IFERROR(I206/G206,0) -> 0 | O206: =IFERROR(L206/$G206,0) -> 0 | P206: =IFERROR(M206/$G206,0) -> 0 | Q206: =IFERROR(N206/$G206,0) -> 0 | R206: =Forecast!J201 -> 0 | S206: =Forecast!N201 -> 0 | T206: =IF(OR(RIGHT(F206,2) = "01",G206 = 0),G206,T205+G206) -> 0 | U206: =IF(RIGHT(F206,2)="01",R206,R206+U205) -> 0 | V206: =IF(RIGHT(F206,2)="01",S206,S206+V205) -> 0 | W206: =X206+Y206 -> 0 | X206: ='Channel & Campaign Metrics'!AR205 -> 0 | Y206: ='Channel & Campaign Metrics'!BS205 -> 0 | AB206: ='Glass Metrics'!AC206 -> 0 | AC206: ='Glass Metrics'!I206 -> 0 | AD206: ='Glass Metrics'!N206 -> 0 | AE206: ='Glass Metrics'!S206 -> 0 | AF206: =IFERROR(AE206/AB206,"") | AG206: =IFERROR(AC206/AE206,"") | AH206: =IFERROR(AD206/AC206,"") | AI206: =IFERROR(G206/AB206,"") | AJ206: =IFERROR(((AK206*AM206)+(AL206*AN206))/(AM206+AN206),"") | AO206: =AJ206 | AS206: =AP206 -> 0 | AV206: =SUM(AT206:AU206) -> 0 | AW206: =BD206-AT206 -> 0 | AX206: =BE206-AU206 -> 0 | AY206: =SUM(AW206,AX206) -> 0 | AZ206: =H206-(BB206+BD206) -> 0 | BA206: =I206-(BC206+BE206) -> 0 | BF206: =IFERROR(AZ206/L206,"-") -> - | BG206: =IFERROR(BA206/L206,"-") -> - | BH206: =IFERROR(BB206/M206,"-") -> - | BI206: =IFERROR(BC206/M206,"-") -> - | BJ206: =IFERROR(BD206/N206,"-") -> - | BK206: =IFERROR(BE206/N206,"-") -> - | BN206: =SUM(BL206:BM206) -> 0
... A210: =LEFT(F210,4)+1 -> 2024 | B210: =RIGHT(F210,2) -> 48 | C210: {=_xlfn.IFS(_xlfn.NUMBERVALUE(B210)<=13,"Q1",AND(_xlfn.NUMBERVALUE(B210)>13,_xlfn.NUMBERVALUE(B210)<=26),"Q2", AND(_xlfn.NUMBERVALUE(B210)>26,_xlfn.NUMBERVALUE(B210)<=39),"Q3",_xlfn.NUMBERVALUE(B210)>39,"Q4")} -> Q4 | D210: =E209+1 -> 45283 | E210: =D210+6 -> 45289 | F210: 202348 | G210: =SUM(H210:I210) -> 0 | J210: =IFERROR(H210/G210,0) -> 0 | K210: =IFERROR(I210/G210,0) -> 0 | O210: =IFERROR(L210/$G210,0) -> 0 | P210: =IFERROR(M210/$G210,0) -> 0 | Q210: =IFERROR(N210/$G210,0) -> 0 | R210: =Forecast!J205 -> 0 | S210: =Forecast!N205 -> 0 | T210: =IF(OR(RIGHT(F210,2) = "01",G210 = 0),G210,T209+G210) -> 0 | U210: =IF(RIGHT(F210,2)="01",R210,R210+U209) -> 0 | V210: =IF(RIGHT(F210,2)="01",S210,S210+V209) -> 0 | W210: =X210+Y210 -> 0 | X210: ='Channel & Campaign Metrics'!AR209 -> 0 | Y210: ='Channel & Campaign Metrics'!BS209 -> 0 | AB210: ='Glass Metrics'!AC210 -> 0 | AC210: ='Glass Metrics'!I210 -> 0 | AD210: ='Glass Metrics'!N210 -> 0 | AE210: ='Glass Metrics'!S210 -> 0 | AF210: =IFERROR(AE210/AB210,"") | AG210: =IFERROR(AC210/AE210,"") | AH210: =IFERROR(AD210/AC210,"") | AI210: =IFERROR(G210/AB210,"") | AJ210: =IFERROR(((AK210*AM210)+(AL210*AN210))/(AM210+AN210),"") | AO210: =AJ210 | AS210: =AP210 -> 0 | AV210: =SUM(AT210:AU210) -> 0 | AW210: =BD210-AT210 -> 0 | AX210: =BE210-AU210 -> 0 | AY210: =SUM(AW210,AX210) -> 0 | AZ210: =H210-(BB210+BD210) -> 0 | BA210: =I210-(BC210+BE210) -> 0 | BF210: =IFERROR(AZ210/L210,"-") -> - | BG210: =IFERROR(BA210/L210,"-") -> - | BH210: =IFERROR(BB210/M210,"-") -> - | BI210: =IFERROR(BC210/M210,"-") -> - | BJ210: =IFERROR(BD210/N210,"-") -> - | BK210: =IFERROR(BE210/N210,"-") -> - | BN210: =SUM(BL210:BM210) -> 0
A211: =LEFT(F211,4)+1 -> 2024 | B211: =RIGHT(F211,2) -> 49 | C211: {=_xlfn.IFS(_xlfn.NUMBERVALUE(B211)<=13,"Q1",AND(_xlfn.NUMBERVALUE(B211)>13,_xlfn.NUMBERVALUE(B211)<=26),"Q2", AND(_xlfn.NUMBERVALUE(B211)>26,_xlfn.NUMBERVALUE(B211)<=39),"Q3",_xlfn.NUMBERVALUE(B211)>39,"Q4")} -> Q4 | D211: =E210+1 -> 45290 | E211: =D211+6 -> 45296 | F211: 202349 | G211: =SUM(H211:I211) -> 330754.05 | H211: =1.5 * (BB211+BD211) -> 123386.55 | I211: =1.5*(BC211+BE211) -> 207367.5 | J211: =IFERROR(H211/G211,0) -> 0.37304623 | K211: =IFERROR(I211/G211,0) -> 0.62695377 | L211: =AZ211+BA211 -> 110251.35 | M211: =BB211+BC211 -> 163031 | N211: =BD211+BE211 -> 57471.7 | O211: =IFERROR(L211/$G211,0) -> 0.33333333 | P211: =IFERROR(M211/$G211,0) -> 0.49290704 | Q211: =IFERROR(N211/$G211,0) -> 0.17375963 | R211: =Forecast!J206 -> 0 | S211: =Forecast!N206 -> 0 | T211: =IF(OR(RIGHT(F211,2) = "01",G211 = 0),G211,T210+G211) -> 330754.05 | U211: =IF(RIGHT(F211,2)="01",R211,R211+U210) -> 0 | V211: =IF(RIGHT(F211,2)="01",S211,S211+V210) -> 0 | W211: =X211+Y211 -> 0 | X211: ='Channel & Campaign Metrics'!AR210 -> 0 | Y211: ='Channel & Campaign Metrics'!BS210 -> 0 | Z211: =W211*0.6 -> 0 | AA211: =W211*0.4 -> 0 | AB211: ='Glass Metrics'!AC211 -> 122171 | AC211: ='Glass Metrics'!I211 -> 139847 | AD211: ='Glass Metrics'!N211 -> 163239 | AE211: ='Glass Metrics'!S211 -> 167446 | AF211: =IFERROR(AE211/AB211,"") -> 1.3705871 | AG211: =IFERROR(AC211/AE211,"") -> 0.83517671 | AH211: =IFERROR(AD211/AC211,"") -> 1.1672685 | AI211: =IFERROR(G211/AB211,"") -> 2.7073041 | AJ211: =IFERROR(((AK211*AM211)+(AL211*AN211))/(AM211+AN211),"") -> 0.50468092 | AK211: 0.49897448 | AL211: 0.51109625 | AM211: 72997 | AN211: 64931 | AO211: =AJ211 -> 0.50468092 | AQ211: 0.41456594 | AR211: 0.67013895 | AS211: =AP211 -> 0 | AT211: 10349 | AU211: =AV211-AT211 -> 33860 | AV211: ='Channel & Campaign Metrics'!Z210 -> 44209 | AW211: =BD211-AT211 -> 3104.7 | AX211: =BE211-AU211 -> 10158 | AY211: =SUM(AW211,AX211) -> 13262.7 | AZ211: =H211-(BB211+BD211) -> 41128.85 | BA211: =I211-(BC211+BE211) -> 69122.5 | BB211: 68804 | BC211: 94227 | BD211: =1.3*AT211 -> 13453.7 | BE211: =1.3*AU211 -> 44018 | BF211: =IFERROR(AZ211/L211,"-") -> 0.37304623 | BG211: =IFERROR(BA211/L211,"-") -> 0.62695377 | BH211: =IFERROR(BB211/M211,"-") -> 0.42203017 | BI211: =IFERROR(BC211/M211,"-") -> 0.57796983 | BJ211: =IFERROR(BD211/N211,"-") -> 0.23409261 | BK211: =IFERROR(BE211/N211,"-") -> 0.76590739 | BL211: 61050 | BM211: 78080 | BN211: =SUM(BL211:BM211) -> 139130
A212: =LEFT(F212,4)+1 -> 2024 | B212: =RIGHT(F212,2) -> 50 | C212: {=_xlfn.IFS(_xlfn.NUMBERVALUE(B212)<=13,"Q1",AND(_xlfn.NUMBERVALUE(B212)>13,_xlfn.NUMBERVALUE(B212)<=26),"Q2", AND(_xlfn.NUMBERVALUE(B212)>26,_xlfn.NUMBERVALUE(B212)<=39),"Q3",_xlfn.NUMBERVALUE(B212)>39,"Q4")} -> Q4 | D212: =E211+1 -> 45297 | E212: =D212+6 -> 45303 | F212: 202350 | G212: =SUM(H212:I212) -> 357467.25 | H212: =1.5 * (BB212+BD212) -> 138898.95 | I212: =1.5*(BC212+BE212) -> 218568.3 | J212: =IFERROR(H212/G212,0) -> 0.38856413 | K212: =IFERROR(I212/G212,0) -> 0.61143587 | L212: =AZ212+BA212 -> 119155.75 | M212: =BB212+BC212 -> 162008 | N212: =BD212+BE212 -> 76303.5 | O212: =IFERROR(L212/$G212,0) -> 0.33333333 | P212: =IFERROR(M212/$G212,0) -> 0.45321075 | Q212: =IFERROR(N212/$G212,0) -> 0.21345592 | R212: =Forecast!J207 -> 239939 | S212: =Forecast!N207 -> 235009 | T212: =IF(OR(RIGHT(F212,2) = "01",G212 = 0),G212,T211+G212) -> 688221.3 | U212: =IF(RIGHT(F212,2)="01",R212,R212+U211) -> 239939 | V212: =IF(RIGHT(F212,2)="01",S212,S212+V211) -> 235009 | W212: =X212+Y212 -> 1351951 | X212: ='Channel & Campaign Metrics'!AR211 -> 1224930 | Y212: ='Channel & Campaign Metrics'!BS211 -> 127021 | Z212: =W212*0.6 -> 811170.6 | AA212: =W212*0.4 -> 540780.4 | AB212: ='Glass Metrics'!AC212 -> 147642 | AC212: ='Glass Metrics'!I212 -> 169234 | AD212: ='Glass Metrics'!N212 -> 159114 | AE212: ='Glass Metrics'!S212 -> 161291 | AF212: =IFERROR(AE212/AB212,"") -> 1.0924466 | AG212: =IFERROR(AC212/AE212,"") -> 1.0492464 | AH212: =IFERROR(AD212/AC212,"") -> 0.94020114 | AI212: =IFERROR(G212/AB212,"") -> 2.4211759 | AJ212: =IFERROR(((AK212*AM212)+(AL212*AN212))/(AM212+AN212),"") -> 0.77624913 | AK212: 0.49897448 | AL212: 0.94803295 | AM212: 50289 | AN212: 81171 | AO212: =AJ212 -> 0.77624913 | AQ212: 0.12982551 | AR212: 0.57624564 | AS212: =AP212 -> 0 | AT212: 19091 | AU212: =AV212-AT212 -> 39604 | AV212: ='Channel & Campaign Metrics'!Z211 -> 58695 | AW212: =BD212-AT212 -> 5727.3 | AX212: =BE212-AU212 -> 11881.2 | AY212: =SUM(AW212,AX212) -> 17608.5 | AZ212: =H212-(BB212+BD212) -> 46299.65 | BA212: =I212-(BC212+BE212) -> 72856.1 | BB212: 67781 | BC212: 94227 | BD212: =1.3*AT212 -> 24818.3 | BE212: =1.3*AU212 -> 51485.2 | BF212: =IFERROR(AZ212/L212,"-") -> 0.38856413 | BG212: =IFERROR(BA212/L212,"-") -> 0.61143587 | BH212: =IFERROR(BB212/M212,"-") -> 0.41838057 | BI212: =IFERROR(BC212/M212,"-") -> 0.58161943 | BJ212: =IFERROR(BD212/N212,"-") -> 0.32525769 | BK212: =IFERROR(BE212/N212,"-") -> 0.67474231 | BL212: 57567 | BM212: 92598 | BN212: =SUM(BL212:BM212) -> 150165
A213: =LEFT(F213,4)+1 -> 2024 | B213: =RIGHT(F213,2) -> 51 | C213: {=_xlfn.IFS(_xlfn.NUMBERVALUE(B213)<=13,"Q1",AND(_xlfn.NUMBERVALUE(B213)>13,_xlfn.NUMBERVALUE(B213)<=26),"Q2", AND(_xlfn.NUMBERVALUE(B213)>26,_xlfn.NUMBERVALUE(B213)<=39),"Q3",_xlfn.NUMBERVALUE(B213)>39,"Q4")} -> Q4 | D213: =E212+1 -> 45304 | E213: =D213+6 -> 45310 | F213: 202351 | G213: =SUM(H213:I213) -> 305077.35 | H213: =1.5 * (BB213+BD213) -> 146779.95 | I213: =1.5*(BC213+BE213) -> 158297.4 | J213: =IFERROR(H213/G213,0) -> 0.48112372 | K213: =IFERROR(I213/G213,0) -> 0.51887628 | L213: =AZ213+BA213 -> 101692.45 | M213: =BB213+BC213 -> 141761 | N213: =BD213+BE213 -> 61623.9 | O213: =IFERROR(L213/$G213,0) -> 0.33333333 | P213: =IFERROR(M213/$G213,0) -> 0.46467232 | Q213: =IFERROR(N213/$G213,0) -> 0.20199435 | R213: =Forecast!J208 -> 229505 | S213: =Forecast!N208 -> 271171 | T213: =IF(OR(RIGHT(F213,2) = "01",G213 = 0),G213,T212+G213) -> 993298.65 | U213: =IF(RIGHT(F213,2)="01",R213,R213+U212) -> 469444 | V213: =IF(RIGHT(F213,2)="01",S213,S213+V212) -> 506180 | W213: =X213+Y213 -> 1335159 | X213: ='Channel & Campaign Metrics'!AR212 -> 1172293 | Y213: ='Channel & Campaign Metrics'!BS212 -> 162866 | Z213: =W213*0.6 -> 801095.4 | AA213: =W213*0.4 -> 534063.6 | AB213: ='Glass Metrics'!AC213 -> 115674 | AC213: ='Glass Metrics'!I213 -> 179474 | AD213: ='Glass Metrics'!N213 -> 149422 | AE213: ='Glass Metrics'!S213 -> 180565 | AF213: =IFERROR(AE213/AB213,"") -> 1.5609817 | AG213: =IFERROR(AC213/AE213,"") -> 0.99395785 | AH213: =IFERROR(AD213/AC213,"") -> 0.83255513 | AI213: =IFERROR(G213/AB213,"") -> 2.6373891 | AJ213: =IFERROR(((AK213*AM213)+(AL213*AN213))/(AM213+AN213),"") -> 0.4015354 | AK213: 0.029332974 | AL213: 0.66704327 | AM213: 68401 | AN213: 95888 | AO213: =AJ213 -> 0.4015354 | AQ213: 0.67013895 | AR213: 0.28083933 | AS213: =AP213 -> 0 | AT213: 19151 | AU213: =AV213-AT213 -> 28252 | AV213: ='Channel & Campaign Metrics'!Z212 -> 47403 | AW213: =BD213-AT213 -> 5745.3 | AX213: =BE213-AU213 -> 8475.6 | AY213: =SUM(AW213,AX213) -> 14220.9 | AZ213: =H213-(BB213+BD213) -> 48926.65 | BA213: =I213-(BC213+BE213) -> 52765.8 | BB213: 72957 | BC213: 68804 | BD213: =1.3*AT213 -> 24896.3 | BE213: =1.3*AU213 -> 36727.6 | BF213: =IFERROR(AZ213/L213,"-") -> 0.48112372 | BG213: =IFERROR(BA213/L213,"-") -> 0.51887628 | BH213: =IFERROR(BB213/M213,"-") -> 0.51464789 | BI213: =IFERROR(BC213/M213,"-") -> 0.48535211 | BJ213: =IFERROR(BD213/N213,"-") -> 0.40400397 | BK213: =IFERROR(BE213/N213,"-") -> 0.59599603 | BL213: 98928 | BM213: 94991 | BN213: =SUM(BL213:BM213) -> 193919
A214: =LEFT(F214,4)+1 -> 2024 | B214: =RIGHT(F214,2) -> 52 | C214: {=_xlfn.IFS(_xlfn.NUMBERVALUE(B214)<=13,"Q1",AND(_xlfn.NUMBERVALUE(B214)>13,_xlfn.NUMBERVALUE(B214)<=26),"Q2", AND(_xlfn.NUMBERVALUE(B214)>26,_xlfn.NUMBERVALUE(B214)<=39),"Q3",_xlfn.NUMBERVALUE(B214)>39,"Q4")} -> Q4 | D214: =E213+1 -> 45311 | E214: =D214+6 -> 45317 | F214: 202352 | G214: =SUM(H214:I214) -> 309909 | H214: =1.5 * (BB214+BD214) -> 120598.05 | I214: =1.5*(BC214+BE214) -> 189310.95 | J214: =IFERROR(H214/G214,0) -> 0.3891402 | K214: =IFERROR(I214/G214,0) -> 0.6108598 | L214: =AZ214+BA214 -> 103303 | M214: =BB214+BC214 -> 142776 | N214: =BD214+BE214 -> 63830 | O214: =IFERROR(L214/$G214,0) -> 0.33333333 | P214: =IFERROR(M214/$G214,0) -> 0.46070298 | Q214: =IFERROR(N214/$G214,0) -> 0.20596369 | R214: =Forecast!J209 -> 191732 | S214: =Forecast!N209 -> 224735 | T214: =IF(OR(RIGHT(F214,2) = "01",G214 = 0),G214,T213+G214) -> 1303207.7 | U214: =IF(RIGHT(F214,2)="01",R214,R214+U213) -> 661176 | V214: =IF(RIGHT(F214,2)="01",S214,S214+V213) -> 730915 | W214: =X214+Y214 -> 1412561 | X214: ='Channel & Campaign Metrics'!AR213 -> 1248860 | Y214: ='Channel & Campaign Metrics'!BS213 -> 163701 | Z214: =W214*0.6 -> 847536.6 | AA214: =W214*0.4 -> 565024.4 | AB214: ='Glass Metrics'!AC214 -> 158838 | AC214: ='Glass Metrics'!I214 -> 156197 | AD214: ='Glass Metrics'!N214 -> 148874 | AE214: ='Glass Metrics'!S214 -> 160546 | AF214: =IFERROR(AE214/AB214,"") -> 1.0107531 | AG214: =IFERROR(AC214/AE214,"") -> 0.97291119 | AH214: =IFERROR(AD214/AC214,"") -> 0.9531169 | AI214: =IFERROR(G214/AB214,"") -> 1.9511011 | AJ214: =IFERROR(((AK214*AM214)+(AL214*AN214))/(AM214+AN214),"") -> 0.18230452 | AK214: 0.23878027 | AL214: 0.13264654 | AM214: 71088 | AN214: 80848 | AO214: =AJ214 -> 0.18230452 | AQ214: 0.13349462 | AR214: 0.73349408 | AS214: =AP214 -> 0 | AT214: 10349 | AU214: =AV214-AT214 -> 38751 | AV214: ='Channel & Campaign Metrics'!Z213 -> 49100 | AW214: =BD214-AT214 -> 3104.7 | AX214: =BE214-AU214 -> 11625.3 | AY214: =SUM(AW214,AX214) -> 14730 | AZ214: =H214-(BB214+BD214) -> 40199.35 | BA214: =I214-(BC214+BE214) -> 63103.65 | BB214: 66945 | BC214: 75831 | BD214: =1.3*AT214 -> 13453.7 | BE214: =1.3*AU214 -> 50376.3 | BF214: =IFERROR(AZ214/L214,"-") -> 0.3891402 | BG214: =IFERROR(BA214/L214,"-") -> 0.6108598 | BH214: =IFERROR(BB214/M214,"-") -> 0.46888132 | BI214: =IFERROR(BC214/M214,"-") -> 0.53111868 | BJ214: =IFERROR(BD214/N214,"-") -> 0.21077393 | BK214: =IFERROR(BE214/N214,"-") -> 0.78922607 | BL214: 80246 | BM214: 88758 | BN214: =SUM(BL214:BM214) -> 169004
A215: =LEFT(F215,4)+1 -> 2025 | B215: =RIGHT(F215,2) -> 01 | C215: {=_xlfn.IFS(_xlfn.NUMBERVALUE(B215)<=13,"Q1",AND(_xlfn.NUMBERVALUE(B215)>13,_xlfn.NUMBERVALUE(B215)<=26),"Q2", AND(_xlfn.NUMBERVALUE(B215)>26,_xlfn.NUMBERVALUE(B215)<=39),"Q3",_xlfn.NUMBERVALUE(B215)>39,"Q4")} -> Q1 | D215: =E214+1 -> 45318 | E215: =D215+6 -> 45324 | F215: 202401 | G215: =SUM(H215:I215) -> 316383.3 | H215: =1.5 * (BB215+BD215) -> 116032.95 | I215: =1.5*(BC215+BE215) -> 200350.35 | J215: =IFERROR(H215/G215,0) -> 0.36674802 | K215: =IFERROR(I215/G215,0) -> 0.63325198 | L215: =AZ215+BA215 -> 105461.1 | M215: 118252 | N215: =BD215+BE215 -> 63107.2 | O215: =IFERROR(L215/$G215,0) -> 0.33333333 | P215: =IFERROR(M215/$G215,0) -> 0.37376183 | Q215: =IFERROR(N215/$G215,0) -> 0.19946438 | R215: =Forecast!J210 -> 228191 | S215: =Forecast!N210 -> 224570 | T215: =IF(OR(RIGHT(F215,2) = "01",G215 = 0),G215,T214+G215) -> 316383.3 | U215: =IF(RIGHT(F215,2)="01",R215,R215+U214) -> 228191 | V215: =IF(RIGHT(F215,2)="01",S215,S215+V214) -> 224570 | W215: =X215+Y215 -> 1366268 | X215: ='Channel & Campaign Metrics'!AR214 -> 1181029 | Y215: ='Channel & Campaign Metrics'!BS214 -> 185239 | Z215: =W215*0.6 -> 819760.8 | AA215: =W215*0.4 -> 546507.2 | AB215: ='Glass Metrics'!AC215 -> 156918 | AC215: ='Glass Metrics'!I215 -> 124458 | AD215: ='Glass Metrics'!N215 -> 135375 | AE215: ='Glass Metrics'!S215 -> 152949 | AF215: =IFERROR(AE215/AB215,"") -> 0.97470653 | AG215: =IFERROR(AC215/AE215,"") -> 0.81372222 | AH215: =IFERROR(AD215/AC215,"") -> 1.0877163 | AI215: =IFERROR(G215/AB215,"") -> 2.0162333 | AJ215: =IFERROR(((AK215*AM215)+(AL215*AN215))/(AM215+AN215),"") -> 0.70947061 | AK215: 0.57863957 | AL215: 0.88686251 | AM215: 88039 | AN215: 64931 | AO215: =AJ215 -> 0.70947061 | AQ215: 0.75652431 | AR215: 0.80546964 | AS215: =AP215 -> 0 | AT215: 13831 | AU215: =AV215-AT215 -> 34713 | AV215: ='Channel & Campaign Metrics'!Z214 -> 48544 | AW215: =BD215-AT215 -> 4149.3 | AX215: =BE215-AU215 -> 10413.9 | AY215: =SUM(AW215,AX215) -> 14563.2 | AZ215: =H215-(BB215+BD215) -> 38677.65 | BA215: =I215-(BC215+BE215) -> 66783.45 | BB215: 59375 | BC215: 88440 | BD215: =1.3*AT215 -> 17980.3 | BE215: =1.3*AU215 -> 45126.9 | BF215: =IFERROR(AZ215/L215,"-") -> 0.36674802 | BG215: =IFERROR(BA215/L215,"-") -> 0.63325198 | BH215: =IFERROR(BB215/M215,"-") -> 0.50210567 | BI215: =IFERROR(BC215/M215,"-") -> 0.74789433 | BJ215: =IFERROR(BD215/N215,"-") -> 0.28491678 | BK215: =IFERROR(BE215/N215,"-") -> 0.71508322 | BL215: 78080 | BM215: 61050 | BN215: =SUM(BL215:BM215) -> 139130
A216: =LEFT(F216,4)+1 -> 2025 | B216: =RIGHT(F216,2) -> 02 | C216: {=_xlfn.IFS(_xlfn.NUMBERVALUE(B216)<=13,"Q1",AND(_xlfn.NUMBERVALUE(B216)>13,_xlfn.NUMBERVALUE(B216)<=26),"Q2", AND(_xlfn.NUMBERVALUE(B216)>26,_xlfn.NUMBERVALUE(B216)<=39),"Q3",_xlfn.NUMBERVALUE(B216)>39,"Q4")} -> Q1 | D216: =E215+1 -> 45325 | E216: =D216+6 -> 45331 | F216: 202402 | G216: =SUM(H216:I216) -> 279995.7 | H216: =1.5 * (BB216+BD216) -> 115826.1 | I216: =1.5*(BC216+BE216) -> 164169.6 | J216: =IFERROR(H216/G216,0) -> 0.413671 | K216: =IFERROR(I216/G216,0) -> 0.586329 | L216: =AZ216+BA216 -> 93331.9 | M216: 102972 | N216: =BD216+BE216 -> 57948.8 | O216: =IFERROR(L216/$G216,0) -> 0.33333333 | P216: =IFERROR(M216/$G216,0) -> 0.36776279 | Q216: =IFERROR(N216/$G216,0) -> 0.20696318 | R216: =Forecast!J211 -> 229073 | S216: =Forecast!N211 -> 211723 | T216: =IF(OR(RIGHT(F216,2) = "01",G216 = 0),G216,T215+G216) -> 596379 | U216: =IF(RIGHT(F216,2)="01",R216,R216+U215) -> 457264 | V216: =IF(RIGHT(F216,2)="01",S216,S216+V215) -> 436293 | W216: =X216+Y216 -> 1282868 | X216: ='Channel & Campaign Metrics'!AR215 -> 1113117 | Y216: ='Channel & Campaign Metrics'!BS215 -> 169751 | Z216: =W216*0.6 -> 769720.8 | AA216: =W216*0.4 -> 513147.2 | AB216: ='Glass Metrics'!AC216 -> 137938 | AC216: ='Glass Metrics'!I216 -> 175543 | AD216: ='Glass Metrics'!N216 -> 150059 | AE216: ='Glass Metrics'!S216 -> 125118 | AF216: =IFERROR(AE216/AB216,"") -> 0.90705969 | AG216: =IFERROR(AC216/AE216,"") -> 1.4030195 | AH216: =IFERROR(AD216/AC216,"") -> 0.85482759 | AI216: =IFERROR(G216/AB216,"") -> 2.0298663 | AJ216: =IFERROR(((AK216*AM216)+(AL216*AN216))/(AM216+AN216),"") -> 0.28093825 | AK216: 0.07355883 | AL216: 0.51109625 | AM216: 81015 | AN216: 72997 | AO216: =AJ216 -> 0.28093825 | AQ216: 0.37695465 | AR216: 0.41456594 | AS216: =AP216 -> 0 | AT216: 15698 | AU216: =AV216-AT216 -> 28878 | AV216: ='Channel & Campaign Metrics'!Z215 -> 44576 | AW216: =BD216-AT216 -> 4709.4 | AX216: =BE216-AU216 -> 8663.4 | AY216: =SUM(AW216,AX216) -> 13372.8 | AZ216: =H216-(BB216+BD216) -> 38608.7 | BA216: =I216-(BC216+BE216) -> 54723.2 | BB216: 56810 | BC216: 71905 | BD216: =1.3*AT216 -> 20407.4 | BE216: =1.3*AU216 -> 37541.4 | BF216: =IFERROR(AZ216/L216,"-") -> 0.413671 | BG216: =IFERROR(BA216/L216,"-") -> 0.586329 | BH216: =IFERROR(BB216/M216,"-") -> 0.55170338 | BI216: =IFERROR(BC216/M216,"-") -> 0.69829662 | BJ216: =IFERROR(BD216/N216,"-") -> 0.3521626 | BK216: =IFERROR(BE216/N216,"-") -> 0.6478374 | BL216: 90449 | BM216: 69716 | BN216: =SUM(BL216:BM216) -> 160165
A217: =LEFT(F217,4)+1 -> 2025 | B217: =RIGHT(F217,2) -> 03 | C217: {=_xlfn.IFS(_xlfn.NUMBERVALUE(B217)<=13,"Q1",AND(_xlfn.NUMBERVALUE(B217)>13,_xlfn.NUMBERVALUE(B217)<=26),"Q2", AND(_xlfn.NUMBERVALUE(B217)>26,_xlfn.NUMBERVALUE(B217)<=39),"Q3",_xlfn.NUMBERVALUE(B217)>39,"Q4")} -> Q1 | D217: =E216+1 -> 45332 | E217: =D217+6 -> 45338 | F217: 202403 | G217: =SUM(H217:I217) -> 316588.5 | H217: =1.5 * (BB217+BD217) -> 153600.9 | I217: =1.5*(BC217+BE217) -> 162987.6 | J217: =IFERROR(H217/G217,0) -> 0.48517524 | K217: =IFERROR(I217/G217,0) -> 0.51482476 | L217: =AZ217+BA217 -> 105529.5 | M217: 117721 | N217: =BD217+BE217 -> 63908 | O217: =IFERROR(L217/$G217,0) -> 0.33333333 | P217: =IFERROR(M217/$G217,0) -> 0.37184231 | Q217: =IFERROR(N217/$G217,0) -> 0.20186457 | R217: =Forecast!J212 -> 237897 | S217: =Forecast!N212 -> 182163 | T217: =IF(OR(RIGHT(F217,2) = "01",G217 = 0),G217,T216+G217) -> 912967.5 | U217: =IF(RIGHT(F217,2)="01",R217,R217+U216) -> 695161 | V217: =IF(RIGHT(F217,2)="01",S217,S217+V216) -> 618456 | W217: =X217+Y217 -> 1257457 | X217: ='Channel & Campaign Metrics'!AR216 -> 1113908 | Y217: ='Channel & Campaign Metrics'!BS216 -> 143549 | Z217: =W217*0.6 -> 754474.2 | AA217: =W217*0.4 -> 502982.8 | AB217: ='Glass Metrics'!AC217 -> 177817 | AC217: ='Glass Metrics'!I217 -> 126648 | AD217: ='Glass Metrics'!N217 -> 150570 | AE217: ='Glass Metrics'!S217 -> 132358 | AF217: =IFERROR(AE217/AB217,"") -> 0.74434953 | AG217: =IFERROR(AC217/AE217,"") -> 0.95685943 | AH217: =IFERROR(AD217/AC217,"") -> 1.1888857 | AI217: =IFERROR(G217/AB217,"") -> 1.7804175 | AJ217: =IFERROR(((AK217*AM217)+(AL217*AN217))/(AM217+AN217),"") -> 0.73441115 | AK217: 0.83518602 | AL217: 0.65820585 | AM217: 75577 | AN217: 99944 | AO217: =AJ217 -> 0.73441115 | AQ217: 0.62847502 | AR217: 0.039045939 | AS217: =AP217 -> 0 | AT217: 15402 | AU217: =AV217-AT217 -> 33758 | AV217: ='Channel & Campaign Metrics'!Z216 -> 49160 | AW217: =BD217-AT217 -> 4620.6 | AX217: =BE217-AU217 -> 10127.4 | AY217: =SUM(AW217,AX217) -> 14748 | AZ217: =H217-(BB217+BD217) -> 51200.3 | BA217: =I217-(BC217+BE217) -> 54329.2 | BB217: 82378 | BC217: 64773 | BD217: =1.3*AT217 -> 20022.6 | BE217: =1.3*AU217 -> 43885.4 | BF217: =IFERROR(AZ217/L217,"-") -> 0.48517524 | BG217: =IFERROR(BA217/L217,"-") -> 0.51482476 | BH217: =IFERROR(BB217/M217,"-") -> 0.69977319 | BI217: =IFERROR(BC217/M217,"-") -> 0.55022468 | BJ217: =IFERROR(BD217/N217,"-") -> 0.3133035 | BK217: =IFERROR(BE217/N217,"-") -> 0.6866965 | BL217: 56282 | BM217: 98491 | BN217: =SUM(BL217:BM217) -> 154773
A218: =LEFT(F218,4)+1 -> 2025 | B218: =RIGHT(F218,2) -> 04 | C218: {=_xlfn.IFS(_xlfn.NUMBERVALUE(B218)<=13,"Q1",AND(_xlfn.NUMBERVALUE(B218)>13,_xlfn.NUMBERVALUE(B218)<=26),"Q2", AND(_xlfn.NUMBERVALUE(B218)>26,_xlfn.NUMBERVALUE(B218)<=39),"Q3",_xlfn.NUMBERVALUE(B218)>39,"Q4")} -> Q1 | D218: =E217+1 -> 45339 | E218: =D218+6 -> 45345 | F218: 202404 | G218: =SUM(H218:I218) -> 311843.25 | H218: =1.5 * (BB218+BD218) -> 134747.7 | I218: =1.5*(BC218+BE218) -> 177095.55 | J218: =IFERROR(H218/G218,0) -> 0.43210074 | K218: =IFERROR(I218/G218,0) -> 0.56789926 | L218: =AZ218+BA218 -> 103947.75 | M218: 107697 | N218: =BD218+BE218 -> 73274.5 | O218: =IFERROR(L218/$G218,0) -> 0.33333333 | P218: =IFERROR(M218/$G218,0) -> 0.3453562 | Q218: =IFERROR(N218/$G218,0) -> 0.23497222 | R218: =Forecast!J213 -> 222613 | S218: =Forecast!N213 -> 222373 | T218: =IF(OR(RIGHT(F218,2) = "01",G218 = 0),G218,T217+G218) -> 1224810.8 | U218: =IF(RIGHT(F218,2)="01",R218,R218+U217) -> 917774 | V218: =IF(RIGHT(F218,2)="01",S218,S218+V217) -> 840829 | W218: =X218+Y218 -> 1324507 | X218: ='Channel & Campaign Metrics'!AR217 -> 1170199 | Y218: ='Channel & Campaign Metrics'!BS217 -> 154308 | Z218: =W218*0.6 -> 794704.2 | AA218: =W218*0.4 -> 529802.8 | AB218: ='Glass Metrics'!AC218 -> 172517 | AC218: ='Glass Metrics'!I218 -> 177268 | AD218: ='Glass Metrics'!N218 -> 178210 | AE218: ='Glass Metrics'!S218 -> 141754 | AF218: =IFERROR(AE218/AB218,"") -> 0.82168134 | AG218: =IFERROR(AC218/AE218,"") -> 1.2505326 | AH218: =IFERROR(AD218/AC218,"") -> 1.005314 | AI218: =IFERROR(G218/AB218,"") -> 1.8076088 | AJ218: =IFERROR(((AK218*AM218)+(AL218*AN218))/(AM218+AN218),"") -> 0.35344773 | AK218: 0.84484131 | AL218: 0.07512063 | AM218: 55908 | AN218: 98707 | AO218: =AJ218 -> 0.35344773 | AQ218: 0.2235853 | AR218: 0.052864552 | AS218: =AP218 -> 0 | AT218: 15796 | AU218: =AV218-AT218 -> 40569 | AV218: ='Channel & Campaign Metrics'!Z217 -> 56365 | AW218: =BD218-AT218 -> 4738.8 | AX218: =BE218-AU218 -> 12170.7 | AY218: =SUM(AW218,AX218) -> 16909.5 | AZ218: =H218-(BB218+BD218) -> 44915.9 | BA218: =I218-(BC218+BE218) -> 59031.85 | BB218: 69297 | BC218: 65324 | BD218: =1.3*AT218 -> 20534.8 | BE218: =1.3*AU218 -> 52739.7 | BF218: =IFERROR(AZ218/L218,"-") -> 0.43210074 | BG218: =IFERROR(BA218/L218,"-") -> 0.56789926 | BH218: =IFERROR(BB218/M218,"-") -> 0.64344411 | BI218: =IFERROR(BC218/M218,"-") -> 0.60655357 | BJ218: =IFERROR(BD218/N218,"-") -> 0.28024483 | BK218: =IFERROR(BE218/N218,"-") -> 0.71975517 | BL218: 99926 | BM218: 91538 | BN218: =SUM(BL218:BM218) -> 191464
A219: =LEFT(F219,4)+1 -> 2025 | B219: =RIGHT(F219,2) -> 05 | C219: {=_xlfn.IFS(_xlfn.NUMBERVALUE(B219)<=13,"Q1",AND(_xlfn.NUMBERVALUE(B219)>13,_xlfn.NUMBERVALUE(B219)<=26),"Q2", AND(_xlfn.NUMBERVALUE(B219)>26,_xlfn.NUMBERVALUE(B219)<=39),"Q3",_xlfn.NUMBERVALUE(B219)>39,"Q4")} -> Q1 | D219: =E218+1 -> 45346 | E219: =D219+6 -> 45352 | F219: 202405 | G219: =SUM(H219:I219) -> 355742.7 | H219: =1.5 * (BB219+BD219) -> 169375.8 | I219: =1.5*(BC219+BE219) -> 186366.9 | J219: =IFERROR(H219/G219,0) -> 0.47611884 | K219: =IFERROR(I219/G219,0) -> 0.52388116 | L219: =AZ219+BA219 -> 118580.9 | M219: 143786 | N219: =BD219+BE219 -> 57428.8 | O219: =IFERROR(L219/$G219,0) -> 0.33333333 | P219: =IFERROR(M219/$G219,0) -> 0.40418538 | Q219: =IFERROR(N219/$G219,0) -> 0.16143353 | R219: =Forecast!J214 -> 218486 | S219: =Forecast!N214 -> 212210 | T219: =IF(OR(RIGHT(F219,2) = "01",G219 = 0),G219,T218+G219) -> 1580553.4 | U219: =IF(RIGHT(F219,2)="01",R219,R219+U218) -> 1136260 | V219: =IF(RIGHT(F219,2)="01",S219,S219+V218) -> 1053039 | W219: =X219+Y219 -> 1192964 | X219: ='Channel & Campaign Metrics'!AR218 -> 1059925 | Y219: ='Channel & Campaign Metrics'!BS218 -> 133039 | Z219: =W219*0.6 -> 715778.4 | AA219: =W219*0.4 -> 477185.6 | AB219: ='Glass Metrics'!AC219 -> 142350 | AC219: ='Glass Metrics'!I219 -> 159301 | AD219: ='Glass Metrics'!N219 -> 124672 | AE219: ='Glass Metrics'!S219 -> 168522 | AF219: =IFERROR(AE219/AB219,"") -> 1.1838567 | AG219: =IFERROR(AC219/AE219,"") -> 0.94528311 | AH219: =IFERROR(AD219/AC219,"") -> 0.78261907 | AI219: =IFERROR(G219/AB219,"") -> 2.4990706 | AJ219: =IFERROR(((AK219*AM219)+(AL219*AN219))/(AM219+AN219),"") -> 0.74713762 | AK219: 0.95089646 | AL219: 0.55838035 | AM219: 51928 | AN219: 56055 | AO219: =AJ219 -> 0.74713762 | AQ219: 0.074359178 | AR219: 0.30702618 | AS219: =AP219 -> 0 | AT219: 10794 | AU219: =AV219-AT219 -> 33382 | AV219: ='Channel & Campaign Metrics'!Z218 -> 44176 | AW219: =BD219-AT219 -> 3238.2 | AX219: =BE219-AU219 -> 10014.6 | AY219: =SUM(AW219,AX219) -> 13252.8 | AZ219: =H219-(BB219+BD219) -> 56458.6 | BA219: =I219-(BC219+BE219) -> 62122.3 | BB219: 98885 | BC219: 80848 | BD219: =1.3*AT219 -> 14032.2 | BE219: =1.3*AU219 -> 43396.6 | BF219: =IFERROR(AZ219/L219,"-") -> 0.47611884 | BG219: =IFERROR(BA219/L219,"-") -> 0.52388116 | BH219: =IFERROR(BB219/M219,"-") -> 0.68772342 | BI219: =IFERROR(BC219/M219,"-") -> 0.56228006 | BJ219: =IFERROR(BD219/N219,"-") -> 0.24434082 | BK219: =IFERROR(BE219/N219,"-") -> 0.75565918 | BL219: 55457 | BM219: 90084 | BN219: =SUM(BL219:BM219) -> 145541
A220: =LEFT(F220,4)+1 -> 2025 | B220: =RIGHT(F220,2) -> 06 | C220: {=_xlfn.IFS(_xlfn.NUMBERVALUE(B220)<=13,"Q1",AND(_xlfn.NUMBERVALUE(B220)>13,_xlfn.NUMBERVALUE(B220)<=26),"Q2", AND(_xlfn.NUMBERVALUE(B220)>26,_xlfn.NUMBERVALUE(B220)<=39),"Q3",_xlfn.NUMBERVALUE(B220)>39,"Q4")} -> Q1 | D220: =E219+1 -> 45353 | E220: =D220+6 -> 45359 | F220: 202406 | G220: =SUM(H220:I220) -> 316070.1 | H220: =1.5 * (BB220+BD220) -> 137173.35 | I220: =1.5*(BC220+BE220) -> 178896.75 | J220: =IFERROR(H220/G220,0) -> 0.4339966 | K220: =IFERROR(I220/G220,0) -> 0.5660034 | L220: =AZ220+BA220 -> 105356.7 | M220: 110874 | N220: =BD220+BE220 -> 72121.4 | O220: =IFERROR(L220/$G220,0) -> 0.33333333 | P220: =IFERROR(M220/$G220,0) -> 0.35078927 | Q220: =IFERROR(N220/$G220,0) -> 0.22818166 | R220: =Forecast!J215 -> 236668 | S220: =Forecast!N215 -> 226991 | T220: =IF(OR(RIGHT(F220,2) = "01",G220 = 0),G220,T219+G220) -> 1896623.5 | U220: =IF(RIGHT(F220,2)="01",R220,R220+U219) -> 1372928 | V220: =IF(RIGHT(F220,2)="01",S220,S220+V219) -> 1280030 | W220: =X220+Y220 -> 1431018 | X220: ='Channel & Campaign Metrics'!AR219 -> 1308152 | Y220: ='Channel & Campaign Metrics'!BS219 -> 122866 | Z220: =W220*0.6 -> 858610.8 | AA220: =W220*0.4 -> 572407.2 | AB220: ='Glass Metrics'!AC220 -> 142626 | AC220: ='Glass Metrics'!I220 -> 143088 | AD220: ='Glass Metrics'!N220 -> 137107 | AE220: ='Glass Metrics'!S220 -> 150311 | AF220: =IFERROR(AE220/AB220,"") -> 1.0538822 | AG220: =IFERROR(AC220/AE220,"") -> 0.9519463 | AH220: =IFERROR(AD220/AC220,"") -> 0.95820055 | AI220: =IFERROR(G220/AB220,"") -> 2.2160763 | AJ220: =IFERROR(((AK220*AM220)+(AL220*AN220))/(AM220+AN220),"") -> 0.79190726 | AK220: 0.72382471 | AL220: 0.86640693 | AM220: 63063 | AN220: 57631 | AO220: =AJ220 -> 0.79190726 | AQ220: 0.07435452 | AR220: 0.14403638 | AS220: =AP220 -> 0 | AT220: 10133 | AU220: =AV220-AT220 -> 45345 | AV220: ='Channel & Campaign Metrics'!Z219 -> 55478 | AW220: =BD220-AT220 -> 3039.9 | AX220: =BE220-AU220 -> 13603.5 | AY220: =SUM(AW220,AX220) -> 16643.4 | AZ220: =H220-(BB220+BD220) -> 45724.45 | BA220: =I220-(BC220+BE220) -> 59632.25 | BB220: 78276 | BC220: 60316 | BD220: =1.3*AT220 -> 13172.9 | BE220: =1.3*AU220 -> 58948.5 | BF220: =IFERROR(AZ220/L220,"-") -> 0.4339966 | BG220: =IFERROR(BA220/L220,"-") -> 0.5660034 | BH220: =IFERROR(BB220/M220,"-") -> 0.70599058 | BI220: =IFERROR(BC220/M220,"-") -> 0.54400491 | BJ220: =IFERROR(BD220/N220,"-") -> 0.18264898 | BK220: =IFERROR(BE220/N220,"-") -> 0.81735102 | BL220: 75350 | BM220: 61365 | BN220: =SUM(BL220:BM220) -> 136715
A221: =LEFT(F221,4)+1 -> 2025 | B221: =RIGHT(F221,2) -> 07 | C221: {=_xlfn.IFS(_xlfn.NUMBERVALUE(B221)<=13,"Q1",AND(_xlfn.NUMBERVALUE(B221)>13,_xlfn.NUMBERVALUE(B221)<=26),"Q2", AND(_xlfn.NUMBERVALUE(B221)>26,_xlfn.NUMBERVALUE(B221)<=39),"Q3",_xlfn.NUMBERVALUE(B221)>39,"Q4")} -> Q1 | D221: =E220+1 -> 45360 | E221: =D221+6 -> 45366 | F221: 202407 | G221: =SUM(H221:I221) -> 449592.9 | H221: =1.5 * (BB221+BD221) -> 130811.4 | I221: =1.5*(BC221+BE221) -> 318781.5 | J221: =IFERROR(H221/G221,0) -> 0.29095522 | K221: =IFERROR(I221/G221,0) -> 0.70904478 | L221: =AZ221+BA221 -> 149864.3 | M221: 105184 | N221: 73500 | O221: =IFERROR(L221/$G221,0) -> 0.33333333 | P221: =IFERROR(M221/$G221,0) -> 0.23395387 | Q221: =IFERROR(N221/$G221,0) -> 0.16348123 | R221: =Forecast!J216 -> 199457 | S221: =Forecast!N216 -> 232534 | T221: =IF(OR(RIGHT(F221,2) = "01",G221 = 0),G221,T220+G221) -> 2346216.4 | U221: =IF(RIGHT(F221,2)="01",R221,R221+U220) -> 1572385 | V221: =IF(RIGHT(F221,2)="01",S221,S221+V220) -> 1512564 | W221: =X221+Y221 -> 1342947 | X221: ='Channel & Campaign Metrics'!AR220 -> 1168236 | Y221: ='Channel & Campaign Metrics'!BS220 -> 174711 | Z221: =W221*0.6 -> 805768.2 | AA221: =W221*0.4 -> 537178.8 | AB221: ='Glass Metrics'!AC221 -> 158838 | AC221: ='Glass Metrics'!I221 -> 141639 | AD221: ='Glass Metrics'!N221 -> 148426 | AE221: ='Glass Metrics'!S221 -> 189422 | AF221: =IFERROR(AE221/AB221,"") -> 1.1925484 | AG221: =IFERROR(AC221/AE221,"") -> 0.74774313 | AH221: =IFERROR(AD221/AC221,"") -> 1.0479176 | AI221: =IFERROR(G221/AB221,"") -> 2.8305122 | AJ221: =IFERROR(((AK221*AM221)+(AL221*AN221))/(AM221+AN221),"") -> 0.59452577 | AK221: 0.83511448 | AL221: 0.35777705 | AM221: 64736 | AN221: 65786 | AO221: =AJ221 -> 0.59452577 | AQ221: 0.012336989 | AR221: 0.93866513 | AS221: =AP221 -> 0 | AT221: 13262 | AU221: =AV221-AT221 -> 116160 | AV221: ='Channel & Campaign Metrics'!Z220 -> 129422 | AW221: =BD221-AT221 -> 3978.6 | AX221: =BE221-AU221 -> 34848 | AY221: =SUM(AW221,AX221) -> 38826.6 | AZ221: =H221-(BB221+BD221) -> 43603.8 | BA221: =I221-(BC221+BE221) -> 106260.5 | BB221: 69967 | BC221: 61513 | BD221: =1.3*AT221 -> 17240.6 | BE221: =1.3*AU221 -> 151008 | BF221: =IFERROR(AZ221/L221,"-") -> 0.29095522 | BG221: =IFERROR(BA221/L221,"-") -> 0.70904478 | BH221: =IFERROR(BB221/M221,"-") -> 0.66518672 | BI221: =IFERROR(BC221/M221,"-") -> 0.58481328 | BJ221: =IFERROR(BD221/N221,"-") -> 0.23456599 | BK221: =IFERROR(BE221/N221,"-") -> 2.0545306 | BL221: 99926 | BM221: 91538 | BN221: =SUM(BL221:BM221) -> 191464
A222: =LEFT(F222,4)+1 -> 2025 | B222: =RIGHT(F222,2) -> 08 | C222: {=_xlfn.IFS(_xlfn.NUMBERVALUE(B222)<=13,"Q1",AND(_xlfn.NUMBERVALUE(B222)>13,_xlfn.NUMBERVALUE(B222)<=26),"Q2", AND(_xlfn.NUMBERVALUE(B222)>26,_xlfn.NUMBERVALUE(B222)<=39),"Q3",_xlfn.NUMBERVALUE(B222)>39,"Q4")} -> Q1 | D222: =E221+1 -> 45367 | E222: =D222+6 -> 45373 | F222: 202408 | G222: =SUM(H222:I222) -> 406108.95 | H222: =1.5 * (BB222+BD222) -> 186214.5 | I222: =1.5*(BC222+BE222) -> 219894.45 | J222: =IFERROR(H222/G222,0) -> 0.45853336 | K222: =IFERROR(I222/G222,0) -> 0.54146664 | L222: =AZ222+BA222 -> 135369.65 | M222: 156239 | N222: =BD222+BE222 -> 75440.3 | O222: =IFERROR(L222/$G222,0) -> 0.33333333 | P222: =IFERROR(M222/$G222,0) -> 0.38472188 | Q222: =IFERROR(N222/$G222,0) -> 0.1857637 | R222: =Forecast!J217 -> 208460 | S222: =Forecast!N217 -> 234841 | T222: =IF(OR(RIGHT(F222,2) = "01",G222 = 0),G222,T221+G222) -> 2752325.4 | U222: =IF(RIGHT(F222,2)="01",R222,R222+U221) -> 1780845 | V222: =IF(RIGHT(F222,2)="01",S222,S222+V221) -> 1747405 | W222: =X222+Y222 -> 1299500 | X222: ='Channel & Campaign Metrics'!AR221 -> 1149238 | Y222: ='Channel & Campaign Metrics'!BS221 -> 150262 | Z222: =W222*0.6 -> 779700 | AA222: =W222*0.4 -> 519800 | AB222: ='Glass Metrics'!AC222 -> 136223 | AC222: ='Glass Metrics'!I222 -> 171093 | AD222: ='Glass Metrics'!N222 -> 163071 | AE222: ='Glass Metrics'!S222 -> 128778 | AF222: =IFERROR(AE222/AB222,"") -> 0.94534697 | AG222: =IFERROR(AC222/AE222,"") -> 1.3285887 | AH222: =IFERROR(AD222/AC222,"") -> 0.95311322 | AI222: =IFERROR(G222/AB222,"") -> 2.9812069 | AJ222: =IFERROR(((AK222*AM222)+(AL222*AN222))/(AM222+AN222),"") -> 0.47312403 | AK222: 0.55280444 | AL222: 0.41309413 | AM222: 67244 | AN222: 89256 | AO222: =AJ222 -> 0.47312403 | AQ222: 0.32990222 | AR222: 0.50325521 | AS222: =AP222 -> 0 | AT222: 18620 | AU222: =AV222-AT222 -> 39411 | AV222: ='Channel & Campaign Metrics'!Z221 -> 58031 | AW222: =BD222-AT222 -> 5586 | AX222: =BE222-AU222 -> 11823.3 | AY222: =SUM(AW222,AX222) -> 17409.3 | AZ222: =H222-(BB222+BD222) -> 62071.5 | BA222: =I222-(BC222+BE222) -> 73298.15 | BB222: 99937 | BC222: 95362 | BD222: =1.3*AT222 -> 24206 | BE222: =1.3*AU222 -> 51234.3 | BF222: =IFERROR(AZ222/L222,"-") -> 0.45853336 | BG222: =IFERROR(BA222/L222,"-") -> 0.54146664 | BH222: =IFERROR(BB222/M222,"-") -> 0.63964183 | BI222: =IFERROR(BC222/M222,"-") -> 0.61035977 | BJ222: =IFERROR(BD222/N222,"-") -> 0.32086299 | BK222: =IFERROR(BE222/N222,"-") -> 0.67913701 | BL222: 85378 | BM222: 79609 | BN222: =SUM(BL222:BM222) -> 164987
A223: =LEFT(F223,4)+1 -> 2025 | B223: =RIGHT(F223,2) -> 09 | C223: {=_xlfn.IFS(_xlfn.NUMBERVALUE(B223)<=13,"Q1",AND(_xlfn.NUMBERVALUE(B223)>13,_xlfn.NUMBERVALUE(B223)<=26),"Q2", AND(_xlfn.NUMBERVALUE(B223)>26,_xlfn.NUMBERVALUE(B223)<=39),"Q3",_xlfn.NUMBERVALUE(B223)>39,"Q4")} -> Q1 | D223: =E222+1 -> 45374 | E223: =D223+6 -> 45380 | F223: 202409 | G223: =SUM(H223:I223) -> 319021.5 | H223: =1.5 * (BB223+BD223) -> 142881.6 | I223: =1.5*(BC223+BE223) -> 176139.9 | J223: =IFERROR(H223/G223,0) -> 0.44787452 | K223: =IFERROR(I223/G223,0) -> 0.55212548 | L223: =AZ223+BA223 -> 106340.5 | M223: 114266 | N223: =BD223+BE223 -> 69849 | O223: =IFERROR(L223/$G223,0) -> 0.33333333 | P223: =IFERROR(M223/$G223,0) -> 0.35817649 | Q223: =IFERROR(N223/$G223,0) -> 0.21894763 | R223: =Forecast!J218 -> 200645 | S223: =Forecast!N218 -> 274152 | T223: =IF(OR(RIGHT(F223,2) = "01",G223 = 0),G223,T222+G223) -> 3071346.9 | U223: =IF(RIGHT(F223,2)="01",R223,R223+U222) -> 1981490 | V223: =IF(RIGHT(F223,2)="01",S223,S223+V222) -> 2021557 | W223: =X223+Y223 -> 1312239 | X223: ='Channel & Campaign Metrics'!AR222 -> 1137761 | Y223: ='Channel & Campaign Metrics'!BS222 -> 174478 | Z223: =W223*0.6 -> 787343.4 | AA223: =W223*0.4 -> 524895.6 | AB223: ='Glass Metrics'!AC223 -> 154285 | AC223: ='Glass Metrics'!I223 -> 141601 | AD223: ='Glass Metrics'!N223 -> 172747 | AE223: ='Glass Metrics'!S223 -> 163863 | AF223: =IFERROR(AE223/AB223,"") -> 1.0620799 | AG223: =IFERROR(AC223/AE223,"") -> 0.86414261 | AH223: =IFERROR(AD223/AC223,"") -> 1.2199561 | AI223: =IFERROR(G223/AB223,"") -> 2.0677415 | AJ223: =IFERROR(((AK223*AM223)+(AL223*AN223))/(AM223+AN223),"") -> 0.45213033 | AK223: 0.57078678 | AL223: 0.32467564 | AM223: 61712 | AN223: 57452 | AO223: =AJ223 -> 0.45213033 | AQ223: 0.6398255 | AR223: 0.10858912 | AS223: =AP223 -> 0 | AT223: 13178 | AU223: =AV223-AT223 -> 40552 | AV223: ='Channel & Campaign Metrics'!Z222 -> 53730 | AW223: =BD223-AT223 -> 3953.4 | AX223: =BE223-AU223 -> 12165.6 | AY223: =SUM(AW223,AX223) -> 16119 | AZ223: =H223-(BB223+BD223) -> 47627.2 | BA223: =I223-(BC223+BE223) -> 58713.3 | BB223: 78123 | BC223: 64709 | BD223: =1.3*AT223 -> 17131.4 | BE223: =1.3*AU223 -> 52717.6 | BF223: =IFERROR(AZ223/L223,"-") -> 0.44787452 | BG223: =IFERROR(BA223/L223,"-") -> 0.55212548 | BH223: =IFERROR(BB223/M223,"-") -> 0.68369419 | BI223: =IFERROR(BC223/M223,"-") -> 0.56630144 | BJ223: =IFERROR(BD223/N223,"-") -> 0.24526335 | BK223: =IFERROR(BE223/N223,"-") -> 0.75473665 | BL223: 76593 | BM223: 88728 | BN223: =SUM(BL223:BM223) -> 165321
A224: =LEFT(F224,4)+1 -> 2025 | B224: =RIGHT(F224,2) -> 10 | C224: {=_xlfn.IFS(_xlfn.NUMBERVALUE(B224)<=13,"Q1",AND(_xlfn.NUMBERVALUE(B224)>13,_xlfn.NUMBERVALUE(B224)<=26),"Q2", AND(_xlfn.NUMBERVALUE(B224)>26,_xlfn.NUMBERVALUE(B224)<=39),"Q3",_xlfn.NUMBERVALUE(B224)>39,"Q4")} -> Q1 | D224: =E223+1 -> 45381 | E224: =D224+6 -> 45387 | F224: 202410 | G224: =SUM(H224:I224) -> 279022.65 | H224: =1.5 * (BB224+BD224) -> 105235.05 | I224: =1.5*(BC224+BE224) -> 173787.6 | J224: =IFERROR(H224/G224,0) -> 0.37715594 | K224: =IFERROR(I224/G224,0) -> 0.62284406 | L224: =AZ224+BA224 -> 93007.55 | M224: 97585 | N224: =BD224+BE224 -> 64034.1 | O224: =IFERROR(L224/$G224,0) -> 0.33333333 | P224: =IFERROR(M224/$G224,0) -> 0.34973863 | Q224: =IFERROR(N224/$G224,0) -> 0.22949427 | R224: =Forecast!J219 -> 222125 | S224: =Forecast!N219 -> 198083 | T224: =IF(OR(RIGHT(F224,2) = "01",G224 = 0),G224,T223+G224) -> 3350369.5 | U224: =IF(RIGHT(F224,2)="01",R224,R224+U223) -> 2203615 | V224: =IF(RIGHT(F224,2)="01",S224,S224+V223) -> 2219640 | W224: =X224+Y224 -> 1346601 | X224: ='Channel & Campaign Metrics'!AR223 -> 1205129 | Y224: ='Channel & Campaign Metrics'!BS223 -> 141472 | Z224: =W224*0.6 -> 807960.6 | AA224: =W224*0.4 -> 538640.4 | AB224: ='Glass Metrics'!AC224 -> 167588 | AC224: ='Glass Metrics'!I224 -> 197650 | AD224: ='Glass Metrics'!N224 -> 165908 | AE224: ='Glass Metrics'!S224 -> 170830 | AF224: =IFERROR(AE224/AB224,"") -> 1.0193451 | AG224: =IFERROR(AC224/AE224,"") -> 1.1569982 | AH224: =IFERROR(AD224/AC224,"") -> 0.83940299 | AI224: =IFERROR(G224/AB224,"") -> 1.6649322 | AJ224: =IFERROR(((AK224*AM224)+(AL224*AN224))/(AM224+AN224),"") -> 0.64925784 | AK224: 0.7370927 | AL224: 0.5689669 | AM224: 89530 | AN224: 97942 | AO224: =AJ224 -> 0.64925784 | AQ224: 0.047442427 | AR224: 0.22624669 | AS224: =AP224 -> 0 | AT224: 14209 | AU224: =AV224-AT224 -> 35048 | AV224: ='Channel & Campaign Metrics'!Z223 -> 49257 | AW224: =BD224-AT224 -> 4262.7 | AX224: =BE224-AU224 -> 10514.4 | AY224: =SUM(AW224,AX224) -> 14777.1 | AZ224: =H224-(BB224+BD224) -> 35078.35 | BA224: =I224-(BC224+BE224) -> 57929.2 | BB224: 51685 | BC224: 70296 | BD224: =1.3*AT224 -> 18471.7 | BE224: =1.3*AU224 -> 45562.4 | BF224: =IFERROR(AZ224/L224,"-") -> 0.37715594 | BG224: =IFERROR(BA224/L224,"-") -> 0.62284406 | BH224: =IFERROR(BB224/M224,"-") -> 0.52964083 | BI224: =IFERROR(BC224/M224,"-") -> 0.72035661 | BJ224: =IFERROR(BD224/N224,"-") -> 0.28846661 | BK224: =IFERROR(BE224/N224,"-") -> 0.71153339 | BL224: 92417 | BM224: 98720 | BN224: =SUM(BL224:BM224) -> 191137
A225: =LEFT(F225,4)+1 -> 2025 | B225: =RIGHT(F225,2) -> 11 | C225: {=_xlfn.IFS(_xlfn.NUMBERVALUE(B225)<=13,"Q1",AND(_xlfn.NUMBERVALUE(B225)>13,_xlfn.NUMBERVALUE(B225)<=26),"Q2", AND(_xlfn.NUMBERVALUE(B225)>26,_xlfn.NUMBERVALUE(B225)<=39),"Q3",_xlfn.NUMBERVALUE(B225)>39,"Q4")} -> Q1 | D225: =E224+1 -> 45388 | E225: =D225+6 -> 45394 | F225: 202411 | G225: =SUM(H225:I225) -> 386364.45 | H225: =1.5 * (BB225+BD225) -> 181619.25 | I225: =1.5*(BC225+BE225) -> 204745.2 | J225: =IFERROR(H225/G225,0) -> 0.47007236 | K225: =IFERROR(I225/G225,0) -> 0.52992764 | L225: =AZ225+BA225 -> 128788.15 | M225: 152344 | N225: =BD225+BE225 -> 67146.3 | O225: =IFERROR(L225/$G225,0) -> 0.33333333 | P225: =IFERROR(M225/$G225,0) -> 0.39430129 | Q225: =IFERROR(N225/$G225,0) -> 0.17379006 | R225: =Forecast!J220 -> 223498 | S225: =Forecast!N220 -> 209451 | T225: =IF(OR(RIGHT(F225,2) = "01",G225 = 0),G225,T224+G225) -> 3736734 | U225: =IF(RIGHT(F225,2)="01",R225,R225+U224) -> 2427113 | V225: =IF(RIGHT(F225,2)="01",S225,S225+V224) -> 2429091 | W225: =X225+Y225 -> 1314716 | X225: ='Channel & Campaign Metrics'!AR224 -> 1132304 | Y225: ='Channel & Campaign Metrics'!BS224 -> 182412 | Z225: =W225*0.6 -> 788829.6 | AA225: =W225*0.4 -> 525886.4 | AB225: ='Glass Metrics'!AC225 -> 123542 | AC225: ='Glass Metrics'!I225 -> 177246 | AD225: ='Glass Metrics'!N225 -> 151690 | AE225: ='Glass Metrics'!S225 -> 134225 | AF225: =IFERROR(AE225/AB225,"") -> 1.0864726 | AG225: =IFERROR(AC225/AE225,"") -> 1.3205141 | AH225: =IFERROR(AD225/AC225,"") -> 0.85581621 | AI225: =IFERROR(G225/AB225,"") -> 3.1273935 | AJ225: =IFERROR(((AK225*AM225)+(AL225*AN225))/(AM225+AN225),"") -> 0.60755644 | AK225: 0.3223349 | AL225: 0.85878607 | AM225: 53229 | AN225: 60431 | AO225: =AJ225 -> 0.60755644 | AQ225: 0.82907039 | AR225: 0.84642512 | AS225: =AP225 -> 0 | AT225: 18375 | AU225: =AV225-AT225 -> 33276 | AV225: ='Channel & Campaign Metrics'!Z224 -> 51651 | AW225: =BD225-AT225 -> 5512.5 | AX225: =BE225-AU225 -> 9982.8 | AY225: =SUM(AW225,AX225) -> 15495.3 | AZ225: =H225-(BB225+BD225) -> 60539.75 | BA225: =I225-(BC225+BE225) -> 68248.4 | BB225: 97192 | BC225: 93238 | BD225: =1.3*AT225 -> 23887.5 | BE225: =1.3*AU225 -> 43258.8 | BF225: =IFERROR(AZ225/L225,"-") -> 0.47007236 | BG225: =IFERROR(BA225/L225,"-") -> 0.52992764 | BH225: =IFERROR(BB225/M225,"-") -> 0.63797721 | BI225: =IFERROR(BC225/M225,"-") -> 0.61202279 | BJ225: =IFERROR(BD225/N225,"-") -> 0.35575303 | BK225: =IFERROR(BE225/N225,"-") -> 0.64424697 | BL225: 56757 | BM225: 56557 | BN225: =SUM(BL225:BM225) -> 113314
...

Sheet Channel & Campaign Metrics
